Workbook

Sheet HEINEKEN
A1: DT | B1: REMESSA | C1: DATA | D1: PL | E1: Peso | F1: Frete | G1: Canal | H1: Cliente | I1: CNPJ Destinatário | J1: Origem | K1: Cidade | L1: UF | M1: Frota / Placa | N1: Tarifa OTM | O1: Margem CF | P1: Valor CF | Q1: OC | R1: Romaneio | S1: Status | T1: Monitoramento (SM) | U1: DT/Hora Chegada Coleta | V1: Saída Coleta | W1: Tempo de Permanência | X1: Agenda Descarga | Y1: DT/ Hora Chegada no Cliente | Z1: Data/Hora Descarga | AA1: Tempo de Permanência | AB1: OC Galileu / Shipsy | AC1: Motivo | AD1: Valor | AE1: Baixa Galileu / Shipsy | AF1: Upload de cahotos
A2: 10064649 | C2: 45293 | D2: 26 | E2: 31625 | F2: TE01 | G2: DTB | H2: COMPAR RIO BRANCO-AC | I2: 04.928.297/0020-73 | J2: PONTA GROSSA | K2: RIO BRANCO | L2: AC | M2: AWB3J16 / MFR2D98 | N2: 35374.19 | O2: =IFERROR(P2/N2,0) -> 0.76326836 | P2: 27000 | Q2: OK | R2: 1248852 | S2: CARREGADO | T2: 4731490 | Y2: 09/01/2024 08:33 | Z2: 09/01 18:25 | AE2: OK
A3: 10070792 | C3: 45293 | D3: 26 | E3: 32553 | F3: TE02 | G3: TRF | H3: CDA CURITIBA-PR | I3: 50.221.019/0083-82 | J3: PONTA GROSSA | K3: CURITIBA | L3: PR | M3: A18000 | N3: 2336.24 | O3: =IFERROR(P3/N3,0) -> 0.64205732 | P3: 1500 | Q3: OK | R3: 1248704 | S3: CARREGADO | T3: 4730568 | Y3: 04/01/2024 6:41 | Z3: 04/01 13:30 | AE3: OK
A4: 10070793 | C4: 45293 | D4: - | E4: - | F4: TE02 | G4: TRF | H4: (RETORNO TE02) CDA CURITIBA-PR | I4: 50.221.019/0083-82 | J4: CURITIBA | K4: PONTA GROSSA | L4: PR | M4: A18000 | N4: 1557.49 | O4: =IFERROR(P4/N4,0) -> 0.44944109 | P4: 700 | R4: 1249431 | S4: CARREGADO | T4: 4734222 | Y4: 05/01/2024 23:56 | Z4: 05/01 23:56 | AE4: OK
A5: 10083900 | C5: 45296.833 | D5: 26 | E5: 32647 | F5: TE01 | G5: DTB | H5: SPAL JOINVILLE-SC | I5: 61.186.888/0175-92 | J5: PONTA GROSSA | K5: JOINVILLE | L5: SC | M5: A18000 | N5: 3587.66 | O5: =IFERROR(P5/N5,0) -> 0.66895971 | P5: 2400 | Q5: OK | R5: 1250023 | S5: CARREGADO | T5: 4737234 | Y5: 09/01 08:57 | Z5: 09/01 08:57 | AE5: OK
A6: 10085050 | C6: 45294 | D6: 26 | E6: 31625 | F6: TE01 | G6: DTB | H6: CDA BLUMENAU-SC | I6: 50.221.019/0077-34 | J6: PONTA GROSSA | K6: BLUMENAU | L6: SC | M6: A54730 | N6: 4696.34 | O6: =IFERROR(P6/N6,0) -> 0.68138167 | P6: 3200 | Q6: OK | R6: 1248860 | S6: CARREGADO | T6: 4731554 | Y6: 04/01 09:18 | Z6: 04/01 09:18 | AE6: OK
A7: 10086808 | C7: 45299.667 | D7: 26 | E7: 31647 | F7: TE01 | G7: DTB | H7: SPAL ANTÔNIO CARLOS-SC | I7: 61.186.888/0176-73 | J7: PONTA GROSSA | K7: ANTONIO CARLOS | L7: SC | M7: A54920 | N7: 4445.42 | O7: =IFERROR(P7/N7,0) -> 0.6999991 | P7: 3111.79 | Q7: OK | R7: 1251657 | S7: CARREGADO | T7: 4744497 | Y7: 10/01 07:54 | Z7: 10/01 11:35 | AE7: OK
A8: 10086825 | C8: 45296.583 | D8: 26 | E8: 31647 | F8: TE01 | G8: DTB | H8: SPAL ANTÔNIO CARLOS-SC | I8: 61.186.888/0176-73 | J8: PONTA GROSSA | K8: ANTONIO CARLOS | L8: SC | M8: A54730 | N8: 4445.42 | O8: =IFERROR(P8/N8,0) -> 0.6999991 | P8: 3111.79 | Q8: OK | R8: 1250012 | S8: CARREGADO | T8: 4737183 | Y8: 06/01 17:31 | Z8: 09/01 10:25 | AE8: OK
A9: 10103146 | C9: 45306.875 | D9: 26 | E9: 31625 | F9: TE01 | G9: ASD | H9: ASUN GRAVATAÍ-RS | I9: 92.091.891/0001-57 | J9: PONTA GROSSA | K9: GRAVATAÍ | L9: RS | M9: A18000 | N9: 9203.69 | O9: =IFERROR(P9/N9,0) -> 0.54326037 | P9: 5000 | Q9: OK | R9: 1255065 | S9: CARREGADO | T9: 4762159 | Y9: 16/01 13:36 | Z9: 19/01 12:18 | AE9: OK
A10: 10120665 | C10: 45313.542 | D10: 26 | E10: 33069 | F10: TE01 | G10: DTB | H10: COMPAR RIO BRANCO-AC | I10: 04.928.297/0020-73 | J10: PONTA GROSSA | K10: RIO BRANCO | L10: AC | M10: AWB3J16 / MFR2D98 | N10: 32898 | O10: =IFERROR(P10/N10,0) -> 0.85111557 | P10: 28000 | Q10: OK | R10: 1259245 | S10: CARREGADO | T10: 4784522 | Y10: 30/01 10:00 | Z10: 30/01 16:00 | AE10: OK
A11: 10120977 | C11: 45311.458 | D11: 26 | E11: 32647 | F11: TE01 | G11: DTB | H11: SPAL JOINVILLE-SC | I11: 61.186.888/0175-92 | J11: PONTA GROSSA | K11: JOINVILLE | L11: SC | M11: A55160 | N11: 3587.66 | O11: =IFERROR(P11/N11,0) -> 0.66895971 | P11: 2400 | Q11: OK | R11: 1258507 | S11: CARREGADO | T11: 4782100 | Y11: 21/01 16:14 | Z11: 22/01 07:42 | AE11: OK
A12: 10123614 | C12: 45313.333 | D12: 26 | E12: 32647 | F12: TE01 | G12: DTB | H12: SPAL ANTÔNIO CARLOS -SC | I12: 61.186.888/0176-73 | J12: PONTA GROSSA | K12: ANTONIO CARLOS | L12: SC | M12: A54920 | N12: 4445.42 | O12: =IFERROR(P12/N12,0) -> 0.67485187 | P12: 3000 | Q12: OK | R12: 1259251 | S12: CARREGADO | T12: 4784537 | Y12: 24/01 15:45 | Z12: 24/01 18:41 | AE12: OK
A13: 10123615 | C13: 45313.333 | D13: 26 | E13: 32647 | F13: TE01 | G13: DTB | H13: SPAL ANTÔNIO CARLOS -SC | I13: 61.186.888/0176-73 | J13: PONTA GROSSA | K13: ANTONIO CARLOS | L13: SC | M13: A18000 | N13: 4445.42 | O13: =IFERROR(P13/N13,0) -> 0.6999991 | P13: 3111.79 | Q13: OK | R13: 1259152 | S13: CARREGADO | T13: 4784032 | Y13: 24/01 22:33 | Z13: 25/01 10:16 | AE13: OK
A14: 10141197 | C14: 45318.833 | D14: 26 | E14: 32553 | F14: TE02 | G14: DTB | H14: DBK SÃO JOSÉ DO RIO PRETO-SP | I14: 14.886.581/0001-15 | J14: PONTA GROSSA | K14: SÃO JOSÉ DO RIO PRETO | L14: SP | M14: A55160 | N14: 6085.8 | O14: =IFERROR(P14/N14,0) -> 0.73942621 | P14: 4500 | Q14: OK | R14: 1262201 | S14: CARREGADO | T14: 4802275 | Y14: 28/01 16:06 | Z14: 29/01 15:58 | AE14: OK
A15: 10141198 | C15: 45318.833 | D15: 25 | E15: 30278 | F15: TE01 | G15: ASD | H15: ASUN GRAVATAÍ-RS | I15: 92.091.891/0001-57 | J15: PONTA GROSSA | K15: GRAVATAÍ | L15: RS | M15: A18000 | N15: 9203.69 | O15: =IFERROR(P15/N15,0) -> 0.54326037 | P15: 5000 | Q15: OK | R15: 1262200 | S15: CARREGADO | T15: 4802274 | Y15: 29/01 19:33 | Z15: 06/02 08:36 | AA15: 7 dias | AB15: OK | AC15: DIÁRIA | AD15: 2450 | AE15: OK
A16: 10141199 | C16: 45318.833 | D16: - | E16: - | F16: TE02 | G16: DTB | H16: (RETORNO TE02) DBK SÃO JOSÉ DO RIO PRETO-SP | I16: 14.886.581/0001-15 | J16: SÃO JOSÉ DO RIO PRETO | K16: PONTA GROSSA | L16: PR | M16: A55160 | N16: 4057.2 | O16: =IFERROR(P16/N16,0) -> 0.73942621 | P16: 3000 | R16: 1263554 | S16: CARREGADO | T16: 4807467 | Y16: 30/01 22:23 | Z16: 31/01 00:08 | AE16: OK
A17: 10152226 | C17: 45323.417 | D17: 26 | E17: 33139 | F17: TE02 | G17: TRF | H17: HNK SÃO JOSÉ-SC | I17: 50.221.019/0076-53 | J17: PONTA GROSSA | K17: SÃO JOSÉ | L17: SC | M17: A55160 | N17: 5305 | O17: =IFERROR(P17/N17,0) -> 0.56550424 | P17: 3000 | Q17: OK | R17: 1265449 | S17: CARREGADO | T17: 4818839 | Y17: 45327.36 | Z17: 45327.478 | AE17: OK
A18: 10154687 | C18: 45323.833 | D18: 26 | E18: 32553 | F18: TE02 | G18: TRF | H18: CDA CURITIBA-PR | I18: 50.221.019/0083-82 | J18: PONTA GROSSA | K18: CURITIBA | L18: PR CAP. | M18: A54730 | N18: 2336.24 | O18: =IFERROR(P18/N18,0) -> 0.64205732 | P18: 1500 | Q18: OK | R18: 1265383 | S18: CARREGADO | T18: 4818348 | Y18: 45323.357 | Z18: 45323.453 | AE18: OK
A19: 10154698 | C19: 45324.375 | D19: - | E19: - | F19: TE02 | G19: TRF | H19: (RETORNO TE02) CDA CURITIBA-PR | I19: 50.221.019/0083-82 | J19: CURITIBA | K19: PONTA GROSSA | L19: TE02 PR | M19: A54730 | N19: 1557.5 | O19: =IFERROR(P19/N19,0) -> 0.4494382 | P19: 700 | R19: 1265532 | S19: CARREGADO | T19: 4819599 | Y19: 45324.05 | Z19: 45324.113 | AE19: OK
A20: 10166462 | C20: 45327.625 | D20: 26 | E20: 32249 | F20: TE01 | G20: DTB | H20: LAGO AZUL MARÍLIA-SP | I20: 58.844.424/0002-01 | J20: PONTA GROSSA | K20: MARÍLIA | L20: SP INT. | M20: A56430 | N20: 4325 | O20: =IFERROR(P20/N20,0) -> 0.69364162 | P20: 3000 | Q20: OK | R20: 1267501 | S20: CARREGADO | T20: 4828032 | Y20: 45327.881 | Z20: 45328.514 | AE20: OK
A21: 10170659 | C21: 45327.208 | D21: 26 | E21: 32553 | F21: TE02 | G21: TRF | H21: CDA CURITIBA-PR | I21: 50.221.019/0083-82 | J21: PONTA GROSSA | K21: CURITIBA | L21: PR CAP. | M21: A54730 | N21: 2336.24 | O21: =IFERROR(P21/N21,0) -> 0.64205732 | P21: 1500 | Q21: OK | R21: 1267506 | S21: CARREGADO | T21: 4828109 | Y21: 45327.673 | Z21: 45327.758 | AE21: OK
A22: 10170660 | C22: 45329.625 | D22: - | E22: - | F22: TE02 | G22: TRF | H22: (RETORNO TE02) CDA CURITIBA-PR | I22: 50.221.019/0083-82 | J22: CURITIBA | K22: PONTA GROSSA | L22: TE02 PR | M22: A54730 | N22: 1557.5 | O22: =IFERROR(P22/N22,0) -> 0.4494382 | P22: 700 | R22: 1268167 | S22: CARREGADO | T22: 4831936 | Y22: 45329.018 | Z22: 45329.062 | AE22: OK
A23: 10171561 | C23: 45325.667 | D23: 26 | E23: 32553 | F23: TE02 | G23: TRF | H23: HNK SÃO JOSÉ-SC | I23: 05.254.957/0038-70 | J23: PONTA GROSSA | K23: SÃO JOSÉ | L23: SC | M23: A55650 | N23: 4717.8 | O23: =IFERROR(P23/N23,0) -> 0.63588961 | P23: 3000 | Q23: OK | R23: 1266780 | S23: CARREGADO | T23: 4826244 | Y23: 45327.456 | Z23: 45327.593 | AE23: OK
A24: 10171562 | C24: 45325.625 | D24: 26 | E24: 32553 | F24: TE02 | G24: TRF | H24: HNK SÃO JOSÉ-SC | I24: 50.221.019/0076-53 | J24: PONTA GROSSA | K24: SÃO JOSÉ | L24: SC | M24: A57390 | N24: 4717.8 | O24: =IFERROR(P24/N24,0) -> 0.63588961 | P24: 3000 | Q24: OK | R24: 1266592 | S24: CARREGADO | T24: 4825303 | Y24: 45327.516 | Z24: 45327.672 | AE24: OK
A25: 10171563 | C25: 45329.625 | D25: - | E25: - | F25: TE02 | G25: TRF | H25: (RETORNO TE02) HNK SÃO JOSÉ-SC | I25: 05.254.957/0038-70 | J25: SÃO JOSÉ | K25: PONTA GROSSA | L25: TE02 SC | M25: A55650 | N25: 3145.2 | O25: =IFERROR(P25/N25,0) -> 0.57230065 | P25: 1800 | R25: 1267748 | S25: CARREGADO | T25: 4829638 | Y25: 45328.693 | Z25: 45329.294 | AE25: OK
A26: 10171564 | C26: 45327 | D26: - | E26: - | F26: TE02 | G26: TRF | H26: (RETORNO TE02) HNK SÃO JOSÉ-SC | I26: 50.221.019/0076-53 | J26: SÃO JOSÉ | K26: PONTA GROSSA | L26: TE02 SC | M26: A57390 | N26: 3145.2 | O26: =IFERROR(P26/N26,0) -> 0.57230065 | P26: 1800 | R26: 1267768 | S26: CARREGADO | T26: 4829764 | Y26: 45328.836 | Z26: 45328.89 | AE26: OK
A27: 10175824 | C27: 45329.417 | D27: 26 | E27: 32647 | F27: TE01 | G27: DTB | H27: SPAL JOINVILLE-SC | I27: 61.186.888/0175-92 | J27: PONTA GROSSA | K27: JOINVILLE | L27: SC | M27: A54730 | N27: 3157.14 | O27: =IFERROR(P27/N27,0) -> 0.76018168 | P27: 2400 | Q27: OK | R27: 1268842 | S27: CARREGADO | T27: 4836594 | U27: 0.41666667 | V27: 0.63541667 | W27: 0.21875 | X27: 08/02 08H | Y27: 45329.908 | Z27: 45330.253 | AE27: OK
A28: 10175897 | C28: 45329.458 | D28: 28 | E28: 34058 | F28: TE01 | G28: DTB | H28: LAGO AZUL REGENTE FEIJÓ-SP | I28: 58.844.424/0003-84 | J28: PONTA GROSSA | K28: REGENTE FEIJÓ | L28: SP INT. | M28: A55650 | N28: 5004.48 | O28: =IFERROR(P28/N28,0) -> 0.69937336 | P28: 3500 | Q28: OK | R28: 1268845 | S28: CARREGADO | T28: 4836610 | U28: 0.49583333 | V28: 0.625 | W28: 0.12916667 | X28: ORDEM | Y28: 45331.289 | Z28: 45331.431 | AE28: OK
A29: 10177845 | C29: 45328.708 | D29: 26 | E29: 31022 | F29: TE01 | G29: DTB | H29: CDA CURITIBA-PR | I29: 50.221.019/0083-82 | J29: PONTA GROSSA | K29: CURITIBA | L29: PR CAP. | M29: A56620 | N29: 2336.24 | O29: =IFERROR(P29/N29,0) -> 0.64205732 | P29: 1500 | Q29: OK | R29: 1268348 | S29: CARREGADO | T29: 4833087 | U29: 0.59652778 | V29: 0.81875 | W29: 0.22222222 | X29: ORDEM | Y29: 45330.436 | Z29: 45330.686 | AB29: OK | AC29: FALTA DE VASILHAME TE02 | AE29: OK
A30: 10177846 | C30: 45328.708 | D30: - | E30: - | F30: TE01 | G30: DTB | H30: (RETORNO TE02) CDA CURITIBA-PR | I30: 50.221.019/0083-82 | J30: CURITIBA | K30: PONTA GROSSA | L30: - | N30: 1446.19 | R30: - | S30: CANCELADA | T30: -
A31: 10178014 | C31: 45327 | D31: - | E31: - | F31: TE02 | G31: TRF | H31: (RETORNO TE02) HNK SÃO JOSÉ-SC | I31: 05.254.957/0038-70 | J31: SÃO JOSÉ | K31: PONTA GROSSA | L31: TE02 SC | M31: A55160 | N31: 3183 | O31: =IFERROR(P31/N31,0) -> 0.56550424 | P31: 1800 | R31: 1267587 | S31: CARREGADO | T31: 4828633 | Y31: 45329.023 | Z31: 45329.065 | AE31: OK
A32: 10178794 | C32: 45329.75 | D32: 26 | E32: 32647 | F32: TE01 | G32: DTB | H32: SPAL SÃO JOSÉ DO RIO PRETO-SP | I32: 61.186.888/0146-58 | J32: PONTA GROSSA | K32: SÃO JOSÉ DO RIO PRETO | L32: SP INT. | M32: A55160 | N32: 5991 | O32: =IFERROR(P32/N32,0) -> 0.75112669 | P32: 4500 | Q32: OK | R32: 1268851 | S32: CARREGADO | T32: 4836654 | U32: 0.45833333 | V32: 0.56944444 | W32: 0.11111111 | X32: 09/02 10H | Y32: 45331.36 | Z32: 45331.442 | AE32: OK
A33: 10179281 | C33: 45329.542 | D33: 26 | E33: 31922 | F33: TE01 | G33: TRF | H33: CDA ITU-SP | I33: 50.221.019/0047-19 | J33: PONTA GROSSA | K33: ITU | L33: SP | M33: A54920 | N33: 5174 | O33: =IFERROR(P33/N33,0) -> 0.77309625 | P33: 4000 | Q33: OK | R33: 1268490 | S33: CARREGADO | T33: 4834195 | U33: 0.14583333 | V33: 0.25 | W33: 0.10416667 | X33: ORDEM | Y33: 45330.303 | Z33: 45330.517 | AE33: OK
A34: 10179591 | C34: 45328.583 | D34: 26 | E34: 31922 | F34: TE01 | G34: TRF | H34: CDA CAÇAPAVA-SP | I34: 50.221.019/0084-63 | J34: PONTA GROSSA | K34: CAÇAPAVA | L34: SP | M34: A55660 | N34: 7880.37 | O34: =IFERROR(P34/N34,0) -> 0.69793677 | P34: 5500 | Q34: OK | R34: 1268453 | S34: CARREGADO | T34: 4833841 | U34: 0.63888889 | V34: 0.75 | W34: 0.11111111 | X34: ORDEM | Y34: 45330.847 | Z34: 45331.552 | AE34: OK
A35: 10179593 | C35: 45334.417 | D35: 26 | E35: 31922 | F35: TE01 | G35: TRF | H35: CDA CAÇAPAVA-SP | I35: 50.221.019/0084-63 | J35: PONTA GROSSA | K35: CAÇAPAVA | L35: SP | M35: A47130 | N35: 7880.37 | O35: =IFERROR(P35/N35,0) -> 0.69793677 | P35: 5500 | Q35: OK | R35: 1271867 | S35: CARREGADO | T35: 4851850 | U35: 0.74583333 | V35: 0.95208333 | X35: ORDEM | Y35: 45336.511 | Z35: 45336.678 | AE35: OK
A36: 10179594 | C36: 45334.417 | D36: 26 | E36: 31922 | F36: TE01 | G36: TRF | H36: CDA CAÇAPAVA-SP | I36: 50.221.019/0084-63 | J36: PONTA GROSSA | K36: CAÇAPAVA | L36: SP | M36: A56750 | N36: 7880.37 | O36: =IFERROR(P36/N36,0) -> 0.69793677 | P36: 5500 | Q36: OK | R36: 1271562 | S36: CARREGADO | T36: 4850447 | U36: 0.41805556 | V36: 0.61388889 | X36: ORDEM | Y36: 45335.725 | Z36: 45336.65 | AE36: OK
A37: 10181317 | C37: 45328.125 | D37: 26 | E37: 30740 | F37: TE02 | G37: TRF | H37: HNK SÃO JOSÉ-SC | I37: 50.221.019/0076-53 | J37: PONTA GROSSA | K37: SÃO JOSÉ | L37: SC | M37: A55640 | N37: 5053 | O37: =IFERROR(P37/N37,0) -> 0.59370671 | P37: 3000 | Q37: OK | R37: 1268471 | S37: CARREGADO | T37: 4834010 | U37: 0.69027778 | V37: 0.79166667 | W37: 0.10694444 | X37: ORDEM | Y37: 45329.622 | Z37: 45329.744 | AE37: OK
A38: 10181318 | C38: 45328.208 | D38: 26 | E38: 30740 | F38: TE02 | G38: TRF | H38: HNK SÃO JOSÉ-SC | I38: 50.221.019/0076-53 | J38: PONTA GROSSA | K38: SÃO JOSÉ | L38: SC | M38: A57130 | N38: 5053 | O38: =IFERROR(P38/N38,0) -> 0.59370671 | P38: 3000 | Q38: OK | R38: 1268567 | S38: CARREGADO | T38: 4834811 | U38: 0.61597222 | V38: 0.75 | W38: 0.19930556 | X38: ORDEM | Y38: 45330.333 | Z38: 45330.526 | AE38: OK
A39: 10185742 | C39: 45335.708 | D39: 28 | E39: 34058 | F39: TE01 | G39: DTB | H39: LAGO AZUL MARÍLIA-SP LUSITANA | I39: 58.844.424/0002-01 | J39: PONTA GROSSA | K39: MARÍLIA | L39: SP INT. | M39: A57860 | N39: 4325 | O39: =IFERROR(P39/N39,0) -> 0.69364162 | P39: 3000 | Q39: OK | R39: 1272225 | S39: CARREGADO | T39: 4852868 | U39: 0.52083333 | V39: 0.70694444 | X39: ORDEM | Y39: 45336.765 | Z39: 45336.777 | AE39: OK
A40: 10185743 | C40: 45335.708 | D40: 26 | E40: 30200 | F40: TE01 | G40: TRF | H40: CDA CURITIBA-PR | I40: 50.221.019/0083-82 | J40: PONTA GROSSA | K40: CURITIBA | L40: PR CAP. | M40: A54920 | N40: 2169.28 | O40: =IFERROR(P40/N40,0) -> 0.69147367 | P40: 1500 | Q40: OK | R40: 1272209 | S40: CARREGADO | T40: 4852798 | U40: 0.33333333 | V40: 0.55902778 | X40: ORDEM | Y40: 45336.244 | Z40: 45336.375 | AE40: OK
A41: 10185747 | C41: 45335.708 | D41: - | E41: - | F41: TE01 | G41: TRF | H41: (RETORNO TE02) CDA CURITIBA-PR | I41: 50.221.019/0083-82 | J41: CURITIBA | K41: PONTA GROSSA | L41: - | N41: 1446.19 | S41: CANCELADA | X41: ORDEM
A42: 10186437 | C42: 45332.083 | D42: 26 | E42: 33139 | F42: TE01 | G42: TRF | H42: CDA CURITIBA-PR | I42: 50.221.019/0083-82 | J42: PONTA GROSSA | K42: CURITIBA | L42: - | N42: 2340.76 | S42: CANCELADA
A43: 10186448 | C43: 45336.25 | D43: 26 | E43: 33139 | F43: TE02 | G43: TRF | H43: CDA CURITIBA-PR | I43: 50.221.019/0083-82 | J43: PONTA GROSSA | K43: CURITIBA | L43: PR CAP. | M43: A57390 | N43: 2340.76 | O43: =IFERROR(P43/N43,0) -> 0.64081751 | P43: 1500 | Q43: OK | R43: 1272472 | S43: CARREGADO | T43: 4853683 | U43: 0 | V43: 0.088194444 | X43: ORDEM | Y43: 45336.381 | Z43: 45336.657 | AE43: OK
A44: 10186449 | C44: 45332.083 | D44: 26 | E44: 33139 | F44: TE01 | G44: TRF | H44: CDA CURITIBA-PR | I44: 50.221.019/0083-82 | J44: PONTA GROSSA | K44: CURITIBA | L44: - | N44: 2340.76 | S44: CANCELADA
A45: 10186450 | C45: 45330.083 | D45: 26 | E45: 33139 | F45: TE01 | G45: TRF | H45: CDA CURITIBA-PR | I45: 50.221.019/0083-82 | J45: PONTA GROSSA | K45: CURITIBA | L45: PR CAP. | M45: A56620 | N45: 2340.76 | O45: =IFERROR(P45/N45,0) -> 0.64081751 | P45: 1500 | Q45: OK | R45: 1269536 | S45: CARREGADO | T45: 4840951 | U45: 0.44444444 | V45: 0.61180556 | X45: ORDEM | Y45: 45330.758 | Z45: 45330.801 | AE45: OK
A46: 10186451 | C46: 45332.583 | D46: 26 | E46: 33139 | F46: TE01 | G46: TRF | H46: CDA CURITIBA-PR | I46: 50.221.019/0083-82 | J46: PONTA GROSSA | K46: CURITIBA | L46: - | N46: 2340.76 | S46: CANCELADA
A47: 10186452 | C47: 45330.042 | D47: 26 | E47: 33139 | F47: TE01 | G47: TRF | H47: CDA CURITIBA-PR | I47: 50.221.019/0083-82 | J47: PONTA GROSSA | K47: CURITIBA | L47: PR CAP. | M47: A47130 | N47: 2340.76 | O47: =IFERROR(P47/N47,0) -> 0.64081751 | P47: 1500 | Q47: OK | R47: 1269601 | S47: CARREGADO | T47: 4841318 | U47: 0.6125 | V47: 0.71388889 | X47: ORDEM | Y47: 45331.354 | Z47: 45331.603 | AE47: OK
A48: 10186453 | C48: 45330.042 | D48: 26 | E48: 33139 | F48: TE01 | G48: TRF | H48: CDA CURITIBA-PR | I48: 50.221.019/0083-82 | J48: PONTA GROSSA | K48: CURITIBA | L48: PR CAP. | M48: A57390 | N48: 2340.76 | O48: =IFERROR(P48/N48,0) -> 0.64081751 | P48: 1500 | Q48: OK | R48: 1269588 | S48: CARREGADO | T48: 4841250 | U48: 0.43958333 | V48: 0.56597222 | X48: ORDEM | Y48: 45330.666 | Z48: 45330.706 | AE48: OK
A49: 10186454 | C49: 45330.083 | D49: 26 | E49: 33139 | F49: TE01 | G49: TRF | H49: CDA CURITIBA-PR | I49: 50.221.019/0083-82 | J49: PONTA GROSSA | K49: CURITIBA | L49: PR CAP. | M49: A54980 | N49: 2340.76 | O49: =IFERROR(P49/N49,0) -> 0.64081751 | P49: 1500 | Q49: OK | R49: 1269747 | S49: CARREGADO | T49: 4842536 | U49: 0.73611111 | V49: 0.97430556 | X49: ORDEM | Y49: 45331.399 | Z49: 45331.442 | AE49: OK
A50: 10186455 | C50: 45330.042 | D50: 26 | E50: 33139 | F50: TE01 | G50: TRF | H50: CDA CURITIBA-PR | I50: 50.221.019/0083-82 | J50: PONTA GROSSA | K50: CURITIBA | L50: PR CAP. | M50: A56360 | N50: 2340.76 | O50: =IFERROR(P50/N50,0) -> 0.64081751 | P50: 1500 | Q50: OK | R50: 1269589 | S50: CARREGADO | T50: 4841253 | U50: 0.64583333 | V50: 0.76319444 | X50: ORDEM | Y50: 45331.415 | Z50: 45331.501 | AE50: OK
A51: 10186456 | C51: 45330.083 | D51: 26 | E51: 29591 | F51: TE01 | G51: TRF | H51: CDA CURITIBA-PR | I51: 50.221.019/0083-82 | J51: PONTA GROSSA | K51: CURITIBA | L51: PR CAP. | M51: A57380 | N51: 2169.28 | O51: =IFERROR(P51/N51,0) -> 0.69147367 | P51: 1500 | Q51: OK | R51: 1269549 | S51: CARREGADO | T51: 4841031 | U51: 0.66388889 | V51: 0.89375 | X51: ORDEM | Y51: 45331.479 | Z51: 45331.681 | AB51: OK | AC51: FALTA DE VASILHAMES TE02 | AE51: OK
A52: 10186457 | C52: 45330.708 | D52: - | E52: - | F52: TE01 | G52: TRF | H52: (RETORNO TE02) CDA CURITIBA-PR | I52: 50.221.019/0083-82 | J52: CURITIBA | K52: PONTA GROSSA | L52: - | N52: 1446.19 | S52: CANCELADA | X52: ORDEM
A53: 10186468 | C53: 45332.125 | D53: 26 | E53: 33139 | F53: TE01 | G53: TRF | H53: CDA CURITIBA-PR | I53: 50.221.019/0083-82 | J53: PONTA GROSSA | K53: CURITIBA | L53: - | N53: 2340.76 | S53: CANCELADA
A54: 10187244 | C54: 45331.833 | D54: 26 | E54: 31625 | F54: TE01 | G54: ASD | H54: IMPORTADORA E EXPORTADORA DE CEREAIS LAJEADO-RS | I54: 91.156.471/0001-49 | J54: PONTA GROSSA | K54: LAJEADO | L54: RS | M54: A54980 | N54: 6808 | O54: =IFERROR(P54/N54,0) -> 0.80787309 | P54: 5500 | Q54: OK | R54: 1270148 | S54: CARREGADO | T54: 4844941 | U54: 0.65277778 | V54: 0.94444444 | X54: 12/02 06H | Y54: 45335.25 | Z54: 45336.708 | AE54: OK
A55: 10187246 | C55: 45331.875 | D55: 26 | E55: 31625 | F55: TE01 | G55: ASD | H55: IMPORTADORA E EXPORTADORA DE CEREAIS LAJEADO-RS | I55: 91.156.471/0001-49 | J55: PONTA GROSSA | K55: LAJEADO | L55: RS | M55: A55620 | N55: 6808 | O55: =IFERROR(P55/N55,0) -> 0.80787309 | P55: 5500 | Q55: OK | R55: 1270300 | S55: CARREGADO | T55: 4846249 | U55: 0.77708333 | V55: 0.43055556 | X55: 12/02 06H | Y55: 45333.735 | Z55: 45334.308 | AE55: OK
A56: 10187276 | C56: 45335.833 | D56: 26 | E56: 31462 | F56: TE02 | G56: TRF | H56: HNK SÃO JOSÉ-SC | I56: 50.221.019/0076-53 | J56: PONTA GROSSA | K56: SÃO JOSÉ | L56: SC | M56: A56430 | N56: 4324 | O56: =IFERROR(P56/N56,0) -> 0.69380204 | P56: 3000 | Q56: OK | R56: 1272207 | S56: CARREGADO | T56: 4852792 | U56: 0.19236111 | V56: 0.29166667 | X56: ORDEM | Y56: 45335.699 | Z56: 45336.374 | AE56: OK
A57: 10187277 | C57: 45341.625 | D57: - | E57: - | F57: TE02 | G57: TRF | H57: (RETORNO TE02) HNK SÃO JOSÉ-SC | I57: 50.221.019/0076-53 | J57: SÃO JOSÉ | K57: PONTA GROSSA | L57: TE02 SC | M57: A56430 | N57: 2883.2 | O57: =IFERROR(P57/N57,0) -> 0.62430633 | P57: 1800 | R57: 1272862 | S57: CARREGADO | T57: 4855100 | X57: ORDEM | Y57: 45341.322 | Z57: 45341.437 | AE57: OK
A58: 10187504 | C58: 45329.625 | D58: - | E58: - | F58: TE02 | G58: TRF | H58: (RETORNO TE02) HNK SÃO JOSÉ-SC | I58: 05.254.957/0038-70 | J58: SÃO JOSÉ | K58: PONTA GROSSA | L58: TE02 SC | M58: A55640 | N58: 3031.8 | O58: =IFERROR(P58/N58,0) -> 0.59370671 | P58: 1800 | R58: 1269436 | S58: CARREGADO | T58: 4840214 | Y58: 45336.751 | Z58: 45337.417 | AE58: OK
A59: 10190402 | C59: 45336.417 | D59: 26 | E59: 32647 | F59: TE01 | G59: DTB | H59: SPAL ANTÔNIO CARLOS -SC | I59: 61.186.888/0176-73 | J59: PONTA GROSSA | K59: ANTONIO CARLOS | L59: SC | M59: A55630 | N59: 4445.42 | O59: =IFERROR(P59/N59,0) -> 0.67485187 | P59: 3000 | Q59: OK | R59: 1272834 | S59: CARREGADO | T59: 4854830 | U59: 0.0048611111 | V59: 0.1375 | X59: 16/02 09H | Y59: 45336.722 | Z59: 45338.447 | AE59: OK
A60: 10190406 | C60: 45336.833 | D60: 28 | E60: 34058 | F60: TE01 | G60: DTB | H60: LAGO AZUL MARÍLIA-SP LUSITANA | I60: 58.844.424/0002-01 | J60: PONTA GROSSA | K60: MARÍLIA | L60: - | N60: 4900 | S60: RETIRADA | X60: ORDEM
A61: 10190534 | C61: 45336.75 | D61: 26 | E61: 31625 | F61: TE01 | G61: TRF | H61: CDA ITU-SP | I61: 50.221.019/0047-19 | J61: PONTA GROSSA | K61: ITU | L61: SP | M61: A56620 | N61: 5174 | O61: =IFERROR(P61/N61,0) -> 0.77309625 | P61: 4000 | Q61: OK | R61: 1272898 | S61: CARREGADO | T61: 4855408 | U61: 0.76041667 | V61: 0.88194444 | X61: ORDEM | Y61: 45337.594 | Z61: 45338.21 | AE61: OK
A62: 10190535 | C62: 45336.75 | D62: 26 | E62: 31625 | F62: TE01 | G62: TRF | H62: CDA ITU-SP | I62: 50.221.019/0047-19 | J62: PONTA GROSSA | K62: ITU | L62: SP | M62: A54920 | N62: 5174 | O62: =IFERROR(P62/N62,0) -> 0.77309625 | P62: 4000 | Q62: OK | R62: 1272851 | S62: CARREGADO | T62: 4855009 | U62: 0.52083333 | V62: 0.69444444 | X62: ORDEM | Y62: 45337.593 | Z62: 45337.75 | AE62: OK
A63: 10190536 | C63: 45336.75 | D63: 26 | E63: 32647 | F63: TE01 | G63: DTB | H63: SPAL SÃO JOSÉ DO RIO PRETO-SP | I63: 61.186.888/0146-58 | J63: PONTA GROSSA | K63: SÃO JOSÉ DO RIO PRETO | L63: SP INT. | M63: A56540 | N63: 5991 | O63: =IFERROR(P63/N63,0) -> 0.75112669 | P63: 4500 | Q63: OK | R63: 1273043 | S63: CARREGADO | T63: 4856400 | U63: 0.77708333 | V63: 0.92638889 | X63: 16/02 10H | Y63: 45338.407 | Z63: 45338.61 | AE63: OK
A64: 10190538 | C64: 45329.625 | D64: - | E64: - | F64: TE02 | G64: TRF | H64: (RETORNO TE02) HNK SÃO JOSÉ-SC | I64: 05.254.957/0038-70 | J64: SÃO JOSÉ | K64: PONTA GROSSA | L64: TE02 SC | M64: A57130 | N64: 3031.8 | O64: =IFERROR(P64/N64,0) -> 0.59370671 | P64: 1800 | R64: 1269582 | S64: CARREGADO | T64: 4841207
A65: 10190751 | C65: 45336.833 | D65: 26 | E65: 31865 | F65: TE01 | G65: TRF | H65: CDA CAÇAPAVA-SP | I65: 50.221.019/0084-63 | J65: PONTA GROSSA | K65: CAÇAPAVA | L65: SP | M65: A57390 | N65: 7880.37 | O65: =IFERROR($P$77/N65,0) -> 0.57103918 | P65: 5500 | Q65: OK | R65: 1273331 | S65: CARREGADO | T65: 4857955 | U65: 0.875 | V65: 0.125 | X65: ORDEM | Y65: 45338.646 | Z65: 45338.706 | AE65: OK
A66: 10191284 | C66: 45334.75 | D66: 26 | E66: 32553 | F66: TE02 | G66: DTB | H66: DBK SÃO JOSÉ DO RIO PRETO-SP | I66: 14.886.581/0001-15 | J66: PONTA GROSSA | K66: SÃO JOSÉ DO RIO PRETO | L66: SP INT. | M66: A55890 | N66: 6085.8 | O66: =IFERROR(P66/N66,0) -> 0.73942621 | P66: 4500 | Q66: OK | R66: 1271896 | S66: CARREGADO | T66: 4851968 | U66: 0.65972222 | V66: 0 | X66: ORDEM | Y66: 45336.676 | Z66: 45337.348 | AE66: OK
A67: 10191285 | C67: 45339.625 | D67: - | E67: - | F67: TE02 | G67: DTB | H67: (RETORNO TE02) DBK SÃO JOSÉ DO RIO PRETO-SP | I67: 14.886.581/0001-15 | J67: SÃO JOSÉ DO RIO PRETO | K67: PONTA GROSSA | L67: TE02 | M67: A55890 | N67: 4057.2 | O67: =IFERROR(P67/N67,0) -> 0.73942621 | P67: 3000 | R67: 1273801 | S67: CARREGADO | T67: 4860643 | X67: ORDEM | Y67: 45338.605 | Z67: 45339.069 | AE67: OK
A68: 10191747 | C68: 45335.75 | D68: 26 | E68: 32553 | F68: TE02 | G68: DTB | H68: DBK SÃO JOSÉ DO RIO PRETO-SP LUSITANA | I68: 14.886.581/0001-15 | J68: PONTA GROSSA | K68: SÃO JOSÉ DO RIO PRETO | L68: SP INT. | M68: A55160 | N68: 6085.8 | O68: =IFERROR(P68/N68,0) -> 0.73942621 | P68: 4500 | Q68: OK | R68: 1272216 | S68: CARREGADO | T68: 4852815 | U68: 0.52013889 | V68: 0.68680556 | X68: ORDEM | Y68: 45337.451 | Z68: 45337.73 | AE68: OK
A69: 10191758 | C69: 45339.625 | D69: - | E69: - | F69: TE02 | G69: DTB | H69: (RETORNO TE02) DBK SÃO JOSÉ DO RIO PRETO-SP | I69: 14.886.581/0001-15 | J69: SÃO JOSÉ DO RIO PRETO | K69: PONTA GROSSA | L69: TE02 | M69: A55160 | N69: 4057.2 | O69: =IFERROR(P69/N69,0) -> 0.73942621 | P69: 3000 | R69: 1273799 | S69: CARREGADO | T69: 4860638 | X69: ORDEM | Y69: 45339.435 | Z69: 45339.81 | AE69: OK
A70: 10191772 | C70: 45334.667 | D70: 26 | E70: 31625 | F70: TE01 | G70: TRF | H70: CDA CURITIBA-PR | I70: 50.221.019/0083-82 | J70: PONTA GROSSA | K70: CURITIBA | L70: PR CAP. | M70: A57700 | N70: 2340.76 | O70: =IFERROR(P70/N70,0) -> 0.64081751 | P70: 1500 | Q70: OK | R70: 1271781 | S70: CARREGADO | T70: 4851462 | U70: 0.73958333 | V70: 0.34583333 | X70: ORDEM | Y70: 45336.432 | Z70: 45336.796 | AE70: OK
A71: 10191790 | C71: 45334.375 | D71: 26 | E71: 31625 | F71: TE01 | G71: TRF | H71: CDA CURITIBA-PR | I71: 50.221.019/0083-82 | J71: PONTA GROSSA | K71: CURITIBA | L71: PR CAP. | M71: A56620 | N71: 2173.57 | O71: =IFERROR(P71/N71,0) -> 0.6901089 | P71: 1500 | Q71: OK | R71: 1271554 | S71: CARREGADO | T71: 4850428 | U71: 0.40138889 | V71: 0.77361111 | X71: ORDEM | Y71: 45336.372 | Z71: 45336.597 | AE71: OK
A72: 10194099 | C72: 45337.708 | D72: 28 | E72: 34058 | F72: TE01 | G72: DTB | H72: LAGO AZUL REGENTE FEIJÓ LUSITANA | I72: 58.844.424/0003-84 | J72: PONTA GROSSA | K72: REGENTE FEIJÓ | L72: SP INT. | M72: A57980 | N72: 5004.48 | O72: =IFERROR(P72/N72,0) -> 0.7493286 | P72: 3750 | Q72: OK | R72: 1273588 | S72: CARREGADO | T72: 4858806 | U72: 0.25 | V72: 0.47916667 | X72: ORDEM | Y72: 45338.233 | Z72: 45338.374 | AE72: OK
A73: 10194100 | C73: 45337.708 | D73: 28 | E73: 34058 | F73: TE01 | G73: DTB | H73: LAGO AZUL REGENTE FEIJÓ LUSITANA | I73: 58.844.424/0003-84 | J73: PONTA GROSSA | K73: REGENTE FEIJÓ | L73: - | N73: 5930.61 | S73: RETIRADA
A74: 10195185 | C74: 45336.833 | D74: 26 | E74: 31625 | F74: TE01 | G74: DTB | H74: DBK SÃO JOSÉ DO RIO PRETO-SP | I74: 14.886.581/0001-15 | J74: PONTA GROSSA | K74: SÃO JOSÉ DO RIO PRETO | L74: - | N74: 7981.39 | S74: RETIRADA
A75: 10195663 | C75: 45337.708 | D75: 26 | E75: 31694 | F75: TE02 | G75: TRF | H75: CDA CAÇAPAVA-SP | I75: 50.221.019/0084-63 | J75: PONTA GROSSA | K75: CAÇAPAVA | L75: SP | M75: A57700 | N75: 7880.37 | O75: =IFERROR($P$77/N75,0) -> 0.57103918 | P75: 5500 | Q75: OK | R75: 1273833 | S75: CARREGADO | T75: 4860919 | U75: 0.87777778 | V75: 0.048611111 | X75: ORDEM | Y75: 45341.391 | Z75: 45341.765 | AE75: OK
A76: 10199322 | C76: 45338.833 | D76: 28 | E76: 34058 | F76: TE01 | G76: DTB | H76: LAGO AZUL MARÍLIA-SP | I76: 58.844.424/0002-01 | J76: PONTA GROSSA | K76: MARÍLIA | L76: SP INT. | M76: A58170 | N76: 4325 | O76: =IFERROR(P76/N76,0) -> 0.69364162 | P76: 3000 | Q76: OK | R76: 1274244 | S76: CARREGADO | T76: 4862863 | U76: 0.40277778 | V76: 0.54166667 | X76: ORDEM | Y76: 45339.31 | Z76: 45339.476 | AE76: OK
A77: 10200865 | C77: 45337.333 | D77: 26 | E77: 27955 | F77: TE02 | G77: DTB | H77: DBK SÃO JOSÉ DO RIO PRETO-SP | I77: 14.886.581/0001-15 | J77: PONTA GROSSA | K77: SÃO JOSÉ DO RIO PRETO | L77: SP INT. | M77: A54730 | N77: 5922.6 | O77: =IFERROR($P$78/N77,0) -> 0.50653429 | P77: 4500 | Q77: OK | R77: 1273678 | S77: CARREGADO | T77: 4859773 | U77: 0.53333333 | V77: 0.73888889 | X77: ORDEM | Y77: 45338.601 | Z77: 45338.788 | AE77: OK
A78: 10200866 | C78: 45339.625 | D78: - | E78: - | F78: TE02 | G78: DTB | H78: (RETORNO TE02) DBK SÃO JOSÉ DO RIO PRETO-SP | I78: 14.886.581/0001-15 | J78: SÃO JOSÉ DO RIO PRETO | K78: PONTA GROSSA | L78: TE02 | M78: A54730 | N78: 3948.4 | O78: =IFERROR($P$79/N78,0) -> 0.9497518 | P78: 3000 | R78: 1274558 | S78: CARREGADO | T78: 4864864 | X78: ORDEM
A79: 10202994 | C79: 45341.833 | D79: 26 | E79: 31625 | F79: TE01 | G79: DTB | H79: LAGO AZUL REGENTE FEIJÓ | I79: 58.844.424/0003-84 | J79: PONTA GROSSA | K79: REGENTE FEIJÓ | L79: SP INT. | M79: A55160 | N79: 5004.48 | O79: =IFERROR(P79/N79,0) -> 0.7493286 | P79: 3750 | Q79: OK | R79: 1275874 | S79: CARREGADO | T79: 4869840 | U79: 0.41180556 | V79: 0.49513889 | X79: ORDEM | Y79: 45342.567 | Z79: 45342.649 | AE79: OK
A80: 10204138 | C80: 45342.875 | D80: 28 | E80: 34058 | F80: TE01 | G80: DTB | H80: LAGO AZUL MARÍLIA-SP | I80: 58.844.424/0002-01 | J80: PONTA GROSSA | K80: MARÍLIA | L80: SP INT. | M80: A56370 | N80: 5004.48 | O80: =IFERROR(P80/N80,0) -> 0.69937336 | P80: 3500 | Q80: OK | R80: 1277194 | S80: CARREGADO | T80: 4878515 | U80: 0.44444444 | X80: ORDEM | Y80: 45344.785 | Z80: 45345.602 | AE80: OK
A81: 10204659 | C81: 45336.625 | D81: - | E81: - | F81: TE02 | G81: TRF | H81: (RETORNO TE02) CDA CURITIBA-PR | I81: 50.221.019/0083-82 | J81: CURITIBA | K81: PONTA GROSSA | L81: TE02 PR | M81: A57390 | N81: 1557.5 | O81: =IFERROR(P81/N81,0) -> 0.4494382 | P81: 700 | R81: 1273063 | S81: CARREGADO | T81: 4856594 | X81: ORDEM | Y81: 45336.781 | Z81: 45336.965 | AE81: OK
A82: 10204813 | C82: 45341.542 | D82: 26 | E82: 31625 | F82: TE01 | G82: TRF | H82: HNK SÃO JOSÉ-SC LUSITANA | I82: 50.221.019/0076-53 | J82: PONTA GROSSA | K82: SÃO JOSÉ | L82: SC | M82: A57390 | N82: 5053 | O82: =IFERROR(P82/N82,0) -> 0.59370671 | P82: 3000 | Q82: OK | R82: 1275900 | S82: CARREGADO | T82: 4870008 | U82: 0.40694444 | V82: 0.63263889 | X82: ORDEM | Y82: 45344.646 | Z82: 45344.722 | AE82: OK
A83: 10204814 | C83: 45339.625 | D83: 26 | E83: 31625 | F83: TE01 | G83: TRF | H83: HNK SÃO JOSÉ-SC | I83: 50.221.019/0076-53 | J83: PONTA GROSSA | K83: SÃO JOSÉ | L83: SC | M83: A55620 | N83: 5053 | O83: =IFERROR(P83/N83,0) -> 0.59370671 | P83: 3000 | Q83: OK | R83: 1275083 | S83: CARREGADO | T83: 4867315 | U83: 0.0625 | V83: 0.77083333 | X83: ORDEM | Y83: 45341.65 | Z83: 45341.85 | AE83: OK
A84: 10204815 | C84: 45342.875 | D84: 26 | E84: 31625 | F84: TE01 | G84: TRF | H84: HNK SÃO JOSÉ-SC | I84: 50.221.019/0076-53 | J84: PONTA GROSSA | K84: SÃO JOSÉ | L84: SC | M84: A47130 | N84: 5053 | O84: =IFERROR(P84/N84,0) -> 0.59370671 | P84: 3000 | Q84: OK | R84: 1276625 | S84: CARREGADO | T84: 4874817 | U84: 0.5625 | X84: ORDEM | Y84: 45343.667 | Z84: 45343.751 | AE84: OK
A85: 10205062 | C85: 45339.625 | D85: 26 | E85: 31133 | F85: TE01 | G85: TRF | H85: CDA ITU-SP | I85: 50.221.019/0047-19 | J85: PONTA GROSSA | K85: ITU | L85: SP | M85: A56060 | N85: 5174 | O85: =IFERROR(P85/N85,0) -> 0.77309625 | P85: 4000 | Q85: OK | R85: 1275065 | S85: CARREGADO | T85: 4867214 | U85: 0.061111111 | V85: 0.24583333 | X85: ORDEM | Y85: 45342.087 | Z85: 45343.549 | AE85: OK
A86: 10206996 | C86: 45343.583 | D86: 28 | E86: 34058 | F86: TE01 | G86: DTB | H86: LAGO AZUL MARÍLIA-SP | I86: 58.844.424/0002-01 | J86: PONTA GROSSA | K86: MARÍLIA | L86: SP INT. | M86: A57620 | N86: 4325 | O86: =IFERROR(P86/N86,0) -> 0.69364162 | P86: 3000 | Q86: OK | R86: 1277119 | S86: CARREGADO | T86: 4877979 | U86: 0.39791667 | V86: 0.55972222 | X86: ORDEM | Y86: 45343.734 | Z86: 45345.502 | AE86: OK
A87: 10206997 | C87: 45343.833 | D87: 28 | E87: 34058 | F87: TE01 | G87: DTB | H87: LAGO AZUL REGENTE FEIJÓ | I87: 58.844.424/0003-84 | J87: PONTA GROSSA | K87: REGENTE FEIJÓ | L87: SP INT. | M87: A56430 | N87: 5004.48 | O87: =IFERROR(P87/N87,0) -> 0.69937336 | P87: 3500 | Q87: OK | R87: 1277146 | S87: CARREGADO | T87: 4878264 | U87: 0.42777778 | V87: 0.67847222 | X87: ORDEM | Y87: 45344.615 | Z87: 45344.745 | AE87: OK
A88: 10207008 | C88: 45343.625 | D88: 28 | E88: 34058 | F88: TE01 | G88: DTB | H88: LAGO AZUL MARÍLIA-SP | I88: 58.844.424/0002-01 | J88: PONTA GROSSA | K88: MARÍLIA | L88: SP INT. | M88: A55650 | N88: 4325 | O88: =IFERROR(P88/N88,0) -> 0.69364162 | P88: 3000 | Q88: OK | R88: 1277159 | S88: CARREGADO | T88: 4878348 | U88: 0.725 | V88: 0.21805556 | X88: ORDEM | Y88: 45344.605 | Z88: 45344.757 | AE88: OK
A89: 10207923 | C89: 45339.583 | D89: 26 | E89: 33430 | F89: TE01 | G89: ASD | H89: ATACADAO S.A. MARINGÁ-PR | I89: 75.315.333/0009-66 | J89: PONTA GROSSA | K89: MARINGÁ | L89: PR OUT. | M89: A57620 | N89: 4551.98 | O89: =IFERROR(P89/N89,0) -> 0.54921155 | P89: 2500 | Q89: OK | R89: 1274541 | S89: CARREGADO | T89: 4864780 | U89: 0.66666667 | V89: 0.88333333 | X89: 19/02 07H | Y89: 45341.231 | Z89: 45342.449 | AE89: OK
A90: 10207924 | C90: 45339.625 | D90: 26 | E90: 33430 | F90: TE01 | G90: ASD | H90: ATACADAO S.A. MARINGÁ-PR | I90: 75.315.333/0009-66 | J90: PONTA GROSSA | K90: MARINGÁ | L90: PR OUT. | M90: A55650 | N90: 4551.98 | O90: =IFERROR(P90/N90,0) -> 0.54921155 | P90: 2500 | Q90: OK | R90: 1274549 | S90: CARREGADO | T90: 4864815 | U90: 0.60555556 | V90: 0.68819444 | X90: 19/02 07H | Y90: 45342.672 | Z90: 45343.365
A91: 10208201 | C91: 45342.042 | D91: 20 | E91: 24327 | F91: TE01 | G91: ASD | H91: TAUSTE SUPERMARCADO ITU-SP | I91: 65.897.910/0013-06 | J91: PONTA GROSSA | K91: ITU | L91: SP | M91: A53130 | N91: 5174 | O91: =IFERROR(P91/N91,0) -> 0.77309625 | P91: 4000 | Q91: OK | R91: 1276833 | S91: CARREGADO | T91: 4876285 | U91: 0.86944444 | V91: 0.98263889 | X91: ORDEM
A92: 10209965 | C92: 45344.875 | D92: 28 | E92: 34058 | F92: TE01 | G92: DTB | H92: LAGO AZUL REGENTE FEIJÓ | I92: 58.844.424/0003-84 | J92: PONTA GROSSA | K92: REGENTE FEIJÓ | L92: SP INT. | M92: A57780 | N92: 5004.48 | O92: =IFERROR(P92/N92,0) -> 0.69937336 | P92: 3500 | Q92: OK | R92: 1277721 | S92: CARREGADO | T92: 4881753 | U92: 0.375 | V92: 0.54166667 | X92: ORDEM | Y92: 45345.271 | Z92: 45346.278 | AE92: OK
A93: 10210287 | C93: 45343.833 | D93: 26 | E93: 31659 | F93: TE02 | G93: TRF | H93: CDA ITU-SP | I93: 50.221.019/0047-19 | J93: PONTA GROSSA | K93: ITU | L93: SP | M93: A54920 | N93: 5174 | O93: =IFERROR(P93/N93,0) -> 0.77309625 | P93: 4000 | Q93: OK | R93: 1277150 | S93: CARREGADO | T93: 4878285 | U93: 0.40069444 | V93: 0.57222222 | X93: ORDEM | Y93: 45344.402 | Z93: 45344.64
A94: 10212316 | C94: 45342.875 | D94: 26 | E94: 31922 | F94: TE01 | G94: ASD | H94: TAUSTE SUPERMARCADO ITU-SP | I94: 65.897.910/0013-06 | J94: PONTA GROSSA | K94: ITU | L94: SP | M94: A56620 | N94: 5174 | O94: =IFERROR(P94/N94,0) -> 0.77309625 | P94: 4000 | Q94: OK | R94: 1276485 | S94: CARREGADO | T94: 4873962 | U94: 0.42083333 | V94: 0.55555556 | X94: ORDEM | Y94: 45343.287 | Z94: 45343.734 | AE94: OK
A95: 10215561 | C95: 45348.542 | D95: 26 | E95: 32647 | F95: TE01 | G95: DTB | H95: SPAL ANTÔNIO CARLOS-SC | I95: 61.186.888/0176-73 | J95: PONTA GROSSA | K95: ANTÔNIO CARLOS | L95: SC | M95: MBG6624/MHC3229 | N95: 4445.42 | O95: =IFERROR(P95/N95,0) -> 0.89980249 | P95: 4000 | Q95: OK | R95: 1279923 | S95: CARREGADO | T95: 4893381 | U95: 0.38958333 | V95: 0.54166667 | X95: 28/02 12H
A96: 10215562 | C96: 45346.083 | D96: 26 | E96: 32647 | F96: TE01 | G96: DTB | H96: SPAL ANTÔNIO CARLOS-SC | I96: 61.186.888/0176-73 | J96: PONTA GROSSA | K96: ANTÔNIO CARLOS | L96: SC | M96: A55640 | N96: 4445.42 | O96: =IFERROR(P96/N96,0) -> 0.67485187 | P96: 3000 | Q96: OK | R96: 1279218 | S96: CARREGADO | T96: 4891263 | U96: 0.27777778 | V96: 0.56736111 | Y96: 45349.603 | Z96: 45349.706 | AE96: OK
A97: 10216207 | C97: 45341.625 | D97: - | E97: - | F97: TE02 | G97: TRF | H97: (RETORNO TE02) CDA CAÇAPAVA-SP | I97: 50.221.019/0084-63 | J97: CAÇAPAVA | K97: PONTA GROSSA | L97: TE02 | M97: A57700 | N97: 4179.55 | O97: =IFERROR($P$79/N97,0) -> 0.89722578 | P97: 3500 | R97: 1276198 | S97: CARREGADO | T97: 4872161 | X97: ORDEM
A98: 10217171 | C98: 45344.458 | D98: 26 | E98: 33176 | F98: TE01 | G98: DTB | H98: CDA ITU-SP | I98: 50.221.019/0047-19 | J98: PONTA GROSSA | K98: ITU | L98: SP | M98: A55660 | N98: 5446 | O98: =IFERROR(P98/N98,0) -> 0.73448402 | P98: 4000 | Q98: OK | R98: 1277919 | S98: CARREGADO | T98: 4883067 | X98: ORDEM | Y98: 45347.762 | Z98: 45348.384 | AE98: OK
A99: 10218269 | C99: 45344.583 | D99: 26 | E99: 32553 | F99: TE02 | G99: DTB | H99: DBK SÃO JOSÉ DO RIO PRETO-SP | I99: 14.886.581/0001-15 | J99: PONTA GROSSA | K99: SÃO JOSÉ DO RIO PRETO | L99: SP INT. | M99: A56540 | N99: 5922.6 | O99: =IFERROR($P$78/N99,0) -> 0.50653429 | P99: 4500 | Q99: OK | R99: 1277910 | S99: CARREGADO | T99: 4883002 | U99: 0.57083333 | V99: 0.86666667 | X99: ORDEM | Y99: 45346.556 | Z99: 45347.333 | AE99: OK
A100: 10218270 | C100: 45347.625 | D100: - | E100: - | F100: TE02 | G100: DTB | H100: (RETORNO TE02) DBK SÃO JOSÉ DO RIO PRETO-SP | I100: 14.886.581/0001-15 | J100: SÃO JOSÉ DO RIO PRETO | K100: PONTA GROSSA | L100: TE02 | N100: 3948.4 | O100: =IFERROR($P$79/N100,0) -> 0.9497518 | P100: 3000 | R100: 1279413 | S100: CARREGADO | T100: 4892045
...

Sheet PEDÁGIO
A1: Nº Ocorrencia | B1: DT | C1: Frete | D1: ROTA | E1: COD. AGREGADO | F1: PLACA | G1: DATA EMBARQUE | H1: INICIO VIAGEM | I1: TERMINO VIAGEM | J1: VALOR ROTA A RECEBER | K1: STATUS VALIDAÇÃO HNK | L1: OBS | M1: Ação Ritmo
A2: 794826 | B2: 11111033 | C2: TE01 | D2: PONTA GROSSA X GUARULHOS | E2: A60950 | F2: AMP9049 | G2: 45689 | H2: 0.00069444444 | I2: 45444.597 | J2: R$ 219,00 | K2: FINALIZADA SEM DEV | L2: CUSTO SAP LANÇ | M2: Aguarda Demonst. Crédito
A3: 794828 | B3: 11111034 | C3: TE01 | D3: PONTA GROSSA X GUARULHOS | E3: A61060 | F3: ALC0D80 | G3: 45717 | H3: 0.3625 | I3: 45809.792 | J3: R$ 219,00 | K3: FINALIZADA SEM DEV | L3: CUSTO SAP LANÇ | M3: Aguarda Demonst. Crédito
A4: 794836 | B4: 11110447 | C4: TE01 | D4: PONTA GROSSA X GUARULHOS | E4: A60720 | F4: JZU1A40 | G4: 45717 | H4: 0.86666667 | I4: 45809.778 | J4: R$ 219,00 | K4: FINALIZADA SEM DEV | L4: CUSTO SAP LANÇ | M4: Aguarda Demonst. Crédito
A5: 782939 | B5: 11110908 | C5: TE01 | D5: PONTA GROSSA X GUARULHOS | E5: A63590 | F5: GHC4E75 | G5: 45717 | H5: 0.4625 | I5: 45809.323 | J5: 248,86 | K5: FINALIZADA SEM DEV | L5: CUSTO SAP LANÇ | M5: Aguarda Demonst. Crédito
A6: 812167 | B6: 11096082 | C6: TE01 | D6: PONTA GROSSA X GUARULHOS | E6: A62740 | F6: NJQ6C66 | G6: 45809 | H6: 0.31388889 | I6: 45870.573 | J6: 216.39 | K6: FINALIZADA SEM DEV | L6: CUSTO SAP LANÇ | M6: Aguarda Demonst. Crédito
A7: 812169 | B7: 11110446 | C7: TE01 | D7: PONTA GROSSA X GUARULHOS | E7: A62920 | F7: BCJ0C22 | G7: 45809 | H7: 0.89652778 | I7: 45839.924 | J7: 142.2 | K7: FINALIZADA SEM DEV | L7: CUSTO SAP LANÇ | M7: Aguarda Demonst. Crédito
A8: 794848 | B8: 11096081 | C8: TE02 | D8: PONTA GROSSA X GUARULHOS | E8: A61710 | F8: AZP0H53 | G8: 45809 | H8: 0.75 | I8: 45870.562 | J8: R$ 219,00 | K8: FINALIZADA SEM DEV | L8: RET. VAZIO | M8: Aguarda Demonst. Crédito
A9: 794854 | B9: 11106283 | C9: TE01 | D9: PONTA GROSSA X CURIITBA | E9: A63440 | F9: DPB1I84 | G9: 45809 | H9: 0.97847222 | I9: 45839.854 | J9: R$ 52,20 | K9: FINALIZADA SEM DEV | L9: CUSTO SAP LANÇ | M9: Aguarda Demonst. Crédito
A10: 794851 | B10: 11106284 | C10: TE01 | D10: PONTA GROSSA X CURIITBA | E10: A61130 | F10: ATJ1E14 | G10: 45809 | H10: 0.83819444 | I10: 45839.743 | J10: R$ 52,20 | K10: FINALIZADA SEM DEV | L10: CUSTO SAP LANÇ | M10: Aguarda Demonst. Crédito
A11: 794856 | B11: 11115111 | C11: TE01 | D11: PONTA GROSSA X GUARULHOS | E11: A62760 | F11: MPP1639 | G11: 45839 | H11: 0.71388889 | I11: 45870.747 | J11: R$ 219,00 | K11: FINALIZADA SEM DEV | L11: CUSTO SAP LANÇ | M11: Aguarda Demonst. Crédito
A12: 794859 | B12: 11115110 | C12: TE01 | D12: PONTA GROSSA X GUARULHOS | E12: A55640 | F12: RLI4I24 | G12: 45839 | H12: 45870.021 | I12: 45901.792 | J12: R$ 219,00 | K12: FINALIZADA SEM DEV | L12: CUSTO SAP LANÇ | M12: Aguarda Demonst. Crédito
A13: 812171 | B13: 11118603 | C13: TE01 | D13: PONTA GROSSA X GUARULHOS | E13: A63500 | F13: EFW3B74 | G13: 45870 | H13: 0.48574074 | I13: 45901.552 | J13: 166.8 | K13: FINALIZADA SEM DEV | L13: CUSTO SAP LANÇ | M13: Aguarda Demonst. Crédito
A14: 812173 | B14: 11118602 | C14: TE01 | D14: PONTA GROSSA X GUARULHOS | E14: A60790 | F14: DTE2491 | G14: 45870 | H14: 0.72898148 | I14: 45931.792 | J14: R$ 219,00 | K14: FINALIZADA SEM DEV | L14: CUSTO SAP LANÇ | M14: Aguarda Demonst. Crédito
A15: 785785 | B15: 11119430 | C15: TE02 | D15: PONTA GROSSA X GUARULHOS | E15: A63590 | F15: GHC4E75 | G15: 45870 | H15: 45901.077 | I15: 45931.073 | J15: R$ 219,00 | K15: FINALIZADA SEM DEV | L15: RET. VAZIO/ CUSTO SAP LANÇ | M15: Aguarda Demonst. Crédito
A16: 796463 | B16: 11121906 | C16: TE01 | D16: PONTA GROSSA X TIJUCAS | E16: A60560 | F16: ASP6I28 | G16: 45901 | H16: 0.57436343 | I16: 15/01/2025 10:00 | J16: R$ 177,00 | K16: FINALIZADA SEM DEV | L16: CUSTO SAP LANÇ | M16: Aguarda Demonst. Crédito
A17: 812176 | B17: 11118870 | C17: TE01 | D17: PONTA GROSSA X TIJUCAS | E17: A61130 | F17: ATJ1E14 | G17: 45901 | H17: 0.74967593 | I17: 15/01/2025 11:00 | J17: R$ 174.39 | K17: FINALIZADA SEM DEV | L17: CUSTO SAP LANÇ | M17: Aguarda Demonst. Crédito
A18: 812182 | B18: 11126308 | C18: TE01 | D18: PONTA GROSSA X GUARULHOS | E18: A62940 | F18: ETU2H73 | G18: 45901 | H18: 0.6362037 | I18: 13/01/2025 7:00 | J18: 257.72 | K18: FINALIZADA SEM DEV | L18: CUSTO SAP LANÇ | M18: Aguarda Demonst. Crédito
A19: 812184 | B19: 11122074 | C19: TE01 | D19: PONTA GROSSA X TIJUCAS | E19: A60720 | F19: JZU1A40 | G19: 45901 | H19: 0.86402778 | I19: 13/01/2025 10:20 | J19: 202.25 | K19: FINALIZADA SEM DEV | L19: CUSTO SAP LANÇ | M19: Aguarda Demonst. Crédito
A20: 788428 | B20: 11119431 | C20: TE01 | D20: PONTA GROSSA X GUARULHOS | E20: A61400 | F20: FUC4F49 | G20: 13/01/2025 | H20: 0.6056713 | I20: 15/01/2025 11:15 | J20: R$ 219,00 | K20: NÃO | L20: N TEM | M20: Finalizado
A21: 788433 | B21: 11119429 | C21: TE01 | D21: PONTA GROSSA X GUARULHOS | E21: A61710 | F21: AZP0H53 | G21: 13/01/2025 | H21: 0.84579861 | I21: 15/01/2025 11:15 | J21: R$ 219,00 | K21: NÃO | L21: HORARIOS NAO CONSTAM | M21: Finalizado
A22: 788443 | B22: 11126514 | C22: TE02 | D22: PONTA GROSSA X GUARULHOS | E22: A63610 | F22: AXN1D92 | G22: 13/01/2025 | H22: 0.2865625 | I22: 17/01/2025 02:10 | J22: R$ 219,00 | K22: NÃO | M22: Finalizado
A23: 800515 | B23: 11126513 | C23: TE02 | D23: GUARULHOS X PONTA GROSSA | E23: A63770 | F23: MLL6E83 | G23: 21/01/2025 | H23: 0 | I23: 23/01/2025 21:30 | J23: R$ 219,00 | K23: FINALIZADA SEM DEV | L23: CUSTO SAP LANÇ | M23: Aguarda Demonst. Crédito
A24: 795472 | B24: 11137473 | C24: TE01 | D24: PONTA GROSSA X SÃO PAULO | E24: A63640 | F24: AEW3F21 | G24: 15/01/2025 | H24: 15/01/2025 21:30 | I24: 18/01/2025 01:00 | J24: R$ 219,00 | K24: FINALIZADA SEM DEV | L24: CUSTO SAP LANÇ | M24: Aguarda Demonst. Crédito
A25: 795479 | B25: 11145471 | C25: TE01 | D25: PONTA GROSSA X OSASCO | E25: A60560 | F25: ASP6I28 | G25: 15/01/2025 | H25: 15/01/2025 23:20 | I25: 21/01/2025 20:40 | J25: R$ 219,00 | K25: FINALIZADA SEM DEV | L25: CUSTO SAP LANÇ | M25: Aguarda Demonst. Crédito
A26: 801383 | B26: 11150944 | C26: TE01 | D26: PONTA GROSSA X MOGI DAS CRUZES | E26: A63650 | F26: MEA5F57 | G26: 22/01/2025 | H26: 0.46527778 | I26: 23/01/2025 12:00 | J26: R$ 600.00 | K26: FINALIZADA SEM DEV | L26: CUSTO SAP LANÇ | M26: Aguarda Demonst. Crédito
A27: 801296 | B27: 11158161 | C27: TE02 | D27: PONTA GROSSA X GUARULHOS | E27: A63640 | F27: AEW3F21 | G27: 23/01/2025 | H27: 0.5 | I27: 27/01/2025 15:25 | J27: R$ 219,00 | K27: FINALIZADA SEM DEV | L27: RET. VAZIO/ CUSTO SAP LANÇ | M27: Aguarda Demonst. Crédito
A28: 816639 | B28: 11164287 | C28: TE01 | D28: PONTA GROSSA X OSASCO | E28: A61710 | F28: AZP0H53 | G28: 24/01/2025 | H28: 0.61805556 | I28: 27/01/2025 06:00 | J28: 216.39 | K28: FINALIZADA SEM DEV | L28: CUSTO SAP LANÇ | M28: Aguarda Demonst. Crédito
A29: 801393 | B29: 11166707 | C29: TE01 | D29: PONTA GROSSA X SÃO PAULO | E29: A63680 | F29: APN2H58 | G29: 25/01/2025 | H29: 0.78472222 | I29: 28/01/2025 16:10 | J29: R$ 219,00 | K29: FINALIZADA SEM DEV | L29: CUSTO SAP LANÇ | M29: Aguarda Demonst. Crédito
A30: 816632 | B30: 11161662 | C30: TE02 | D30: IGREJINHA X VESPASIANO CORREIA | E30: IOZ9E30 | F30: IOZ9E30 | G30: 30/01/2025 | H30: 0.60416667 | I30: 31/01/2025 11:25 | J30: R$ 143.00 | K30: FINALIZADA SEM DEV | L30: CUSTO SAP LANÇ | M30: Aguarda Demonst. Crédito
A31: 816647 | B31: 11161669 | C31: TE02 | D31: VESPASIANO CORREIA X IGREJINHA | E31: IOZ9E30 | F31: IOZ9E30 | G31: 31/01/2025 | H31: 0.47569444 | I31: 45718.41 | J31: R$ 60,50 | K31: FINALIZADA SEM DEV | L31: CUSTO SAP LANÇ | M31: Aguarda Demonst. Crédito
A32: 805114 | B32: 11172544 | C32: TE01 | D32: PONTA GROSSA X OSASCO | E32: A60720 | F32: JZU1A40 | G32: 29/01/2025 | H32: 0.72916667 | I32: 45659.042 | J32: R$ 219,00 | K32: FINALIZADA SEM DEV | L32: CUSTO SAP LANÇ | M32: Aguarda Demonst. Crédito
A33: 813902 | B33: 11180189 | C33: TE01 | D33: PONTA GROSSA X PORTO BELO | E33: A60560 | F33: ASP6I28 | G33: 29/01/2025 | H33: 0.77083333 | I33: 45659.167 | J33: 82.65 | K33: FINALIZADA SEM DEV | L33: CUSTO SAP LANÇ | M33: Aguarda Demonst. Crédito
B34: 11182101 | C34: TE02 | D34: IGREJINHA X JOAÇABA | E34: A58340 | F34: IEU5D15 | G34: 30/01/2025 | H34: 0.58333333 | I34: 31/01/2025 18:00 | K34: NÃO | M34: Finalizado
B35: 11182104 | C35: TE02 | D35: JOAÇABA X IGREJINHA | E35: A58340 | F35: IEU5D15 | G35: 45659 | H35: 0.41666667 | I35: 45718.396 | K35: NÃO | M35: Finalizado
B36: 11180188 | C36: TE01 | D36: PONTA GROSSA X PORTO BELO | E36: A63860 | F36: GBN9E05 | G36: 31/01/2025 | H36: 0.79166667 | I36: 45718.167 | J36: R$ 145,80 | K36: NÃO | M36: Finalizado
A37: 805126 | B37: 11182762 | C37: TE01 | D37: PONTA GROSSA X JUNDIAI | E37: A55640 | F37: RLI4I24 | G37: 31/01/2025 | H37: 0.20833333 | I37: 45718.292 | J37: R$ 496,80 | K37: FINALIZADA SEM DEV | L37: CUSTO SAP | M37: Aguarda Demonst. Crédito
B38: 11170686 | C38: TE01 | D38: PONTA GROSSA X GUARULHOS | E38: A63940 | F38: AYP3B37 | G38: 45718 | H38: 0 | I38: 45779.479 | K38: NAO | L38: VEICULO SEM TAG/ AUDINEI | M38: Finalizado
A39: 813915 | B39: 11186826 | C39: TE01 | D39: PONTA GROSSA X GUARULHOS | E39: A63820 | F39: ATF7H89 | G39: 45718 | H39: 0 | I39: 45749.917 | J39: 104.19 | K39: FINALIZADA SEM DEV | L39: CUSTO SAP | M39: Aguarda Demonst. Crédito
A40: 813919 | B40: 11185640 | C40: TE01 | D40: PONTA GROSSA X OSASCO | E40: A63320 | F40: MGF4H86 | G40: 45779 | H40: 0 | I40: 45840.542 | J40: 68.66 | K40: FINALIZADA SEM DEV | L40: CUSTO SAP | M40: Aguarda Demonst. Crédito
A41: 823853 | B41: 11196700 | C41: TE01 | D41: PONTA GROSSA X GUARULHOS | E41: A63690 / A56540 | F41: AET2E84 / AOO8H10 | G41: 45810 | H41: 0 | I41: 45963.99 | J41: R$ 236.13 | K41: FINALIZADA SEM DEV | M41: Finalizado
A42: 813925 | B42: 11193294 | C42: TE01 | D42: PONTA GROSSA X SÃO PAULO | E42: A56540 | F42: AOO8H10 | G42: 45840 | H42: 0 | I42: 45932.25 | J42: 208.19 | K42: FINALIZADA SEM DEV | L42: CUSTO SAP | M42: Aguarda Demonst. Crédito
A43: 814063 | B43: 11193293 | C43: TE01 | D43: PONTA GROSSA X SÃO JOSÉ DOS PINHAIS | E43: A63650 | F43: MEA5F57 | G43: 45871 | H43: 0 | I43: 45932.25 | J43: 49.59 | K43: FINALIZADA SEM DEV | L43: CUSTO SAP | M43: Aguarda Demonst. Crédito
A44: 814065 | B44: 11193478 | C44: TE01 | D44: PONTA GROSSA X SÃO JOSÉ DOS PINHAIS | E44: A61060 | F44: ALC0D80 | G44: 45871 | H44: 0 | I44: 45932.25 | J44: 49.59 | K44: FINALIZADA SEM DEV | L44: CUSTO SAP | M44: Aguarda Demonst. Crédito
B45: 11197335 | C45: TE01 | D45: PONTA GROSSA X GUARULHOS | E45: A63860 | F45: GBN9E05 | G45: 45932 | H45: 0 | I45: 45993.451 | K45: NÃO | M45: Finalizado
B46: 11197334 | C46: TE01 | D46: PONTA GROSSA X GUARULHOS | E46: A63850 | F46: BAN2A60 | G46: 45932 | H46: 0 | I46: 45963.569 | K46: NAO | M46: Finalizado
B47: 11200286 | C47: TE01 | D47: PONTA GROSSA X OSASCO | E47: A60000 | F47: EPB9B81 | G47: 45932 | H47: 0 | I47: 45993.583 | K47: NAO | L47: SEM EXTRATO / DAVID | M47: Finalizado
A48: 827159 | B48: 11197344 | C48: TE01 | D48: PONTA GROSSA X GUARULHOS | E48: A63820 | F48: ATF7H89 | G48: 45932 | H48: 0 | I48: 45963.979 | J48: R$ 100,91 | K48: FINALIZADA SEM DEV | M48: Finalizado
B49: 11197403 | C49: TE01 | D49: PONTA GROSSA X GUARULHOS | E49: A63410 | F49: NUF0C80 | G49: 45963 | H49: 0.375 | I49: 17/02/2025 08:30 | K49: NÃO | L49: SEM EXTRATO | M49: Finalizado
A50: 814839 | B50: 11204232 | C50: TE01 | D50: PONTA GROSSA X GUARULHOS | E50: A61060 | F50: ALC0D80 | G50: 45993 | H50: 0.20833333 | I50: 14/02/2025 08:55 | J50: 213 | K50: FINALIZADA SEM DEV | L50: CUSTO SAP | M50: Aguarda Demonst. Crédito
A51: 816659 | B51: 11225243 | C51: TE02 | D51: PONTA GROSSA X CURITIBA | E51: A63320 | F51: MGF4H86 | G51: 17/02/2025 | H51: 0.91666667 | I51: 18/02/2025 12:00 | J51: 52.2 | K51: FINALIZADA SEM DEV | L51: CUSTO SAP LANÇ | M51: Aguarda Demonst. Crédito
A52: 817727 | B52: 11225244 | C52: TE02 | D52: CURITIBA X PONTA GROSSA | E52: A63320 | F52: MGF4H86 | G52: 19/02/2025 | H52: 0.20833333 | I52: 19/02/2025 13:00 | J52: 52.2 | K52: FINALIZADA SEM DEV | L52: CUSTO SAP LANÇ | M52: Aguarda Demonst. Crédito
A53: 824031 | B53: 11225307 | C53: TE01 | D53: PONTA GROSSA X CURITIBA | E53: A62940 | F53: ETU2H73 | G53: 17/02/2025 | H53: 0.85416667 | I53: 18/02/2025 10:00 | J53: R$ 49.59 | K53: FINALIZADA SEM DEV | M53: Finalizado
A54: 823877 | B54: 11232955 | C54: TE01 | D54: PONTA GROSSA X JUNDIAI | E54: A55640 | F54: RLI4I24 | G54: 18/02/2025 | H54: 0.97222222 | I54: 20/02/2025 14:49 | J54: R$ 459,20 | K54: FINALIZADA SEM DEV | M54: Finalizado
A55: 832272 | B55: 11224541 | C55: TE01 | D55: PONTA GROSSA X OSASCO | E55: A55160 | F55: ILI8C72 | G55: 19/02/2025 | H55: 0.8125 | I55: 21/02/2025 13:00 | J55: R$ 248.86 | K55: FINALIZADA SEM DEV | L55: TICKETS | M55: Finalizado
A56: 827228 | B56: 11234665 | C56: TE01 | D56: PONTA GROSSA X PINHAIS | E56: A60950 | F56: AMP9049 | G56: 20/02/2025 | H56: 0.91666667 | I56: 21/02/2025 09:55 | J56: R$ 49.59 | K56: FINALIZADA SEM DEV | L56: CUSTO SAP LANÇ | M56: Finalizado
A57: 823758 | B57: 11234664 | C57: TE01 | D57: PONTA GROSSA X PINHAIS | E57: A60720 | F57: JZU1A40 | G57: 20/02/2025 | H57: 0.65972222 | I57: 21/02/2025 07:00 | J57: R$ 49.59 | K57: FINALIZADA SEM DEV | M57: Finalizado
A58: 833224 | B58: 11238602 | C58: TE01 | D58: PONTA GROSSA X JAU | E58: A64220 | F58: JLQ7H51 | G58: 21/02/2025 | H58: 0.95833333 | I58: 25/02/2025 00:00 | J58: R$ 327.40 | K58: FINALIZADA SEM DEV | L58: TICKETS | M58: Finalizado
B59: 11234898 | C59: TE01 | D59: PONTA GROSSA X PINHAIS | E59: A63680 | F59: APN2H58 | G59: 21/02/2025 | H59: 0.99652778 | I59: 24/02/2025 07:00 | K59: NÃO | L59: SEM EXTRATO NA TAG REPOM | M59: Finalizado
A60: 827152 | B60: 11233507 | C60: TE01 | D60: PONTA GROSSA X BARUERI | E60: A59460 | F60: EVU7C10 | G60: 24/02/2025 | H60: 0.97916667 | I60: 26/02/2025 13:35 | J60: R$ 261,65 | K60: FINALIZADA SEM DEV | M60: Finalizado
A61: 823934 | B61: 11233446 | C61: TE01 | D61: PONTA GROSSA X MARILIA | E61: A63660 | F61: GVQ2B17 | G61: 24/02/2025 | H61: 0.97916667 | I61: 26/02/2025 12:20 | J61: R$ 358,36 | K61: FINALIZADA SEM DEV | M61: Finalizado
A62: 827230 | B62: 11233447 | C62: TE01 | D62: PONTA GROSSA X JUNDIAI | E62: A63010 | F62: MEN5G01 | G62: 24/02/2025 | H62: 0.98611111 | I62: 26/02/2025 09:50 | J62: R$ 367,50 | K62: FINALIZADA SEM DEV | M62: Finalizado
A63: 841574 | B63: 11233445 | C63: TE01 | D63: PONTA GROSSA X JUNDIAI | E63: A63640 | F63: AEW3F21 | G63: 24/02/2025 | H63: 0.99305556 | I63: 26/02/2025 11:50 | J63: R$ 415.90 | K63: FINALIZADA SEM DEV | L63: CUSTO SAP LANÇ | M63: Finalizado
A64: 827129 | B64: 11238670 | C64: TE01 | D64: PONTA GROSSA X JUNDIAI | E64: A61710 | F64: AZP0H53 | G64: 25/02/2025 | H64: 0.6875 | I64: 27/02/2025 16:45 | J64: R$ 558,07 | K64: FINALIZADA SEM DEV | M64: Finalizado
A65: 827233 | B65: 11241667 | C65: TE01 | D65: PONTA GROSSA X JUNDIAI | E65: A62740 | F65: NJQ6C66 | G65: 26/02/2025 | H65: 0.70833333 | I65: 28/02/2025 08:00 | J65: R$ 558,07 | K65: FINALIZADA SEM DEV | M65: Finalizado
A66: 834220 | B66: 11262430 | C66: TE01 | D66: PONTA GROSSA X GUARULHOS | E66: A62480 | F66: CVN3I94 | G66: 45660 | H66: 0.47916667 | I66: 45719.729 | J66: R$ 228.69 | K66: FINALIZADA SEM DEV | M66: Finalizado
A67: 834222 | B67: 11265875 | C67: TE01 | D67: PONTA GROSSA X GUARULHOS | E67: A60560 | F67: ASP6I28 | G67: 45811 | H67: 0.625 | I67: 45964.938 | J67: R$ 258,13 | K67: FINALIZADA SEM DEV | M67: Finalizado
A68: 835381 | B68: 11274232 | C68: TE01 | D68: PONTA GROSSA X JUNDIAI | E68: A62480 | F68: CVN3I94 | G68: 45841 | H68: 0.875 | I68: 45933.41 | J68: R$ 558,07 | K68: FINALIZADA SEM DEV | M68: Finalizado
A69: 836533 | B69: 11277477 | C69: TE01 | D69: PONTA GROSSA X GUARULHOS | E69: A63680 | F69: APN2H58 | G69: 45994 | H69: 0.91666667 | I69: 14/03/2025 20:54 | J69: R$174.53 | K69: FINALIZADA SEM DEV | M69: Finalizado
A70: 840848 | B70: 11300759 | C70: TE01 | D70: PONTA GROSSA X GUARULHOS | E70: A64570 | F70: AWD1B98 | G70: 20/03/2025 | H70: 0.875 | I70: 24/03/2025 12:15 | J70: R$ 298.30 | K70: FINALIZADA SEM DEV | L70: CUSTO SAP LANÇ | M70: Finalizado
A71: 844518 | B71: 11325509 | C71: TE01 | D71: GUARULHOS X PONTA GROSSA | E71: A64570 | F71: AWD1B98 | G71: 25/03/2025 | H71: 0.15277778 | I71: 26/03/2025 20:06 | J71: R$ 289.09 | K71: FINALIZADA SEM DEV | L71: CUSTO SAP LANÇ | M71: Finalizado
A72: 851806 | B72: 11324853 | C72: TE01 | D72: PONTA GROSSA X PALHOÇA | E72: A64410 | F72: MIS0H20 | G72: 29/03/2025 | H72: 0.375 | I72: 31/03/2025 07:00 | J72: R$ 198.17 | K72: FINALIZADA SEM DEV | L72: CUSTO SAP LANÇ | M72: Finalizado
A73: 860923 | B73: 11367913 | C73: TE01 | D73: PONTA GROSSA X ITU | E73: A64950 | F73: ILZ1B64 | G73: 14/04/2025 | H73: 0.83333333 | I73: 17/04/2025 10:00 | J73: R$ 331.36 | K73: FINALIZADA SEM DEV | L73: CUSTO SAP LANÇ | M73: Finalizado
A74: 864801 | B74: 11368488 | C74: TE01 | D74: PONTA GROSSA X ITU | E74: A64420 | F74: JLQ7H51 | G74: 15/04/2025 | H74: 0.375 | I74: 17/04/2025 20:40 | J74: R$ 358,57 | K74: FINALIZADA SEM DEV | L74: CUSTO SAP LANÇ | M74: Finalizado
A75: 864808 | B75: 11370196 | C75: TE02 | D75: PONTA GROSSA X ARAÇATUBA | E75: A64900 | F75: MIO0D70 | G75: 16/04/2025 | H75: 0.70833333 | I75: 22/04/2025 06:30 | J75: R$ 625,63 | K75: FINALIZADA SEM DEV | L75: CUSTO SAP LANÇ | M75: Finalizado
A76: 864812 | B76: 11370197 | C76: TE02 | D76: ARAÇATUBA X PONTA GROSSA | E76: A64900 | F76: MIO0D70 | G76: 22/04/2025 | H76: 0.64236111 | I76: 23/04/2025 13:30 | J76: R$ 561.48 | K76: FINALIZADA SEM DEV | L76: CUSTO SAP LANÇ | M76: Finalizado
A77: 864814 | B77: 11368489 | C77: TE01 | D77: PONTA GROSSA X ITU | E77: A62300 | F77: BCP9H00 | G77: 16/04/2025 | H77: 0 | I77: 17/04/2025 16:17 | J77: R$ 331.36 | K77: FINALIZADA SEM DEV | L77: CUSTO SAP LANÇ | M77: Finalizado
A78: 872786 | B78: 11417432 | C78: TE02 | D78: PONTA GROSSA X ITU | E78: A64420 | F78: JLQ7H51 | G78: 45813 | H78: 0.54166667 | I78: 45874 | J78: R$ 528.95 | K78: FINALIZADA SEM DEV | L78: CUSTO SAP LANÇ | M78: Finalizado
A79: 872788 | B79: 11417436 | C79: TE02 | D79: ITU X PONTA GROSSA | E79: A64420 | F79: JLQ7H51 | G79: 45874 | H79: 0.5 | I79: 45905.479 | J79: R$ 505.95 | K79: FINALIZADA SEM DEV | L79: CUSTO SAP LANÇ | M79: Finalizado
A80: 876256 | B80: 11429862 | C80: TE01 | D80: PONTA GROSSA X CANDIDO MOTA | E80: A65460 | F80: QJK5J00 | G80: 45935 | H80: 0.75694444 | I80: 13/05/2025 07:00 | J80: R$ 599.38 | K80: FINALIZADA SEM DEV | L80: CUSTO SAP LANÇ | M80: Finalizado
A81: 878395 | B81: 11436175 | C81: TE01 | D81: PONTA GROSSA X ITU | E81: A64220 | F81: JLQ7H51 | G81: 45966 | H81: 0.040972222 | I81: 45996.646 | J81: R$ 527.73 | K81: FINALIZADA SEM DEV | L81: CUSTO SAP LANÇ | M81: Finalizado
A82: 876259 | B82: 11437552 | C82: TE01 | D82: PONTA GROSSA X ITU | E82: A64310 | F82: AXS2A52 | G82: 45935 | H82: 0.89930556 | I82: 19/05/2025 08:42 | J82: R$ 306.78 | K82: FINALIZADA SEM DEV | L82: CUSTO SAP LANÇ | M82: Finalizado
A83: 878313 | B83: 11445376 | C83: TE01 | D83: PONTA GROSSA X GUARULHOS | E83: A64030 | F83: MEK4B39 | G83: 17/05/2025 | H83: 0.99652778 | I83: 19/05/2025 22:37 | J83: R$ 313,94 | K83: FINALIZADA SEM DEV | L83: CUSTO SAP LANÇ | M83: Finalizado
A84: 878315 | B84: 11445377 | C84: TE01 | D84: PONTA GROSSA X GUARULHOS | E84: A64570 | F84: AWD1B98 | G84: 18/05/2025 | H84: 0.16041667 | I84: 19/05/2025 14:28 | J84: R$ 276.27 | K84: FINALIZADA SEM DEV | L84: CUSTO SAP LANÇ | M84: Finalizado
A85: 883674 | B85: 11451902 | C85: TE01 | D85: PONTA GROSSA X GUARULHOS | E85: A64300 | F85: GXS8G38 | G85: 22/05/2025 | I85: 26/05/2025 14:10 | J85: R$ 313.94 | K85: NOVO | M85: Acompanhar
A86: 886346 | B86: 11473453 | C86: TE01 | D86: PONTA GROSSA X JUNDIAI | E86: A62300 | F86: BCP9H00 | G86: 26/05/2025 | H86: 0.80486111 | I86: 28/05/2025 16:25 | J86: R$ 230.66 | K86: FINALIZADA SEM DEV | L86: CUTO SAP LANÇADO | M86: Finalizado
A87: 904160 | B87: 11557451 | C87: TE01 | D87: PONTA GROSSA X CURITIBA | E87: A66130 | F87: MGN6G66 | G87: 26/06/2025 | H87: 0.45833333 | I87: 26/06/2025 14:00 | J87: R$ 49.59 | K87: FINALIZADA SEM DEV | L87: CUTO SAP LANÇADO | M87: Finalizado
A88: 904678 | B88: 11552452 | C88: TE01 | D88: PONTA GROSSA X JUNDIAI | E88: A65890 | F88: EPB9B81 | G88: 27/06/2025 | H88: 0.51388889 | I88: 28/06/2025 12:30 | J88: R$ 596.45 | K88: FINALIZADA SEM DEV | L88: CUTO SAP LANÇADO | M88: Finalizado
A89: 904202 | B89: 11552451 | C89: TE01 | D89: PONTA GROSSA X JUNDIAI | E89: A65540 | F89: RLJ5B74 | G89: 27/06/2025 | H89: 0.54166667 | I89: 28/06/2025 08:00 | J89: R$ 596.45 | K89: FINALIZADA SEM DEV | L89: CUTO SAP LANÇADO | M89: Finalizado
A90: 904208 | B90: 11552450 | C90: TE01 | D90: PONTA GROSSA X JUNDIAI | E90: A59270 | F90: ATR5484 | G90: 27/06/2025 | H90: 0.75 | I90: 30/06/2025 06:15 | J90: R$ 534.70 | K90: NOVO | M90: Acompanhar
A91: 904210 | B91: 11552449 | C91: TE02 | D91: PONTA GROSSA X ARAÇATUBA | E91: A66130 | F91: MGN6G66 | G91: 27/06/2025 | H91: 0.5 | I91: 28/06/2025 19:00 | J91: R$ 494.72 | K91: FINALIZADA SEM DEV | L91: CUTO SAP LANÇADO | M91: Finalizado
A92: 904680 | B92: 11552453 | C92: TE02 | D92: ARAÇATUBA X PONTA GROSSA | E92: A66130 | F92: MGN6G66 | G92: 30/06/2025 | H92: 0.54166667 | I92: 30/06/2025 00:00 | J92: R$ 365.83 | K92: FINALIZADA SEM DEV | L92: CUTO SAP LANÇADO | M92: Finalizado
A93: 904216 | B93: 11558173 | C93: TE01 | D93: PONTA GROSSA X MARINGÁ | E93: A46380 | F93: MFY4I74 | G93: 28/06/2025 | H93: 0.75 | I93: 29/06/2025 21:00 | J93: R$ 218.88 | K93: FINALIZADA SEM DEV | L93: CUTO SAP LANÇADO | M93: Finalizado
A94: 904936 | B94: 11559929 | C94: TE01 | D94: PONYT GROSSA X CANDIDO MOTA | E94: A65020 | F94: ABZ5A09 | G94: 28/06/2025 | H94: 0.47916667 | I94: 30/06/2025 08:00 | J94: R$ 230.66 | K94: FINALIZADA SEM DEV | L94: CUSTO SAP LANÇADA | M94: Finalizado
A95: 908659 | B95: 11560322 | C95: TE01 | D95: PONTA GROSSA X MARINGÁ | E95: A65540 | F95: RLJ5B74 | G95: 29/06/2025 | H95: 0.54166667 | I95: 45664.396 | J95: R$ 218.88 | K95: FINALIZADA SEM DEV | L95: CUSTO LANÇADA SAP | M95: Finalizado
A96: 904682 | B96: 11563474 | C96: TE01 | D96: PONTA GROSSA X PINHAIS | E96: A62740 | F96: NJQ6C66 | G96: 30/06/2025 | H96: 0.5 | I96: 45664.396 | J96: R$ 49.59 | K96: FINALIZADA SEM DEV | L96: CUTO SAP LANÇADO | M96: Finalizado
A97: 14718 | B97: 11593850 | C97: TE02 | D97: PONTA GROSSA X CURITIBA | E97: A66530 | F97: TAS0H43 | G97: 14/07/2025 | H97: 0.6875 | I97: 15/07/2025 20:20 | J97: 49.59 | K97: FINALIZADA SEM DEV | L97: CUSTO LANÇADA SAP | M97: Finalizado
A98: 14738 | B98: 11593851 | C98: TE02 | D98: CURITIBA X PONTA GROSSA | E98: A66530 | F98: TAS0H43 | G98: 15/07/2025 | H98: 0.8125 | I98: 17/07/2025 00:30 | J98: 49.59 | K98: FINALIZADA SEM DEV | L98: CUSTO LANÇADA SAP | M98: Finalizado
A99: 33739 | B99: 11631962 | C99: TE01 | D99: PONTA GROSSA X CAMBE | E99: A66490 | F99: ATI8J32 | G99: 31/07/2025 | H99: 0.625 | I99: 45877.396 | J99: R$ 145.92 | K99: FINALIZADA SEM DEV | L99: CUSTO LANÇADA SAP | M99: Finalizado
A100: 43320 | B100: 11631866 | C100: TE01 | D100: PONTA GROSSA X GUARULHOS | E100: A65620 | F100: MFI1G76 | G100: 14/08/2025 | H100: 0.78472222 | I100: 16/08/2025 06:00 | J100: R$ 323.41 | K100: FINALIZADA SEM DEV | L100: CUSTO LANÇADA SAP | M100: Finalizado
...

Sheet CONTROLE DE OCORRENCIAS
A1: DATA | B1: Tipo de Ocorrencia | C1: Nº Ocorrencia | D1: DT | E1: ROTA | F1: CTE | G1: ROMANEIO | H1: CÓD. AGREGADO | I1: PLACA | J1: VALOR A RECEBER (CLIENTE) | K1: CUSTO MOTORISTA | L1: STATUS VALIDAÇÃO HNK | M1: OBSERVAÇÃO | N1: Ação Ritmo
A2: 13/11/2024 | B2: DIÁRIA DE DESCARGA | C2: 742087 | D2: 10937188 | E2: PONTA GROSSA X SÃO PAULO | F2: 2018 | G2: 1455533 | H2: A61710 | I2: AZP0H53 | J2: - | K2: - | L2: FINALIZADA SEM DEV | M2: Não Gerou descarregou no dia | N2: Finalizado
A3: 14/11/2024 | B3: DIÁRIA DE DESCARGA | C3: 742803 | D3: 10939807 | E3: PONTA GROSSA X SÃO PAULO | F3: 2020 | G3: 1456766 | H3: A60560 | I3: ASP6I28 | J3: - | K3: - | L3: FINALIZADA SEM DEV | M3: Não Gerou descarregou no dia | N3: Finalizado
A4: 20/11/2024 | B4: DIÁRIA DE DESCARGA | C4: 746417 | D4: 10961709 | E4: PONTA GROSSA X CURITIBA | F4: 2021 | G4: 1462210 | H4: A61380 | I4: MIZ9F60 | J4: - | K4: - | L4: FINALIZADA SEM DEV | M4: Não Gerou descarregou no dia | N4: Finalizado
A5: 21/11/2024 | B5: FALTA DE VASILHAME | C5: 746772 | D5: 10961709 | E5: CURITIBA X PONTA GROSSA | G5: - | H5: A61380 | I5: MIZ9F60 | L5: FINALIZADA SEM DEV | M5: Finalizada aberta OC 762729, que foi validada | N5: Finalizado
A6: 21/11/2024 | B6: DIÁRIA DE DESCARGA | C6: 747307 | D6: 10961677 | E6: PONTA GROSSA X CURITIBA | F6: 2023 | G6: 1463425 | H6: A62780 | I6: ASO5I06 | J6: - | K6: - | L6: FINALIZADA SEM DEV | M6: aberto outra e validado OC 759955 | N6: Finalizado
A7: 22/11/2024 | B7: DIÁRIA DE DESCARGA | C7: 748039 | D7: 10961677 | E7: CURITIBA X PONTA GROSSA | G7: 1465435 | H7: A62780 | I7: ASO5I06 | J7: - | K7: - | L7: FINALIZADA SEM DEV | M7: Não Gerou descarregou no dia Fabrica P.Grossa | N7: Finalizado
A8: 22/11/2024 | B8: RET. VAZIO | C8: 748042 | D8: 10974234 | E8: PONTA GROSSA X JUNDIAI | F8: 2022 | G8: 1463577 | H8: A60720 | I8: JZU1A40 | J8: R$ 3.640,00 | L8: FINALIZADA SEM DEV | M8: Validado Gerado demonstrativo crédito | N8: Finalizado
A9: 25/11/2024 | B9: DIÁRIA DE DESCARGA | C9: 749553 | D9: 10974234 | E9: JUNDIAI X PONTA GROSSA | G9: - | H9: A60720 | I9: JZU1A40 | J9: R$ 1.600,00 | L9: FINALIZADA SEM DEV | M9: Validado Gerado demonstrativo crédito | N9: Finalizado
A10: 26/11/2024 | B10: DIÁRIA DE DESCARGA | C10: 750540 | D10: 10968119 | E10: GUARULHOS X PONTA GROSSA | F10: 497999 | G10: 1467712 | H10: A62620 | I10: AWG4F46 | L10: FINALIZADA SEM DEV | M10: Comprov. anexos, MOT. NÃO apres. quando chamado para descarga | N10: Finalizado
A11: 25/11/2024 | B11: FALTA DE AGENDA | C11: 749246 | D11: 10981833 | E11: PONTA GROSSA X CURITIBA | F11: 2024 | G11: 1465807 | H11: A61380 | I11: MIZ9F60 | J11: - | L11: FINALIZADA SEM DEV | M11: Não Gerou descarregou no dia | N11: Finalizado
A12: 25/11/2024 | B12: DIÁRIA DE DESCARGA | C12: 749650 | D12: 10987912 | E12: PONTA GROSSA X GUARULHOS | F12: 2026 | G12: 1466420 | H12: A62900 | I12: ACS4B05 | L12: FINALIZADA SEM DEV | M12: Não Gerou descarregou no dia | N12: Finalizado
A13: 25/11/2024 | B13: DIÁRIA DE DESCARGA | C13: 749653 | D13: 10987911 | E13: PONTA GROSSA X GUARULHOS | F13: 2028 | G13: 1466482 | H13: A62940 | I13: ETU2H73 | J13: - | K13: - | L13: CANCELADO | N13: Finalizado
A14: 27/11/2024 | B14: DIÁRIA DE DESCARGA | C14: 751940 | D14: 10974238 | E14: MARILIA X PONTA GROSSA | F14: 498075 | G14: 1468026 | H14: A62890 | I14: CVN3A01 | J14: - | K14: - | L14: CANCELADO | M14: CANCELADO POR CAMILA | N14: Finalizado
A15: 29/11/2024 | B15: PERDA DE AGENDA | C15: 753772 | D15: 10987836 | E15: PONTA GROSSA X CANDIDO MOTA | F15: 2032 | G15: 1470957 | H15: A62890 | I15: CVN3A01 | L15: FINALIZADA SEM DEV | M15: Fin. por Marcos, OC aberta antes chegada no cliente | N15: Finalizado
A16: 45334 | B16: PERDA DE AGENDA | C16: 755575 | D16: 10987836 | E16: PONTA GROSSA X CANDIDO MOTA | F16: 2032 | G16: 1470957 | H16: A62890 | I16: CVN3A01 | J16: R$ 3.200,00 | L16: FINALIZADA SEM DEV | M16: Validado HNK já recebido Demonstrativo de crédito | N16: Finalizado
A17: 45334 | B17: PERDA DE AGENDA | C17: 755372 | D17: 11004320 | E17: PONTA GROSSA X FOZ DO IGUAÇU | F17: 2035 | G17: 1472030 | H17: A62940 | I17: ETU2H73 | L17: FINALIZADA SEM DEV | M17: Descarregou no cliente - Não gerou diária descarga | N17: Finalizado
A18: 45363 | B18: TAXA DE DESCARGA | C18: 756598 | D18: 11004320 | E18: PONTA GROSSA X FOZ DO IGUAÇU | F18: 2035 | G18: 1472030 | H18: A62940 | I18: ETU2H73 | J18: R$ 208,00 | L18: FINALIZADA SEM DEV | M18: Validado HNK já recebido Demonstrativo de crédito | N18: Finalizado
A19: 45363 | B19: AVARIA | C19: 756953 | D19: 10989997 | E19: PONTA GROSSA X MARILIA | F19: 2030 | G19: 1469686 | H19: A63120 | I19: ALO5I04 | L19: FINALIZADA SEM DEV | M19: AG. VALIDAÇÃO DA ORIGEM P/ DIRECIONAR O DEBITO | N19: Finalizado
A20: 45363 | B20: DIARIA DE DESCARGA | C20: 757028 | D20: 11003631 | E20: ITAPETININGA X PONTA GROSSA | F20: 499427 | G20: 1474259 | H20: A63080 | I20: CUE4E05 | J20: R$ 800,00 | L20: FINALIZADA SEM DEV | M20: Validado HNK já recebido Demonstrativo de crédito | N20: Finalizado
A21: 45363 | B21: DIARIA DE DESCARGA | C21: 757265 | D21: 10989997 | E21: MARILIA X PONTA GROSSA | F21: 499425 | G21: 1474217 | H21: A63120 | I21: ALO5I04 | L21: CANCELADO | M21: CANCELADA PELA FÁBRICA | N21: Finalizado
A22: 45455 | B22: DIARIA DE DESCARGA | C22: 759955 | D22: 10961677 | E22: PONTA GROSSA X CURITIBA | F22: 2023 | G22: 1463425 | H22: A62780 | I22: ASO5I06 | J22: R$ 800,00 | K22: R$ 500.00 | L22: FINALIZADA SEM DEV | M22: Validado HNK já recebido Demonstrativo de crédito | N22: Finalizado
A23: 45485 | B23: TAXA DE DESCARGA | C23: 760765 | D23: 10987836 | E23: PONTA GROSSA X CANDIDO MOTA | F23: 2032 | G23: 1470957 | H23: A62890 | I23: CVN3A01 | J23: R$ 352,00 | L23: FINALIZADA SEM DEV | M23: Validado HNK já recebido Demonstrativo de crédito | N23: Finalizado
A24: 45485 | B24: DIARIA DE DESCARGA | C24: 760848 | D24: 11011017 | E24: MARILIA X PONTA GROSSA | F24: 277485 | G24: 1477828 | H24: A63080 | I24: CUE4E05 | L24: CANCELADO | M24: CANCELADO PELA FÁBRICA | N24: Finalizado
A25: 45485 | B25: DIARIA DE DESCARGA | C25: 760873 | D25: 11005911 | E25: GUARULHOS X PONTA GROSSA | F25: 500130 | G25: 1477476 | H25: A63120 | I25: ALO5I04 | L25: FINALIZADA SEM DEV | M25: Não Gerou descarregou no dia | N25: Finalizado
A26: 45485 | B26: DIARIA DE DESCARGA | C26: 761703 | D26: 11019253 | E26: PONTA GROSSA X CURITIBA | F26: 2044 | G26: 1478353 | H26: A62890 | I26: CVN3A01 | L26: FINALIZADA SEM DEV | M26: Não validaram a diária reaberto OC 768166 e Validado HNK | N26: Finalizado
A27: 45547 | B27: DIARIA DE DESCARGA | C27: 761929 | D27: 11011068 | E27: MARILIA X PONTA GROSSA | F27: 500185 | G27: 1477828 | H27: A63080 | I27: CUE4E05 | L27: FINALIZADA SEM DEV | M27: Mot. foi chamado, mas não compareceu, não podendo então validar a diária | N27: Finalizado
A28: 45577 | B28: AVARIA | C28: 761929 | D28: 10994934 | E28: PONTA GROSSA X PORTO VELHO | F28: 2033 | G28: 1471916 | H28: AYY5D91 | I28: AYY5D91 | L28: FINALIZADA SEM DEV | M28: AUTORIZADO VIA HNK DESCARTE E FINALIZADO OC. | N28: Finalizado
A29: 45577 | B29: AVARIA | C29: 762571 | D29: 10994936 | E29: PONTA GROSSA X PORTO VELHO | F29: 2034 | G29: 1471946 | H29: AYZ6C77 | I29: AYZ6C77 | L29: FINALIZADA SEM DEV | M29: AUTORIZADO VIA HNK DESCARTE E FINALIZADO OC. | N29: Finalizado
A30: 45577 | B30: DEV. ATIVOS - PALLET | C30: 762649 | D30: 11019253 | E30: PONTA GROSSA X CURITIBA | F30: 2044 | G30: 1478353 | H30: A62890 | I30: CVN3A01 | L30: FINALIZADA SEM DEV | M30: OC. aberta p/ fins de quitação saldo pois o canht. pallet nao foi assinado | N30: Finalizado
A31: 45577 | B31: FALTA DE VASILHAME | C31: 762729 | D31: 10961709 | E31: CURITIBA X PONTA GROSSA | F31: 2021 | G31: - | H31: A61380 | I31: MIZ9F60 | J31: R$ 1.601,60 | L31: FINALIZADA SEM DEV | M31: Validado HNK já recebido Demonstrativo de crédito | N31: Finalizado
A32: 45608 | B32: DIARIA DE DESCARGA | C32: 763113 | D32: 11025298 | E32: GUARULHOS X PONTA GROSSA | F32: 500456 | G32: 1479350 | H32: A60560 | I32: ASP6I28 | J32: R$ 800,00 | L32: FINALIZADA SEM DEV | M32: Validado HNK já recebido Demonstrativo de crédito | N32: Finalizado
A33: 45608 | B33: DIARIA DE DESCARGA | C33: 763122 | D33: 11019254 | E33: CURITIBA X PONTA GROSSA | F33: 183309 | G33: 1480233 | H33: A62890 | I33: CVN3A01 | J33: R$ 800,00 | L33: FINALIZADA SEM DEV | M33: Validado HNK já recebido Demonstrativo de crédito | N33: Finalizado
A34: 45638 | B34: DIARIA DE DESCARGA | C34: 764208 | D34: 11026961 | E34: GUARULHOS X PONTA GROSSA | F34: 500815 | G34: 1481106 | H34: A61710 | I34: AZP0H53 | J34: R$ 800,00 | L34: FINALIZADA SEM DEV | M34: Validado HNK já recebido Demonstrativo de crédito | N34: Finalizado
A35: 13/12/2024 | B35: TAXA DE DESCARGA | C35: 765522 | D35: 11030433 | E35: PONTA GROSSA X SÃO JOSÉ DOS PINHAIS | F35: 2047 | G35: 1482155 | H35: A61270 | I35: DBC8790 | J35: R$ 390,00 | L35: FINALIZADA SEM DEV | N35: Aguarda Demonst. Crédito
A36: 13/12/2024 | B36: DESCARTE PALLET | C36: 765576 | D36: 11030433 | E36: PONTA GROSSA X SÃO JOSÉ DOS PINHAIS | F36: 2047 | G36: 1482155 | H36: A61270 | I36: DBC8790 | L36: FINALIZADA SEM DEV | M36: Ocorrência incorreta - Finalizado HNK não anexado NF de pallets | N36: Finalizado
A37: 13/12/2024 | B37: AVARIA | C37: 765583 | D37: 11030433 | E37: PONTA GROSSA X SÃO JOSÉ DOS PINHAIS | F37: 2047 | G37: 1482155 | H37: A61270 | I37: DBC8790 | L37: FINALIZADA SEM DEV | M37: AUTORIZADO VIA HNK DESCARTE E FINALIZADO OC. | N37: Finalizado
A38: 16/12/2024 | B38: DESCARTE PALLET | C38: 766495 | D38: 11030433 | E38: PONTA GROSSA X SÃO JOSÉ DOS PINHAIS | F38: 2047 | G38: 1482155 | H38: A61270 | I38: DBC8790 | L38: FINALIZADA SEM DEV | M38: Ocorrência incorreta - Finalizado HNK - Anexado NF incorreta | N38: Finalizado
A39: 16/12/2024 | B39: DESCARTE PALLET | C39: 766825 | D39: 11030433 | E39: PONTA GROSSA X SÃO JOSÉ DOS PINHAIS | F39: 2047 | G39: 1482155 | H39: A61270 | I39: DBC8790 | L39: FINALIZADA SEM DEV | M39: BAIXADA PELA GEOVANA, MAS SEM TRAT. NA OC | N39: Finalizado
A40: 14/12/2024 | B40: DIARIA DE DESCARGA | C40: 766044 | D40: 11040247 | E40: PONTA GROSSA X GARULHOS | F40: 2049 | G40: 1482372 | H40: A60560 | I40: ASP6I28 | L40: CANCELADO | M40: Não Gerou | N40: Finalizado
A41: 14/12/2024 | B41: FALTA DE VASILHAME | C41: 766047 | D41: 11040258 | E41: GUARULHOS X PONTA GROSSA | F41: - | G41: - | H41: A61510 | I41: NZU2538 | J41: R$ 3.920, 00 | L41: FINALIZADA SEM DEV | M41: Validado HNK já recebido Demonstrativo de crédito | N41: Finalizado
A42: 17/12/2024 | B42: DIARIA DE DESCARGA | C42: 767774 | D42: 11040260 | E42: GUARULHOS X PONTA GROSSA | F42: 501480 | G42: 1484540 | H42: A60560 | I42: ASP6I28 | L42: FINALIZADA SEM DEV | M42: Compr. Anexado - Não Validou Estadia | N42: Finalizado
A43: 17/12/2024 | B43: DIARIA DE DESCARGA | C43: 767787 | D43: 11041790 | E43: ITAPETININGA X PONTA GROSSA | F43: 501607 | G43: 1485492 | H43: A61710 | I43: AZP0H53 | J43: R$ 800,00 | L43: FINALIZADA SEM DEV | M43: Validado HNK já recebido Demonstrativo de crédito | N43: Finalizado
A44: 17/12/2024 | B44: DIARIA DE DESCARGA | C44: 768166 | D44: 11019253 | E44: PONTA GROSSA X CURITIBA | F44: 2044 | G44: 1478353 | H44: A62890 | I44: CVN3A01 | J44: R$ 800,00 | L44: FINALIZADA SEM DEV | M44: Validado HNK já recebido Demonstrativo de crédito | N44: Finalizado
A45: 19/12/2024 | B45: DIARIA DE DESCARGA | C45: 770250 | D45: 11042327 | E45: GUARULHOS X PONTA GROSSA | F45: 501890 | G45: 1486836 | H45: A63330 | I45: EUX8A96 | L45: FINALIZADA SEM DEV | M45: Não Gerou | N45: Finalizado
A46: 19/12/2024 | B46: DIARIA DE DESCARGA | C46: 770253 | D46: 11042326 | E46: GUARULHOS X PONTA GROSSA | F46: 502012 | G46: 1487525 | H46: A63320 | I46: MGF4H86 | J46: R$ 4.000,00 | L46: FINALIZADA SEM DEV | M46: Validado HNK já recebido Demonstrativo de crédito | N46: Finalizado
A47: 20/12/2024 | B47: RET. VAZIO | C47: 770687 | D47: 11054928 | E47: GUARULHOS X PONTA GROSSA | F47: - | G47: - | H47: A63410 | I47: NUF0C80 | J47: R$ 3.920,00 | L47: FINALIZADA SEM DEV | M47: Validado HNK já recebido Demonstrativo de crédito | N47: Finalizado
A48: 21/12/2024 | B48: DIARIA DE DESCARGA | C48: 771856 | D48: 11069471 | E48: CURITIBA X PONTA GROSSA | F48: 183641 | G48: 1488812 | H48: A63330 | I48: EUX8A96 | J48: R$ 800,00 | L48: FINALIZADA SEM DEV | M48: Validado HNK já recebido Demonstrativo de crédito | N48: Finalizado
A49: 21/12/2024 | B49: DIARIA DE DESCARGA | C49: 771867 | D49: 11054322 | E49: MARILIA X PONTA GROSSA | F49: 502279 | G49: 1488668 | H49: A61710 | I49: AZP0H53 | J49: R$ 1.600,00 | L49: FINALIZADA SEM DEV | M49: Validado HNK já recebido Demonstrativo de crédito | N49: Finalizado
A50: 23/12/2024 | B50: DIARIA DE DESCARGA | C50: 772663 | D50: 11057540 | E50: GUARULHOS X PONTA GROSSA | F50: 502378 | G50: 1489083 | H50: A62920 | I50: BCJ0C22 | L50: FINALIZADA SEM DEV | M50: Nao validou | N50: Finalizado
A51: 23/12/2024 | B51: DIARIA DE DESCARGA | C51: 772670 | D51: 11080757 | E51: GUARULHOS X PONTA GROSSA | F51: 502325 | G51: 1488866 | H51: A62440 | I51: MFI7B86 | L51: FINALIZADA SEM DEV | M51: Nao validou | N51: Finalizado
A52: 26/12/2024 | B52: DIARIA DE DESCARGA | C52: 774783 | D52: 11064400 | E52: MARILIA X PONTA GROSSA | F52: 502679 | G52: 1490814 | H52: A63530 | I52: CPJ2F67 | L52: FINALIZADA SEM DEV | N52: Finalizado
A53: 26/12/2024 | B53: DIARIA DE DESCARGA | C53: 775464 | D53: 11057544 | E53: GUARULHOS X PONTA GROSSA | F53: 502712 | G53: 1491118 | H53: A63500 | I53: EFW3B74 | L53: FINALIZADA SEM DEV | M53: Nao validou | N53: Finalizado
A54: 27/12/2024 | B54: DIARIA DE DESCARGA | C54: 776179 | D54: 11057540 | E54: GUARULHOS X PONTA GROSSA | F54: 502378 | G54: 1489083 | H54: A62920 | I54: BCJ0C22 | J54: R$ 800,00 | L54: FINALIZADA SEM DEV | M54: Validado HNK já recebido Demonstrativo de crédito | N54: Finalizado
A55: 27/12/2024 | B55: DIARIA DE DESCARGA | C55: 776211 | D55: 11080757 | E55: GUARULHOS X PONTA GROSSA | F55: 502325 | G55: 1488866 | H55: A62440 | I55: MFI7B86 | J55: R$ 800,00 | L55: FINALIZADA SEM DEV | M55: Validado HNK já recebido Demonstrativo de crédito | N55: Finalizado
A56: 27/12/2024 | B56: DIARIA DE DESCARGA | C56: 776689 | D56: 11085420 | E56: PONTA GROSSA X FOZ DO IGUAÇU | F56: 2065 | G56: 1491364 | H56: A60560 | I56: ASP6I28 | L56: CANCELADO | M56: Cancelado por Camila | N56: Finalizado
A57: 27/12/2024 | B57: DESCARTE PALLET | C57: 776997 | D57: 11085420 | E57: PONTA GROSSA X FOZ DO IGUAÇU | F57: 2065 | G57: 1491364 | H57: A60560 | I57: ASP6I28 | L57: CANCELADO | N57: Finalizado
A58: 28/12/2024 | B58: DESCARTE PALLET | C58: 777358 | D58: 11085420 | E58: PONTA GROSSA X FOZ DO IGUAÇU | F58: 2065 | G58: 1491364 | H58: A60560 | I58: ASP6I28 | L58: FINALIZADA SEM DEV | M58: Descarte autorizado por Geovana | N58: Finalizado
A59: 27/12/2024 | B59: TAXA DE DESCARGA | C59: 776996 | D59: 11085420 | E59: PONTA GROSSA X FOZ DO IGUAÇU | F59: 2065 | G59: 1491364 | H59: A60560 | I59: ASP6I28 | J59: R$ 520,00 | L59: FINALIZADA SEM DEV | N59: Aguarda Demonst. Crédito
A60: 28/12/2024 | B60: DIARIA DE DESCARGA | C60: 777369 | D60: 11073694 | E60: ITAPETININGA X PONTA GROSSA | F60: 503077 | G60: 1493366 | H60: A61710 | I60: AZP0H53 | L60: CANCELADO | M60: validado diaria na DT DE RETORNO | N60: Finalizado
A61: 28/12/2024 | B61: AGENDA FUTURA | C61: 778057 | D61: 11101336 | E61: PONTA GROSSA X SÃO LEOPOLDO | F61: - | G61: - | H61: A60790 | I61: DTE2491 | L61: FINALIZADA SEM DEV | M61: Nao validada, só são pagas a partir da data de agendamento origem | N61: Finalizado
A62: 28/12/2024 | B62: DIARIA DE DESCARGA | C62: 778171 | D62: 11073695 | E62: ITAPETININGA X PONTA GROSSA | F62: 503077 | G62: 1493366 | H62: A61710 | I62: AZP0H53 | J62: R$ 800,00 | L62: FINALIZADA SEM DEV | N62: Aguarda Demonst. Crédito
A63: 30/12/2024 | B63: DESCARTE PALLET | C63: 778491 | D63: 11095190 | E63: PONTA GROSSA X SÃO PAULO | F63: 2070 | G63: 1493370 | H63: A63430 | I63: EVO2A67 | L63: FINALIZADA SEM DEV | N63: Finalizado
A64: 30/12/2024 | B64: DESCARTE PALLET | C64: 778596 | D64: 11095190 | E64: PONTA GROSSA X SÃO PAULO | F64: 2070 | G64: 1493370 | H64: A63430 | I64: EVO2A67 | L64: FINALIZADA SEM DEV | M64: Descarte autorizado por MARCELO | N64: Finalizado
A65: 30/12/2024 | B65: DIARIA DE DESCARGA | C65: 778551 | D65: 11057544 | E65: GUARULHOS X PONTA GROSSA | F65: 502712 | G65: 1491118 | H65: A63500 | I65: EFW3B74 | J65: R$ 800,00 | L65: FINALIZADA SEM DEV | N65: Aguarda Demonst. Crédito
A66: 30/12/2024 | B66: DIÁRIA DE DESCARGA | C66: 778577 | D66: 11085004 | E66: ITAPETININGA X PONTA GROSSA | F66: 503396 | G66: 1494205 | H66: A60950 | I66: AMP9049 | J66: R$ 1.600,00 | L66: FINALIZADA SEM DEV | N66: Aguarda Demonst. Crédito
A67: 45689 | B67: AVARIA | C67: 780613 | D67: 11101335 | E67: PONTA GROSSA X TIJUCAS | F67: 2074 | G67: 1495225 | H67: A62920 | I67: BCJ0C22 | L67: FINALIZADA SEM DEV | N67: Finalizado
A68: 45689 | B68: DESCARTE PALLET | C68: 780626 | D68: 11101335 | E68: PONTA GROSSA X TIJUCAS | F68: 2074 | G68: 1495225 | H68: A62920 | I68: BCJ0C22 | L68: FINALIZADA SEM DEV | N68: Finalizado
A69: 45839 | B69: DIÁRIA DE DESCARGA | C69: 784301 | D69: 11106284 | E69: PONTA GROSSA X CURIITBA | F69: 2080 | G69: 1499044 | H69: A61130 | I69: ATJ1E14 | L69: FINALIZADA SEM DEV | N69: Finalizado
A70: 45870 | B70: RET. VAZIO | C70: 785072 | D70: 11096081 | E70: PONTA GROSSA X GUARULHOS | F70: 2082 | G70: 1499039 | H70: A61710 | I70: AZP0H53 | J70: R$ 3.640,00 | L70: FINALIZADA SEM DEV | N70: Aguarda Demonst. Crédito
A71: 45901 | B71: DIÁRIA DE DESCARGA | C71: 786088 | D71: 11116445 | E71: PONTA GROSSA X MARILIA | F71: 2085 | G71: 1499989 | H71: A61510 | I71: NZU2538 | J71: R$ 800,00 | L71: FINALIZADA SEM DEV | N71: Aguarda Demonst. Crédito
A72: 45931 | B72: RET. VAZIO | C72: 786425 | D72: 11119430 | E72: PONTA GROSSA X GUARULHOS | F72: 2089 | G72: 1501460 | H72: A63590 | I72: GHC4E75 | J72: R$ 3.640,00 | L72: FINALIZADA SEM DEV | N72: Aguarda Demonst. Crédito
A73: 45931 | B73: FALTA DE AGENDA | C73: 786433 | D73: 11121906 | E73: PONTA GROSSA X TIJUCAS | F73: 2090 | G73: 1501696 | H73: A60560 | I73: ASP6I28 | J73: R$ 4.000,00 | L73: FINALIZADA SEM DEV | N73: Aguarda Demonst. Crédito
A74: 45931 | B74: FALTA DE AGENDA | C74: 786467 | D74: 11118870 | E74: PONTA GROSSA X TIJUCAS | F74: 2091 | G74: 1501793 | H74: A61130 | I74: ATJ1E14 | J74: R$ 4.000,00 | L74: FINALIZADA SEM DEV | N74: Aguarda Demonst. Crédito
A75: 45992 | B75: DIÁRIA DE DESCARGA | C75: 787236 | D75: 11116446 | E75: MARILIA X PONTA GROSSA | F75: 504826 | G75: 1502837 | H75: A61510 | I75: NZU2538 | J75: R$ 800,00 | L75: FINALIZADA SEM DEV | N75: Aguarda Demonst. Crédito
A76: 13/01/2024 | B76: AVARIA | C76: 787810 | D76: 11122074 | E76: PONTA GROSSA X TIJUCAS | F76: 2093 | G76: 1502855 | H76: A60720 | I76: JZU1A40 | L76: FINALIZADA SEM DEV | N76: Finalizado
A77: 13/01/2024 | B77: DESCARTE PALLET | C77: 787829 | D77: 11122074 | E77: PONTA GROSSA X TIJUCAS | F77: 2093 | G77: 1502855 | H77: A60720 | I77: JZU1A40 | L77: FINALIZADA SEM DEV | M77: Descarte autorizado | N77: Finalizado
A78: 15/01/2025 | B78: AVARIA | C78: 789565 | D78: 11121906 | E78: PONTA GROSSA X TIJUCAS | F78: 2090 | G78: 1501696 | H78: A60560 | I78: ASP6I28 | L78: FINALIZADA SEM DEV | M78: Descarte autorizado | N78: Finalizado
A79: 15/01/2025 | B79: DESCARTE PALLET | C79: 789560 | D79: 11121906 | E79: PONTA GROSSA X TIJUCAS | F79: 2090 | G79: 1501696 | H79: A60560 | I79: ASP6I28 | L79: FINALIZADA SEM DEV | M79: Descarte autorizado | N79: Finalizado
A80: 15/01/2025 | B80: DESCARTE PALLET | C80: 789629 | D80: 11118870 | E80: PONTA GROSSA X TIJUCAS | F80: 2091 | G80: 1501793 | H80: A61130 | I80: ATJ1E14 | L80: FINALIZADA SEM DEV | M80: Descarte autorizado | N80: Finalizado
A81: 15/01/2025 | B81: AVARIA | C81: 789644 | D81: 11118870 | E81: PONTA GROSSA X TIJUCAS | F81: 2091 | G81: 1501793 | H81: A61130 | I81: ATJ1E14 | L81: FINALIZADA SEM DEV | M81: Descarte autorizado | N81: Finalizado
A82: 17/01/2025 | B82: PERDA DE AGENDA | C82: 791609 | D82: 11137473 | E82: PONTA GROSSA X SÃO PAULO | F82: 2098 | G82: 1506690 | H82: A63640 | I82: AEW3F21 | L82: FINALIZADA SEM DEV | N82: Finalizado
A83: 17/01/2025 | B83: DESCARTE PALLET | C83: 791639 | D83: 11101336 | E83: PONTA GROSSA X SÃO LEOPOLDO | F83: 2073 | G83: 1494443 | H83: A60790 | I83: DTE2491 | L83: FINALIZADA SEM DEV | M83: Descarte autorizado | N83: Finalizado
A84: 17/01/2025 | B84: TAXA DE DESCARGA | C84: 791680 | D84: 11101336 | E84: PONTA GROSSA X SÃO LEOPOLDO | F84: 2073 | G84: 1494443 | H84: A60790 | I84: DTE2491 | J84: R$ 280.00 | L84: FINALIZADA SEM DEV | N84: Aguarda Demonst. Crédito
A85: 21/01/2025 | B85: DIÁRIA DE DESCARGA | C85: 793961 | D85: 11145471 | E85: PONTA GROSSA X OSASCO | F85: 2099 | G85: 1509000 | H85: A60560 | I85: ASP6I28 | L85: CANCELADO | M85: Não gerou diária | N85: Finalizado
A86: 23/01/2025 | B86: TAXA DE DESCARGA | C86: 795723 | D86: 11150944 | E86: PONTA GROSSA X MOGI DAS CRUZES | F86: 2100 | G86: 1511196 | H86: A63650 | I86: MEA5F57 | J86: R$ 420.00 | L86: FINALIZADA SEM DEV | N86: Aguarda Demonst. Crédito
A87: 24/01/2025 | B87: DIÁRIA DE DESCARGA | C87: 796353 | D87: 11126513 | E87: GUARULHOS X PONTA GROSSA | F87: 505685 | G87: 1507788 | H87: A63770 | I87: MLL6E83 | J87: R$ 1.600,00 | L87: FINALIZADA SEM DEV | N87: Aguarda Demonst. Crédito
A88: 27/01/2025 | B88: DESCARTE PALLET | C88: 798560 | D88: 11164287 | E88: PONTA GROSSA X OSASCO | F88: 2103 | G88: 1512774 | H88: A61710 | I88: AZP0H53 | L88: FINALIZADA SEM DEV | M88: Descarte aut. por Geovana | N88: Finalizado
A89: 27/01/2025 | B89: RET. VAZIO | C89: 798561 | D89: 11158161 | E89: PONTA GROSSA X GUARULHOS | F89: 2101 | G89: 1512042 | H89: A63640 | I89: AEW3F21 | J89: R$ 3.640,00 | L89: FINALIZADA SEM DEV | N89: Aguarda Demonst. Crédito
A90: 29/01/2025 | B90: DESCARTE PALLET | C90: 800019 | D90: 11166707 | E90: PONTA GROSSA X SÃO PAULO | F90: 2104 | G90: 1513508 | H90: A63680 | I90: APN2H58 | L90: FINALIZADA SEM DEV | M90: AG RET. NO E-MAIL SOBRE OS PALLETS | N90: Finalizado
A91: 30/01/2025 | B91: TAXA DE DESCARGA | C91: 801657 | D91: 11166823 | E91: IGREJINHA X FARROUPILHA | F91: 2107 | G91: 1515426 | H91: IQW4G94 | I91: IQW4G94 | J91: R$ 520.00 | L91: FINALIZADA SEM DEV | N91: Aguarda Demonst. Crédito
A92: 31/01/2025 | B92: DIARIA DE DESCARGA | C92: 802109 | D92: 11161981 | E92: GUARULHOS X PONTA GROSSA | F92: 507342 | G92: 1515738 | H92: A63820 | I92: ATF7H89 | L92: FINALIZADA SEM DEV | M92: Não gerou | N92: Finalizado
A93: 31/01/2025 | B93: TAXA DE DESCARGA | C93: 802215 | D93: 11166701 | E93: IGREJINHA X FARROUPILHA | F93: 2113 | G93: 1517024 | H93: HZE2F70 | I93: HZE2F70 | J93: R$ 400.00 | L93: FINALIZADA SEM DEV | N93: Aguarda Demonst. Crédito
A94: 45659 | B94: DESCARTE PALLET | C94: 802752 | D94: 11180189 | E94: PONTA GROSSA X PORTO BELO | F94: 2109 | G94: 1515983 | H94: A60560 | I94: ASP6I28 | L94: FINALIZADA SEM DEV | M94: Descarte aut. por Marcelo | N94: Finalizado
A95: 45659 | B95: AVARIA | C95: 802756 | D95: 11180189 | E95: PONTA GROSSA X PORTO BELO | F95: 2109 | G95: 1515983 | H95: A60560 | I95: ASP6I28 | L95: FINALIZADA SEM DEV | N95: Finalizado
A96: 45718 | B96: PERDA DE AGENDA | C96: 803369 | D96: 11182082 | E96: PONTA GROSSA X PORTO BELO | F96: 2114 | G96: 1517932 | H96: A63850 | I96: BAN2A60 | L96: FINALIZADA SEM DEV | N96: Finalizado
A97: 45718 | B97: DESCARTE PALLET | C97: 804426 | D97: 11180188 | E97: PONTA GROSSA X PORTO BELO | F97: 2115 | G97: 1517415 | H97: A63860 | I97: GBN9E05 | L97: FINALIZADA SEM DEV | M97: Descarte aut. Geovana | N97: Finalizado
A98: 45718 | B98: AVARIA | C98: 804428 | D98: 11180188 | E98: PONTA GROSSA X PORTO BELO | F98: 2115 | G98: 1517415 | H98: A63860 | I98: GBN9E05 | L98: FINALIZADA SEM DEV | N98: Finalizado
A99: 45718 | B99: DESCARTE PALLET | C99: 805323 | D99: 11182082 | E99: PONTA GROSSA X PORTO BELO | F99: 2114 | G99: 1517932 | H99: A63850 | I99: BAN2A60 | L99: FINALIZADA SEM DEV | M99: Autorizado por Geovana | N99: Finalizado
A100: 45718 | B100: TAXA DE DESCARGA | C100: 805423 | D100: 11182082 | E100: PONTA GROSSA X PORTO BELO | F100: 2114 | G100: 1517932 | H100: A63850 | I100: BAN2A60 | J100: R$ 156.00 | L100: FINALIZADA SEM DEV | N100: Aguarda Demonst. Crédito
...

Sheet RETIRADAS
A1: DT | B1: REMESSA | C1: DATA | D1: PL | E1: Peso | F1: Frete | G1: Canal | H1: Cliente | I1: CNPJ Destinatário | J1: Origem | K1: Cidade | L1: UF | M1: Frota | N1: Tarifa OTM | O1: Margem CF | P1: Valor CF | Q1: OC | R1: Romaneio | S1: Status | T1: Monitoramento (SM) | U1: DT/Hora Chegada Coleta | V1: Saída Coleta | W1: Tempo de Permanência | X1: Agenda Descarga | Y1: DT/ Hora Chegada no Cliente | Z1: Data/Hora Descarga | AA1: Tempo de Permanência | AB1: OC Galileu | AC1: Motivo | AD1: Valor | AE1: Baixa Galileu | AG1: MODALIDADE RETORNO | AH1: DESTINO | AI1: DATA/HORA CARREGAMENTO | AJ1: TEMPO DE ESPERA | AK1: FRETE DE RETORNO | AL1: KM ROTA | AM1: R$/KM
A2: 10921648 | C2: 45302 | D2: 26 | E2: 31.625 | F2: TE01 | G2: ASD | H2: CBD OSASCO - SP | I2: 47.508.411/0832-64 | J2: PONTA GROSSA | K2: OSASCO | L2: SP | M2: - | N2: 6500 | O2: =IFERROR(P2/N2,0) -> 0.65384615 | P2: 4250 | Q2: - | R2: - | S2: RETIRADA
A3: 10921637 | C3: 45302 | D3: 26 | E3: 31.625 | F3: TE01 | G3: ASD | H3: CBD OSASCO - SP | I3: 47.508.411/0832-64 | J3: PONTA GROSSA | K3: OSASCO | L3: SP | M3: - | N3: 6500 | O3: =IFERROR(P3/N3,0) -> 0.65384615 | P3: 4250 | Q3: - | R3: - | S3: RETIRADA
A4: 10914015 | C4: 45333 | D4: 26 | E4: 31.922 | F4: TE01 | G4: TRF | H4: CDA GUARULHOS-SP | I4: 50.221.019/0089-78 | J4: PONTA GROSSA | K4: GUARULHOS | L4: SP | M4: - | N4: 6200 | O4: =IFERROR(P4/N4,0) -> 0.80645161 | P4: 5000 | R4: - | S4: RETIRADA
A5: 10932681 | C5: 45454 | D5: 26 | E5: 31.922 | F5: TE01 | G5: TRF | H5: CDA GUARULHOS-SP | I5: 50.221.019/0089-78 | J5: PONTA GROSSA | K5: GUARULHOS | L5: SP | M5: - | N5: 6200 | O5: =IFERROR(P5/N5,0) -> 0.68548387 | P5: 4250 | Q5: - | R5: - | S5: RETIRADA
A6: 10932680 | C6: 45454 | D6: 26 | E6: 31.922 | F6: TE01 | G6: TRF | H6: CDA GUARULHOS-SP | I6: 50.221.019/0089-78 | J6: PONTA GROSSA | K6: GUARULHOS | L6: SP | M6: - | N6: 6200 | O6: =IFERROR(P6/N6,0) -> 0.68548387 | P6: 4250 | Q6: - | R6: - | S6: RETIRADA
A7: 10932679 | B7: 1001530134 | C7: 45484 | D7: 26 | E7: 31.922 | F7: TE01 | G7: TRF | H7: CDA GUARULHOS-SP | I7: 50.221.019/0089-78 | J7: PONTA GROSSA | K7: GUARULHOS | L7: SP | M7: - | N7: 6200 | O7: =IFERROR(P7/N7,0) -> 0.68548387 | P7: 4250 | Q7: - | R7: - | S7: RETIRADA
A8: 10928688 | B8: 1001527663 | C8: 45484 | D8: 26 | E8: 31.625 | F8: TE01 | G8: ASD | H8: ATACADAO S.A. PINHAIS-PR | I8: 75.315.333/0177-70 | J8: PONTA GROSSA | K8: PINHAIS | L8: PR OUT. | M8: - | N8: 2600 | O8: =IFERROR(P8/N8,0) -> 0.65384615 | P8: 1700 | Q8: - | R8: - | S8: RETIRADA
A9: 10932123 | B9: 1001529896 | C9: 45515 | D9: 26 | E9: 31.625 | F9: TE01 | G9: ASD | H9: ATACADAO S.A. PINHAIS-PR | I9: 75.315.333/0177-70 | J9: PONTA GROSSA | K9: PINHAIS | L9: PR OUT. | M9: - | N9: 2600 | O9: =IFERROR(P9/N9,0) -> 0.65384615 | P9: 1700 | Q9: - | R9: - | S9: RETIRADA
A10: 10937185 | C10: 45607 | D10: 26 | E10: 31.922 | F10: TE01 | G10: ASD | H10: CBD SÃO PAULO-SP | I10: 47.508.411/2627-89 | J10: PONTA GROSSA | K10: SÃO PAULO | L10: SP | M10: - | N10: 6700 | O10: =IFERROR(P10/N10,0) -> 0.67164179 | P10: 4500 | Q10: - | R10: - | S10: RETIRADA
A11: 10939809 | B11: 1001539018 | C11: 45637 | D11: 26 | E11: 31.922 | F11: TE01 | G11: ASD | H11: CBD SÃO PAULO-SP | I11: 47.508.411/2627-89 | J11: PONTA GROSSA | K11: SÃO PAULO | L11: SP | M11: - | N11: 6700 | O11: =IFERROR(P11/N11,0) -> 0.67164179 | P11: 4500 | Q11: - | R11: - | S11: DECLINADO
A12: 10944408 | B12: 1001543420 | C12: 13/11/2024 | D12: 26 | E12: 31.625 | F12: TE01 | G12: ASD | H12: ATACADAO S.A. PINHAIS-PR | I12: 75.315.333/0177-70 | J12: PONTA GROSSA | K12: PINHAIS | L12: PR OUT. | M12: - | N12: 2600 | O12: =IFERROR(P12/N12,0) -> 0 | P12: - | Q12: - | R12: - | S12: RETIRADA
A13: 10936279 | B13: 1001534062 | C13: 13/11/2024 | D13: 26 | E13: 31625 | F13: TE01 | G13: ASD | H13: CBD SÃO PAULO-SP | I13: 47.508.411/2627-89 | J13: PONTA GROSSA | K13: SÃO PAULO | L13: SP | M13: - | N13: 6700 | O13: =IFERROR(P13/N13,0) -> 0 | P13: - | Q13: - | R13: - | S13: RETIRADA | X13: 15/11/2024 06:00
A14: 10954666 | B14: 1001553098 | C14: 16/11/2024 | D14: 26 | E14: 33,43 | F14: TE01 | G14: ASD | H14: JAD ZOGNHEIB & CIA BAURU/SP | I14: 53.045.266/0001-17 | J14: PONTA GROSSA | K14: BAURU | L14: SP INT. | M14: - | N14: 5317 | O14: =IFERROR(P14/N14,0) -> 0 | P14: - | Q14: - | R14: - | S14: DECLINADO | X14: 19/11/2024 11:00
A15: 10957190 | B15: 1001555346 | C15: 16/11/2024 | D15: 26 | E15: 31.922 | F15: TE01 | G15: TRF | H15: CDA GUARULHOS-SP | I15: 50.221.019/0089-78 | J15: PONTA GROSSA | K15: GUARULHOS | L15: SP | M15: - | N15: 6200 | O15: =IFERROR(P15/N15,0) -> 0 | P15: - | Q15: - | R15: - | S15: DECLINADO
A16: 10959222 | B16: 1001558003 | C16: 16/11/2024 | D16: 26 | E16: 30847 | F16: TE02 | G16: DTB | H16: LAGO AZUL JUNDIAÍ-SP | I16: 58.844.424/0001-12 | J16: PONTA GROSSA | K16: JUNDIAÍ | L16: SP INT. | M16: - | N16: 5460 | O16: =IFERROR(P16/N16,0) -> 0 | P16: - | Q16: - | R16: - | S16: DECLINADO
A17: 10959223 | B17: 1001558001 | C17: 16/11/2024 | D17: - | E17: - | F17: TE02 | G17: DTB | H17: RETORNO TE02 LAGO AZUL JUNDIAÍ-SP | I17: 58.844.424/0001-12 | J17: JUNDIAÍ | K17: PONTA GROSSA | L17: TE02 | M17: - | N17: 4360 | O17: =IFERROR(P17/N17,0) -> 0 | P17: - | Q17: - | R17: - | S17: DECLINADO
A18: 10961708 | B18: 1001559552 | C18: 18/11/2024 | D18: 26 | E18: 31.625 | F18: TE01 | G18: TRF | H18: CDA GUARULHOS-SP | I18: 50.221.019/0089-78 | J18: PONTA GROSSA | K18: GUARULHOS | L18: SP | M18: - | N18: 6200 | O18: =IFERROR(P18/N18,0) -> 0 | P18: - | Q18: - | R18: - | S18: DECLINADO
A19: 10957533 | B19: 1001555680 | C19: 18/11/2024 | D19: 26 | E19: 31.922 | F19: TE01 | G19: TRF | H19: CDA GUARULHOS-SP | I19: 50.221.019/0089-78 | J19: PONTA GROSSA | K19: GUARULHOS | L19: SP | M19: - | N19: 6200 | O19: =IFERROR(P19/N19,0) -> 0 | P19: - | Q19: - | R19: - | S19: DECLINADO
A20: 10974235 | B20: 1001574088 | C20: 21/11/2024 | D20: 26 | E20: 29.747 | F20: TE02 | G20: DTB | H20: LAGO AZUL JUNDIAÍ-SP | I20: 58.844.424/0001-12 | J20: PONTA GROSSA | K20: JUNDIAÍ | L20: SP INT. | M20: CM Leonardo SP | N20: 5460 | O20: =IFERROR(P20/N20,0) -> 0 | S20: RETIRADA
A21: 10974240 | B21: 1001574091 | C21: 21/11/2024 | D21: - | E21: - | F21: TE02 | G21: DTB | H21: RETORNO TE02 LAGO AZUL JUNDIAÍ-SP | I21: 58.844.424/0001-12 | J21: JUNDIAÍ | K21: PONTA GROSSA | L21: TE02 | M21: CM Leonardo SP | N21: 4360 | O21: =IFERROR(P21/N21,0) -> 0 | S21: RETIRADA
A22: 10995377 | B22: 1001596036 | C22: 28/11/2024 | D22: 26 | E22: 31.526 | F22: TE02 | G22: TRF | H22: CDA CURITIBA-PR | I22: 50.221.019/0083-82 | J22: PONTA GROSSA | K22: CURITIBA | L22: PR | N22: 2402.4 | O22: =IFERROR(P22/N22,0) -> 0 | S22: RETIRADA
A23: 10995398 | B23: 1001596090 | C23: 28/11/2024 | D23: - | E23: - | F23: TE02 | G23: TRF | H23: (RETORNO TE02) CDA CURITIBA-PR | I23: 50.221.019/0083-82 | J23: CURITIBA | K23: PONTA GROSSA | L23: PR | N23: 1601.6 | O23: =IFERROR(P23/N23,0) -> 0 | S23: RETIRADA
A24: 10989507 | B24: 1001592302 | C24: 26/11/2024 | D24: 26 | E24: 33.139 | F24: TE01 | G24: ASD | H24: SUPERMERCADOS JAU SERVE LTDA JAÚ/SP | I24: 03.640.467/0011-66 | J24: PONTA GROSSA | K24: JAÚ | L24: SP INT. | M24: A61400 | N24: 5625 | O24: =IFERROR(P24/N24,0) -> 0 | Q24: OK | R24: 5427243 | S24: DECLINADO
A25: 10983846 | B25: 1001584894 | C25: 27/11/2024 | D25: 26 | E25: 31.489 | F25: TE01 | G25: ASD | H25: CASA AVENIDA COMERCIO E IMPORTAÇÃO CANDIDO MOTA SP | J25: PONTA GROSSA | K25: CANDIDO MOTA | L25: SP | N25: 5163 | O25: =IFERROR(P25/N25,0) -> 0 | S25: DECLINADO | X25: 28/11/2024 06:00
A26: 10994933 | B26: 1001596250 | C26: 27/11/2024 | D26: 22 | E26: 26.759 | F26: TE01 | G26: ASD | H26: ATACADÃO PORTO VELHO/RO | I26: 75.315.333/0213-78 | J26: PONTA GROSSA | K26: PORTO VELHO | L26: RO | N26: 29800 | O26: =IFERROR(P26/N26,0) -> 0 | S26: DECLINADO | X26: 45485.25
A27: 10989528 | B27: 1001592301 | C27: 28/11/2024 | D27: 26 | E27: 33.139 | F27: TE01 | G27: ASD | H27: SUPERMERCADOS JAU SERVE LTDA JAÚ/SP | I27: 03.640.467/0011-66 | J27: PONTA GROSSA | K27: JAÚ | L27: SP INT. | M27: A63080 | N27: 5625 | O27: =IFERROR(P27/N27,0) -> 0 | Q27: OK | R27: 1470837 | S27: DECLINADO | T27: 5941448
A28: 10994935 | B28: 1001596212 | C28: 29/11/2024 | D28: 26 | E28: 31.625 | F28: TE01 | G28: ASD | H28: ATACADÃO PORTO VELHO/RO | I28: 75.315.333/0213-78 | J28: PONTA GROSSA | K28: PORTO VELHO | L28: RO | N28: 29800 | O28: =IFERROR(P28/N28,0) -> 0 | S28: DECLINADO
A29: 10994146 | B29: 1001594356 | C29: 30/11/2024 | D29: 26 | E29: 30.961 | F29: TE01 | G29: ASD | H29: ATACADÃO SÃO PAULO/SP | I29: 75.315.333/0111-43 | J29: PONTA GROSSA | K29: SÃO PAULO | L29: SP | N29: 6700 | O29: =IFERROR(P29/N29,0) -> 0 | S29: DECLINADO
A30: 10997620 | B30: 1001598407 | C30: 45334 | D30: 26 | E30: 30.961 | F30: TE01 | G30: ASD | H30: ATACADÃO SÃO PAULO/SP | I30: 75.315.333/0111-43 | J30: PONTA GROSSA | K30: SÃO PAULO | L30: SP | N30: 6700 | O30: =IFERROR(P30/N30,0) -> 0 | S30: DECLINADO
A31: 11002562 | B31: 1001605210 | C31: 45334 | D31: 26 | E31: 31.625 | F31: TE01 | G31: TRF | H31: CDA GUARULHOS-SP | I31: 50.221.019/0089-78 | J31: PONTA GROSSA | K31: GUARULHOS | L31: SP | N31: 6200 | O31: =IFERROR(P31/N31,0) -> 0 | S31: DECLINADO
A32: 11025248 | B32: 1001624039 | C32: 45485 | D32: 26 | E32: 31.625 | F32: TE01 | G32: TRF | H32: CDA GUARULHOS-SP | I32: 50.221.019/0089-78 | J32: PONTA GROSSA | K32: GUARULHOS | L32: SP | N32: 6200 | O32: =IFERROR(P32/N32,0) -> 0 | S32: DECLINADO
A33: 11026795 | B33: 1001626393 | C33: 45547 | D33: 26 | E33: 31.922 | F33: TE01 | G33: TRF | H33: CDA GUARULHOS-SP | I33: 50.221.019/0089-78 | J33: PONTA GROSSA | K33: GUARULHOS | L33: SP | N33: 6200 | O33: =IFERROR(P33/N33,0) -> 0 | R33: 5435890 | S33: DECLINADO
A34: 11077710 | B34: 1001681482 | C34: 23/12/2024 | D34: 26 | E34: 32.597 | F34: TE01 | G34: DTB | H34: LAGO AZUL REGENTE FEIJÓ-SP | I34: 58.844.424/0003-84 | J34: PONTA GROSSA | K34: REGENTE FEIJÓ | L34: SP INT. | N34: 6161 | O34: 0 | S34: RETIRADA
A35: 11081506 | B35: 1001681769 | C35: 23/12/2024 | D35: 26 | E35: 33.431 | F35: TE01 | G35: DTB | H35: CDA CURITIBA-PR | I35: 50.221.019/0083-82 | J35: PONTA GROSSA | K35: CURITIBA | L35: PR | N35: 2696 | O35: =IFERROR(P35/N35,0) -> 0.15133531 | P35: 408 | Q35: OK | R35: 5444677 | S35: DECLINADO
A36: 11081521 | B36: 1001681808 | C36: 23/12/2024 | D36: 26 | E36: 33.431 | F36: TE01 | G36: DTB | H36: CDA CURITIBA-PR | I36: 50.221.019/0083-82 | J36: PONTA GROSSA | K36: CURITIBA | L36: PR | N36: 2696 | O36: =IFERROR(P36/N36,0) -> 0.15133531 | P36: 408 | Q36: OK | R36: 5444678 | S36: DECLINADO
A37: 11085535 | B37: 1001683670 | C37: 23/12/2024 | D37: 26 | E37: 32.504 | F37: TE01 | G37: ASD | H37: CASA AVENIDA COMERCIO E IMPORTAÇÃO CANDIDO MOTA SP | I37: 44.358.067/0037-89 | J37: PONTA GROSSA | K37: CANDIDO MOTA | L37: SP INT. | N37: 5317 | O37: =IFERROR(P37/N37,0) -> 0 | S37: DECLINADO
A38: 11113011 | B38: 1001708005 | C38: 45839 | D38: 26 | E38: 29.208 | F38: TE02 | G38: TRF | H38: CDA CURITIBA-PR | I38: 50.221.019/0083-82 | J38: PONTA GROSSA | K38: CURITIBA | L38: PR | M38: A61510 | N38: 2402.4 | O38: =IFERROR(P38/N38,0) -> 0 | S38: RETIRADA
A39: 11115252 | B39: 1001709813 | C39: 45536 | D39: 26 | E39: 30.02 | F39: TE02 | G39: TRF | H39: CDA GUARULHOS-SP | I39: 50.221.019/0089-78 | J39: PONTA GROSSA | K39: GUARULHOS | L39: SP | N39: 5460 | O39: =IFERROR(P39/N39,0) -> 0 | S39: RETIRADA
A40: 11115253 | B40: 1001709777 | C40: 45536 | D40: 3 | E40: 4.819 | F40: TE02 | G40: TRF | H40: RETORNO TE02 CDA GUARULHOS-SP | I40: 05.254.957/0028-06 | J40: GUARULHOS | K40: PONTA GROSSA | L40: PR OUT. | N40: 3640 | O40: =IFERROR(RETIRADAS!P39/RETIRADAS!N39,0) -> 0 | S40: RETIRADA
A41: 11126361 | B41: 1001723407 | C41: 15/01/2025 | D41: 26 | E41: 31.625 | F41: TE01 | G41: TRF | H41: CDA GUARULHOS-SP | I41: 50.221.019/0089-78 | J41: PONTA GROSSA | K41: GUARULHOS | L41: SP | N41: 6200 | O41: =IFERROR(P41/N41,0) -> 0 | S41: RETIRADA
A42: 11126360 | B42: 1001723381 | C42: 15/01/2025 | D42: 26 | E42: 31.625 | F42: TE01 | G42: TRF | H42: CDA GUARULHOS-SP | I42: 50.221.019/0089-78 | J42: PONTA GROSSA | K42: GUARULHOS | L42: SP | N42: 6200 | O42: =IFERROR(P42/N42,0) -> 0 | S42: RETIRADA
A43: 11137474 | B43: 1001734778 | C43: 16/01/2025 | D43: 26 | E43: 31.533 | F43: TE01 | G43: DTB | H43: LAGO AZUL JUNDIAÍ-SP | I43: 58.844.424/0001-12 | J43: PONTA GROSSA | K43: JUNDIAÍ | L43: SP | N43: 6200 | O43: =IFERROR(P42/N42,0) -> 0 | S43: RETIRADA
A44: 11137703 | B44: 1001734682 | C44: 18/01/2025 | D44: 20 | E44: 25.601 | F44: TE01 | G44: ASD | H44: CARREFOUR PINHAIS-PR | J44: PONTA GROSSA | K44: PINHAIS | L44: PR OUT. | N44: 2600 | O44: =IFERROR(P43/N43,0) -> 0 | S44: RETIRADA
A45: 11137704 | B45: 1001734692 | C45: 18/01/2025 | D45: 20 | E45: 25.045 | F45: TE01 | G45: ASD | H45: CARREFOUR PINHAIS-PR | J45: PONTA GROSSA | K45: PINHAIS | L45: PR OUT. | N45: 2000 | O45: =IFERROR(#REF!/#REF!,0) -> 0 | S45: RETIRADA
A46: 11126511 | B46: 1001723246 | C46: 14/01/2025 | D46: 26 | E46: 32.553 | F46: TE02 | G46: TRF | H46: CDA GUARULHOS-SP | I46: 50.221.019/0089-78 | J46: PONTA GROSSA | K46: GUARULHOS | L46: SP | N46: 5460 | O46: =IFERROR(P46/N46,0) -> 0 | S46: FALTA DE VEÍCULO
A47: 11126512 | B47: 1001723245 | C47: 14/01/2025 | D47: 3 | E47: 15.911 | F47: TE02 | G47: TRF | H47: RETORNO TE02 CDA GUARULHOS-SP | I47: 05.254.957/0028-06 | J47: GUARULHOS | K47: PONTA GROSSA | L47: PR OUT. | N47: 3640 | O47: =IFERROR(P46/N46,0) -> 0 | S47: FALTA DE VEÍCULO
A48: 11144632 | B48: 1001742740 | C48: 20/01/2025 | D48: 26 | E48: 31.625 | F48: TE01 | G48: DTB | H48: LAGO AZUL JUNDIAÍ-SP | I48: 58.844.424/0001-12 | J48: PONTA GROSSA | K48: JUNDIAÍ | L48: SP INT. | N48: 6200 | S48: RETIRADA
A49: 11144761 | B49: 1001742575 | C49: 20/01/2025 | D49: 26 | E49: 31.347 | F49: TE02 | G49: TRF | H49: CDA GUARULHOS-SP | I49: 50.221.019/0089-78 | J49: PONTA GROSSA | K49: GUARULHOS | L49: SP | N49: 5460 | O49: =IFERROR(P49/N49,0) -> 0 | S49: RETIRADA
A50: 11144762 | B50: 1001742433 | C50: 20/01/2025 | D50: 1 | E50: 111 | F50: TE02 | G50: TRF | H50: RETORNO TE02 CDA GUARULHOS-SP | I50: 05.254.957/0028-06 | J50: GUARULHOS | K50: PONTA GROSSA | L50: PR OUT. | N50: 3640 | O50: =IFERROR(P50/N50,0) -> 0 | S50: RETIRADA
A51: 11147499 | B51: 1001744954 | C51: 21/01/2025 | D51: 26 | E51: 33.139 | F51: TE01 | G51: TRF | H51: CDA CURITIBA-PR | I51: 50.221.019/0083-82 | J51: PONTA GROSSA | K51: CURITIBA | L51: PR | N51: 2696 | O51: =IFERROR(P51/N51,0) -> 0 | S51: RETIRADA
A52: 11148686 | B52: 1001746715 | C52: 20/01/2025 | D52: 26 | E52: 33.43 | F52: T01 | G52: ASD | H52: JAD ZOGNHEIB & CIA BAURU/SP | I52: 53.045.266/0001-17 | J52: PONTA GROSSA | K52: BAURU | L52: SP | N52: 5317 | O52: =IFERROR(P52/N52,0) -> 0 | S52: FALTA DE VEÍCULO | X52: 22/01 10:00
A53: 11151226 | B53: 1001750071 | C53: 21/01/2025 | D53: 26 | E53: 31.648 | F53: TE01 | G53: DTB | H53: LAGO AZUL JUNDIAÍ-SP | I53: 58.844.424/0001-12 | J53: PONTA GROSSA | K53: JUNDIAÍ | L53: SP INT. | N53: 6200 | O53: =IFERROR(P53/N53,0) -> 0 | S53: RETIRADA
A54: 11147370 | B54: 1001744930 | C54: 22/01/2025 | D54: 26 | E54: 31.625 | F54: TE01 | G54: ASD | H54: CBD OSASCO - SP | I54: 47.508.411/0832-64 | J54: PONTA GROSSA | K54: OSASCO | L54: SP | M54: A63650 | N54: 6500 | O54: =IFERROR(P54/N54,0) -> 0 | S54: RETIRADA | X54: 24/01 03:00
A55: 11157908 | B55: 1001755158 | C55: 25/01/2025 | D55: 26 | E55: 31.625 | F55: TE01 | G55: TRF | H55: CDA GUARULHOS-SP | I55: 50.221.019/0089-78 | J55: PONTA GROSSA | K55: GUARULHOS | L55: SP | N55: 6200 | O55: =IFERROR(P55/N55,0) -> 0 | S55: RETIRADA
A56: 11157896 | B56: 1001755190 | C56: 25/01/2025 | D56: 26 | E56: 31.625 | F56: TE01 | G56: TRF | H56: CDA GUARULHOS-SP | I56: 50.221.019/0089-78 | J56: PONTA GROSSA | K56: GUARULHOS | L56: SP | N56: 6200 | O56: =IFERROR(P56/N56,0) -> 0 | S56: RETIRADA
A57: 11161510 | B57: 1001758746 | C57: 28/01/2025 | D57: 26 | E57: 31.625 | F57: TE01 | G57: DTB | H57: LAGO AZUL JUNDIAÍ-SP | I57: 58.844.424/0001-12 | J57: PONTA GROSSA | K57: JUNDIAÍ | L57: SP INT. | N57: 6200 | O57: =IFERROR(P57/N57,0) -> 0 | S57: RETIRADA
A58: 11166420 | B58: 1001763859 | C58: 29/01/2025 | D58: 26 | E58: 31.625 | F58: TE01 | G58: DTB | H58: LAGO AZUL JUNDIAÍ-SP | I58: 58.844.424/0001-12 | J58: PONTA GROSSA | K58: JUNDIAÍ | L58: SP INT. | N58: 6200 | O58: =IFERROR(P58/N58,0) -> 0 | S58: RETIRADA
A59: 11170683 | B59: 1001768551 | C59: 27/01/2025 | D59: 26 | E59: 31.625 | F59: TE01 | G59: TRF | H59: CDA GUARULHOS-SP | I59: 50.221.019/0089-78 | J59: PONTA GROSSA | K59: GUARULHOS | L59: SP | N59: 6200 | O59: =IFERROR(P59/N59,0) -> 0 | S59: RETIRADA
A60: 11170704 | B60: 1001768475 | C60: 28/01/2025 | D60: 26 | E60: 31.625 | F60: TE01 | G60: TRF | H60: CDA GUARULHOS-SP | I60: 50.221.019/0089-78 | J60: PONTA GROSSA | K60: GUARULHOS | L60: SP | N60: 6200 | O60: =IFERROR(P60/N60,0) -> 0 | S60: RETIRADA
A61: 11171053 | B61: 1001768504 | C61: 28/01/2025 | D61: 26 | E61: 31.625 | F61: TE01 | G61: TRF | H61: CDA CURITIBA-PR | I61: 50.221.019/0083-82 | J61: PONTA GROSSA | K61: CURITIBA | L61: PR | M61: A60690 | N61: 2696 | O61: =IFERROR(P61/N61,0) -> 0 | S61: RETIRADA
A62: 11171052 | B62: 1001768510 | C62: 29/01/2025 | D62: 26 | E62: 31.625 | F62: TE01 | G62: TRF | H62: CDA CURITIBA-PR | I62: 50.221.019/0083-82 | J62: PONTA GROSSA | K62: CURITIBA | L62: PR | N62: 2696 | O62: =IFERROR(P62/N62,0) -> 0 | S62: RETIRADA
A63: 11178683 | B63: 1001774084 | C63: 45659 | D63: 26 | E63: 34.933 | F63: TE01 | G63: ASD | H63: ATACADAO S.A | I63: 75.315.333/0242-02 | J63: IGREJINHA | K63: VIAMÃO | L63: RS | N63: 3143 | O63: =IFERROR(P63/N63,0) -> 0 | S63: RETIRADA | X63: 45718.208
A64: 11182763 | B64: 1001780024 | C64: 45659 | D64: 26 | E64: 25.337 | F64: TE01 | G64: ASD | H64: CBD OSASCO - SP | I64: 47.508.411/0832-64 | J64: PONTA GROSSA | K64: OSASCO | L64: SP | N64: 6500 | O64: =IFERROR(P64/N64,0) -> 0 | S64: RETIRADA | X64: 45718
A65: 11176141 | B65: 1001772508 | C65: 45659 | D65: 26 | E65: 34.933 | F65: TE01 | G65: ASD | H65: PASSARELA CENTER LTDA | I65: 03.107.202/0024-11 | J65: IGREJINHA | K65: ESTRELA | L65: RS | M65: HZE2F70 | N65: 3423 | O65: =IFERROR(P65/N65,0) -> 0 | S65: RETIRADA | X65: 45718.292
A66: 11172545 | B66: 1001768999 | C66: 31/01/2025 | D66: 26 | E66: 31.922 | F66: TE01 | G66: ASD | H66: CBD OSASCO - SP | I66: 47.508.411/0832-64 | J66: PONTA GROSSA | K66: OSASCO | L66: SP | M66: A63910 | N66: 6500 | O66: =IFERROR(P66/N66,0) -> 0 | Q66: OK | S66: RETIRADA | X66: 45690.083
A67: 11195843 | B67: 1001792103 | C67: 45932 | D67: 26 | E67: 31.922 | F67: TE01 | G67: TRF | H67: CDA GUARULHOS-SP | I67: 47.508.411/0106-23 | J67: PONTA GROSSA | K67: GUARULHOS | L67: SP | N67: 6200 | O67: =IFERROR(P67/N67,0) -> 0 | S67: RETIRADA
A68: 11196058 | B68: 1001792139 | C68: 45932 | D68: 26 | E68: 31.922 | F68: TE01 | G68: TRF | H68: CDA GUARULHOS-SP | I68: 47.508.411/0106-23 | J68: PONTA GROSSA | K68: GUARULHOS | L68: SP | N68: 6200 | O68: =IFERROR(P68/N68,0) -> 0 | S68: RETIRADA
A69: 11196059 | B69: 1001792244 | C69: 45932 | D69: 26 | E69: 33.43 | F69: TE01 | G69: TRF | H69: CDA GUARULHOS-SP | I69: 47.508.411/0106-23 | J69: PONTA GROSSA | K69: GUARULHOS | L69: SP | N69: 6677 | O69: =IFERROR(P69/N69,0) -> 0 | S69: RETIRADA
A70: 11201206 | B70: 1001798095 | C70: 13/02/2025 | D70: 26 | E70: 33.43 | F70: TE01 | G70: TRF | H70: CDA CURITIBA-PR | I70: 50.221.019/0083-82 | J70: PONTA GROSSA | K70: CURITIBA | L70: PR OUT. | N70: 2696 | O70: =IFERROR(P70/N70,0) -> 0 | S70: RETIRADA
A71: 11204061 | B71: 1001801727 | C71: 13/02/2025 | D71: 26 | E71: 31.625 | F71: TE01 | G71: TRF | H71: CDA GUARULHOS-SP | I71: 50.221.019/0089-78 | J71: PONTA GROSSA | K71: GUARULHOS | L71: SP | N71: 6200 | O71: =IFERROR(P71/N71,0) -> 0 | S71: RETIRADA
A72: 11204060 | B72: 1001801725 | C72: 13/02/2025 | D72: 26 | E72: 31.625 | F72: TE01 | G72: TRF | H72: CDA GUARULHOS-SP | I72: 50.221.019/0089-78 | J72: PONTA GROSSA | K72: GUARULHOS | L72: SP | N72: 6200 | O72: =IFERROR(P72/N72,0) -> 0 | S72: RETIRADA
A73: 11212915 | B73: 1001809908 | C73: 14/02/2025 | D73: 26 | E73: 31.625 | F73: TE01 | G73: TRF | H73: CDA GUARULHOS-SP | I73: 50.221.019/0089-78 | J73: PONTA GROSSA | K73: GUARULHOS | L73: SP | N73: 6200 | O73: =IFERROR(P73/N73,0) -> 0 | S73: RETIRADA
A74: 11213545 | B74: 1001809978 | C74: 14/02/2025 | D74: 26 | E74: 31.625 | F74: TE01 | G74: TRF | H74: CDA GUARULHOS-SP | I74: 50.221.019/0089-78 | J74: PONTA GROSSA | K74: GUARULHOS | L74: SP | N74: 6200 | O74: =IFERROR(P74/N74,0) -> 0 | S74: RETIRADA | X74: ORDEM
A75: 11217494 | B75: 1001814292 | C75: 14/02/2025 | D75: 26 | E75: 31.625 | F75: TE01 | G75: TRF | H75: CDA GUARULHOS-SP | I75: 50.221.019/0089-78 | J75: PONTA GROSSA | K75: GUARULHOS | L75: SP | N75: 6200 | O75: =IFERROR(P75/N75,0) -> 0 | S75: RETIRADA | X75: ORDEM
A76: 11210652 | B76: 1001806804 | C76: 15/02/2025 | D76: 20 | E76: 25.716 | F76: TE01 | G76: ASD | H76: AM/PM COMESTÍVEIS LTDA | I76: 40.299.810/0030-40 | J76: PONTA GROSSA | K76: SÃO JOSE DOS PINHAIS | L76: PR OUT. | N76: 2900 | O76: =IFERROR(P76/N76,0) -> 0 | S76: RETIRADA | X76: 17/02 07:30
A77: 11217359 | B77: 1001814308 | C77: 17/02/2025 | D77: 26 | E77: 31.625 | F77: TE01 | G77: TRF | H77: CDA GUARULHOS-SP | I77: 50.221.019/0089-78 | J77: PONTA GROSSA | K77: GUARULHOS | L77: SP | N77: 6200 | O77: 0,00% | S77: RETIRADA
A78: 11217358 | B78: 1001814235 | C78: 15/02/2025 | D78: 26 | E78: 31.625 | F78: TE01 | G78: TRF | H78: CDA GUARULHOS-SP | I78: 50.221.019/0089-78 | J78: PONTA GROSSA | K78: GUARULHOS | L78: SP | N78: 6200 | O78: 0,00% | S78: RETIRADA
A79: 11217360 | B79: 1001814286 | C79: 17/02/2025 | D79: 26 | E79: 31.625 | F79: TE01 | G79: TRF | H79: CDA GUARULHOS-SP | I79: 50.221.019/0089-78 | J79: PONTA GROSSA | K79: GUARULHOS | L79: SP | N79: 6200 | O79: 0,00% | S79: RETIRADA
A80: 11219364 | B80: 1001817565 | C80: 17/02/2025 | D80: 26 | E80: 31.625 | F80: TE01 | G80: TRF | H80: CDA GUARULHOS-SP | I80: 50.221.019/0089-78 | J80: PONTA GROSSA | K80: GUARULHOS | L80: SP | N80: 6200 | O80: 0,00% | S80: RETIRADA
A81: 11224839 | B81: 1001822471 | C81: 19/02/2025 | D81: 26 | E81: 31.625 | F81: TE01 | G81: DTB | H81: LAGO AZUL MARÍLIA-SP | I81: 58.844.424/0002-01 | J81: PONTA GROSSA | K81: MARÍLIA | L81: SP INT. | N81: 5323 | O81: =IFERROR(P81/N81,0) -> 0 | S81: RETIRADA | X81: ORDEM
A82: 11225308 | B82: 1001821913 | C82: 19/02/2025 | D82: 26 | E82: 33.43 | F82: TE01 | G82: TRF | H82: CDA CURITIBA-PR | I82: 50.221.019/0083-82 | J82: PONTA GROSSA | K82: CURITIBA | L82: PR OUT. | N82: 2696 | O82: =IFERROR(P82/N82,0) -> 0 | S82: RETIRADA
A83: 11225309 | B83: 1001821915 | C83: 19/02/2025 | D83: 26 | E83: 33.43 | F83: TE01 | G83: TRF | H83: CDA CURITIBA-PR | I83: 50.221.019/0083-82 | J83: PONTA GROSSA | K83: CURITIBA | L83: PR OUT. | N83: 2696 | O83: =IFERROR(P83/N83,0) -> 0 | S83: RETIRADA
A84: 11229448 | B84: 1001825850 | C84: 22/02/2025 | D84: 26 | E84: 31.625 | F84: TE01 | G84: DTB | H84: LAGO AZUL JUNDIAÍ-SP | I84: 58.844.424/0001-12 | J84: PONTA GROSSA | K84: JUNDIAÍ | L84: SP | N84: 6200 | O84: =IFERROR(P84/N84,0) -> 0 | S84: RETIRADA
A85: 11229537 | B85: 1001825874 | C85: 22/02/2025 | D85: 26 | E85: 31.922 | F85: TE01 | G85: DTB | H85: LAGO AZUL JUNDIAÍ-SP | I85: 58.844.424/0001-12 | J85: PONTA GROSSA | K85: JUNDIAÍ | L85: SP | N85: 6200 | O85: =IFERROR(P85/N85,0) -> 0 | S85: RETIRADA
A86: 11229645 | B86: 1001825849 | C86: 22/02/2025 | D86: 26 | E86: 31.625 | F86: TE01 | G86: DTB | H86: LAGO AZUL JUNDIAÍ-SP | I86: 58.844.424/0001-12 | J86: PONTA GROSSA | K86: JUNDIAÍ | L86: SP | N86: 6200 | O86: =IFERROR(P86/N86,0) -> 0 | S86: RETIRADA
A87: 11251332 | B87: 1001850099 | C87: 27/02/2025 | D87: 26 | E87: 30.737 | F87: TE02 | G87: DTB | H87: IRMÃOS CANCELLI LTDA | I87: 82.939.307/0005-40 | J87: IGREJINHA | K87: JOAÇABA | L87: SC | N87: 5281 | O87: =IFERROR(P87/N87,0) -> 0 | S87: RETIRADA
A88: 11251334 | B88: 1001850108 | C88: 27/02/2025 | D88: 8 | E88: 7.222 | F88: TE02 | G88: DTB | H88: RETORNO TE02 IRMÃOS CANCELLI LTDA | I88: 82.939.307/0005-40 | J88: JOAÇABA | K88: IGREJINHA | L88: RS | N88: 3520 | O88: =IFERROR(P88/N88,0) -> 0 | S88: RETIRADA
A89: 11241681 | B89: 1001837352 | C89: 26/02/2025 | D89: 26 | E89: 33.43 | F89: TE01 | G89: DTB | H89: LAGO AZUL JUNDIAÍ-SP | I89: 58.844.424/0001-12 | J89: PONTA GROSSA | K89: JUNDIAÍ | L89: SP INT. | N89: 6677 | O89: =IFERROR(P89/N89,0) -> 0 | P89: KM | S89: FALTA DE VEÍCULO
A90: 11251230 | B90: 1001849695 | C90: 45719 | D90: 26 | E90: 27.033 | F90: TE02 | G90: TRF | H90: CDA CURITIBA-PR | I90: 50.221.019/0083-82 | J90: PONTA GROSSA | K90: CURITIBA | L90: TE02 PR | N90: 2402 | O90: =IFERROR(P90/N90,0) -> 0 | S90: RETIRADA
A91: 11251231 | B91: 1001849855 | C91: 45719 | D91: 1 | E91: 962 | F91: TE02 | G91: TRF | H91: RETORNO TE02 CDA CURITIBA-PR | I91: 50.221.019/0083-82 | J91: CURITIBA | K91: PONTA GROSSA | L91: TE02 PR | N91: 1601 | O91: =IFERROR(P91/N91,0) -> 0 | S91: RETIRADA
A92: 11259300 | B92: 1001859046 | C92: 45811 | D92: 26 | E92: 30.714 | F92: TE02 | G92: TRF | H92: CDA CURITIBA-PR | I92: 50.221.019/0083-82 | J92: PONTA GROSSA | K92: CURITIBA | L92: TE02 PR | N92: 2402 | O92: =IFERROR(P92/N92,0) -> 0 | S92: RETIRADA
A93: 11259301 | B93: 1001858993 | C93: 45811 | D93: 1 | E93: 962 | F93: TE02 | G93: TRF | H93: RETORNO TE02 CDA CURITIBA-PR | I93: 50.221.019/0083-82 | J93: CURITIBA | K93: PONTA GROSSA | L93: TE02 PR | N93: 1601 | O93: =IFERROR(P93/N93,0) -> 0 | S93: RETIRADA
A94: 11254669 | B94: 1001854597 | C94: 27/02/2025 | D94: 26 | E94: 31.625 | F94: TE01 | G94: ASD | H94: CBD OSASCO - SP | I94: 47.508.411/0832-64 | J94: PONTA GROSSA | K94: OSASCO | L94: SP | N94: 6500 | O94: =IFERROR(P94/N94,0) -> 0 | S94: FALTA DE VEÍCULO | X94: 45660.333
A95: 11256144 | B95: 1001854959 | C95: 28/01/2025 | D95: 26 | E95: 31.625 | F95: TE01 | G95: ASD | H95: SDB PORTO BELO-SC | I95: 09.477.652/0057-40 | J95: PONTA GROSSA | K95: PORTO BELO | L95: SC | N95: 5200 | O95: =IFERROR(P95/N95,0) -> 0.67788462 | P95: 3525 | Q95: OK | S95: PROGRAMADO | X95: 45719
A96: 11256143 | B96: 1001855103 | C96: 28/01/2025 | D96: 26 | E96: 31.625 | F96: TE01 | G96: ASD | H96: SDB PORTO BELO-SC | I96: 09.477.652/0057-40 | J96: PONTA GROSSA | K96: PORTO BELO | L96: SC | N96: 5200 | O96: =IFERROR(P96/N96,0) -> 0 | X96: 45719
A97: 11258783 | B97: 1001859225 | C97: 45841 | D97: 26 | E97: 32.111 | F97: TE01 | G97: ASD | H97: AM/PM COMESTÍVEIS LTDA | I97: 40.299.810/0030-40 | J97: PONTA GROSSA | K97: SÃO JOSE DOS PINHAIS | L97: PR OUT. | N97: 3124 | O97: =IFERROR(P97/N97,0) -> 0 | S97: RETIRADA | X97: 45933.292
A98: 11259048 | B98: 1001859254 | C98: 45841 | D98: 24 | E98: 28.304 | F98: TE01 | G98: ASD | H98: AM/PM COMESTÍVEIS LTDA | I98: 40.299.810/0030-40 | J98: PONTA GROSSA | K98: SÃO JOSE DOS PINHAIS | L98: PR OUT. | N98: 2900 | O98: =IFERROR(P98/N98,0) -> 0 | S98: RETIRADA | X98: 45933.292
A99: 11273459 | B99: 1001876712 | C99: 45872 | D99: 26 | E99: 32.553 | F99: TE02 | G99: TRF | H99: CDA GUARULHOS-SP | I99: 50.221.019/0089-78 | J99: PONTA GROSSA | K99: GUARULHOS | L99: SP | N99: 5880 | O99: =IFERROR(P99/N99,0) -> 0 | S99: RETIRADA
A100: 11273461 | B100: 1001876669 | C100: 45872 | D100: 14 | E100: 15.911 | F100: TE02 | G100: TRF | H100: RETORNO TE02 CDA GUARULHOS-SP | I100: 05.254.957/0028-06 | J100: GUARULHOS | K100: PONTA GROSSA | L100: PR OUT. | N100: 3920 | O100: =IFERROR(P100/N100,0) -> 0 | S100: RETIRADA
...

Sheet CUSTO EXTRA
A1: AGREGADO | B1: PLACA | C1: DÍG | D1: CLIENTE | E1: TIPO DE OCORRENCIA | F1: ROTA | G1: DATA | H1: CTE | I1: DT | J1: ROMANEIO | K1: Nº Ocorrencia | L1: VALOR A RECEBER (CLIENTE) | M1: VALOR A PAGAR (MOTORISTA) | N1: SENHA | O1: VALIDAÇÃO | P1: Status Ritmo
A2: AGREGADO | B2: AWC1157 | C2: 57 | D2: KEINEKEN | E2: DIARIA DESCARGA | F2: MARILIA X PONTA GROSSA | G2: 16/10/2024 | H2: 493534 | I2: 10865886 | J2: 1432759 | K2: 728084 | L2: R$ 800,00 | M2: R$ 500,00 | O2: APROVADO | P2: Pago
A3: AGREGADO | B3: AWC1157 | C3: 57 | D3: KEINEKEN | E3: DIARIA CARREGAMENTO | F3: PONTA GROSSA X PINHAIS | H3: - | I3: - | J3: - | M3: R$ 500,00 | P3: Pago
A4: AGREGADO | B4: MFI7B86 | C4: 86 | D4: HEINEKEN | E4: ESTADIA DESCARGA | F4: PONTA GROSSA X TIJUCAS SC | G4: 45302 | H4: 2010 | I4: 10917587 | J4: 1446846 | K4: 733273 | L4: R$ 800,00 | M4: R$ 500,00 | O4: APROVADO | P4: Pago
A5: AGREGADO | B5: ASO5I06 | C5: 6 | D5: HEINEKEN | E5: ESTADIA DESCARGA | F5: PONTA GROSSA X PINHAIS | G5: 21/11/2024 | H5: 2023 | I5: 10961677 | J5: 1463425 | K5: 759955 | L5: R$ 800,00 | M5: R$ 500,00 | O5: APROVADO | P5: Pago
A6: AGREGADO | B6: IEU5D15 | C6: 15 | D6: HEINEKEN | E6: ESTADIA DESCARGA | F6: JOAÇABA X IGREJINHA | G6: 45780 | H6: 43782 | I6: 11251333 | J6: 1540436 | K6: 828065 | L6: R$ 6.363,64 | M6: R$ 2.500.00 | O6: APROVADO | P6: Pago
A7: AGREGADO | B7: AXS2A52 | C7: 52 | D7: HEINEKEN | E7: ESTADIA DESCARGA | F7: GUARULHOS X PONTA GROSSA | G7: 45994 | H7: 512544 | I7: 11273314 | J7: 1544248 | K7: 832540 | L7: R$ 1818.18 | M7: R$ 1.000,00 | O7: APROVADO | P7: Pago
A8: AGREGADO | B8: MIS0H20 | C8: 20 | D8: HEINEKEN | E8: ESTADIA DESCARGA | F8: GUARULHOS X PONTA GROSSA | G8: 18/03/2025 | H8: 513706 | I8: 11277554 | J8: 1548665 | K8: 836622 | L8: R$ 800,00 | M8: R$ 500,00 | O8: APROVADO | P8: Pago
A9: AGREGADO | B9: BAP2G10 | C9: 10 | D9: HEINEKEN | E9: ESTADIA DESCARGA | F9: PONTA GROSSA X OSASCO | G9: 45994 | H9: 2172 | I9: 11265070 | J9: 1540397 | K9: 832415 | L9: R$ 3.636,36 | M9: R$ 1.000,00 | O9: APROVADO | P9: Não pagar
A10: AGREGADO | B10: BAP2G10 | C10: 10 | D10: HEINEKEN | E10: ESTADIA DESCARGA | F10: GUARULHOS X PONTA GROSSA | G10: 26/03/2025 | H10: 514707 | I10: 11300765 | J10: 1553352 | K10: 842290 | L10: R$ 1818.18 | M10: R$ 1.000,00 | O10: APROVADO | P10: Não pagar
A11: AGREGADO | B11: ATX0A70 | C11: 70 | D11: HEINEKEN | E11: ESTADIA DESCARGA | F11: GUARULHOS X PONTA GROSSA | G11: 45720 | H11: 516223 | I11: 11328138 | J11: 1560724 | K11: 850072 | L11: R$ 909,09 | M11: R$ 500,00 | O11: APROVADO | P11: Pago
A12: AGREGADO | B12: MGF4H86 | C12: 86 | D12: HEINEKEN | E12: ESTADIA DESCARGA | F12: PONTA GROSSA X OSASCO | G12: 45841 | H12: 2171 | I12: 11264930 | J12: 1540379 | K12: 829290 | M12: R$ 500,00 | O12: RECUSADA | P12: Pago
A13: AGREGADO | B13: AWD1B98 | C13: 98 | D13: HEINEKEN | E13: ESTADIA DESCARGA | F13: GUARULHOS X PONTA GROSSA | G13: 26/03/2025 | H13: 514820 | I13: 11325509 | J13: 1553802 | K13: 842686 | L13: R$ 800,00 | M13: R$ 500,00 | O13: APROVADO | P13: Pago
A14: AGREGADO | B14: AWD1B98 | C14: 98 | D14: HEINEKEN | E14: ESTADIA DESCARGA | F14: GUARULHOS X PONTA GROSSA | G14: 45720 | H14: 516270 | I14: 11328139 | J14: 1560932 | K14: 851230 | L14: R$2.727.27 | M14: R$ 1.500,00 | O14: APROVADO | P14: Pago
A15: AGREGADO | B15: MIS0H20 | C15: 20 | D15: HEINEKEN | E15: ESTADIA DESCARGA | F15: GUARULHOS X PONTA GROSSA | G15: 45812 | H15: 516540 | I15: 11339160 | J15: 1562285 | K15: 851363 | L15: R$ 1.818.18 | M15: R$ 1.000,00 | O15: APROVADO | P15: Pago
A16: AGREGADO | B16: MGF4H86 | C16: 86 | D16: HEINEKEN | E16: ESTADIA DESCARGA | F16: GUARULHOS X PONTA GROSSA | G16: 45812 | H16: 516482 | I16: 11339161 | J16: 1561927 | K16: 851367 | L16: R$ 1.818.18 | M16: R$ 1.820,00 | O16: APROVADO | P16: Pago
A17: AGREGADO | B17: ATX0A70 | C17: 70 | D17: HEINEKEN | E17: ESTADIA DESCARGA | F17: GUARULHOS X PONTA GROSSA | G17: 45965 | H17: 516670 | I17: 11344828 | J17: 1563051 | K17: 855000 | L17: R$2.727.27 | M17: R$ 1.000,00 | O17: APROVADO | P17: Pago
A18: AGREGADO | B18: AGG7742 | C18: 42 | D18: HEINEKEN | E18: ESTADIA DESCARGA | F18: PINHAIS X PONTA GROSSA | G18: 45719 | I18: 11256395 | K18: 825446 | L18: R$ 3.200,00 | M18: R$ 2.000.00 | O18: APROVADO | P18: Pago
A19: AGREGADO | B19: ATX0A70 | C19: 70 | D19: HEINEKEN | E19: ESTADIA DESCARGA | F19: GUARULHOS X PONTA GROSSA | G19: 45874 | H19: 520543 | I19: 11417243 | J19: 1586421 | K19: 872186 | L19: R$ 1.818.18 | M19: R$ 500,00 | O19: APROVADO | P19: Pago
A20: AGREGADO | B20: AXS2A52 | C20: 52 | D20: HEINEKEN | E20: ESTADIA DESCARGA | F20: GUARULHOS X PONTA GROSSA | G20: 45874 | H20: 520461 | I20: 11432484 | J20: 1586144 | K20: 872091 | L20: R$ 1.818.18 | M20: R$ 500,00 | O20: APROVADO | P20: Pago
A21: AGREGADO | B21: HZE2F70 | C21: 70 | D21: HEINEKEN | E21: TAXA DE DESCARGA | F21: IGREJINHA X ESTRELA | G21: 26/04/2025 | H21: 2226 | I21: 11392188 | J21: 1576116 | K21: 863945 | M21: R$ 450.00 | O21: PENDENTE | P21: Pago
A22: AGREGADO | B22: MIS0H20 | C22: 20 | D22: HEINEKEN | E22: ESTADIA DESCARGA | F22: ITU X PONTA GROSSA | G22: 16/05/2025 | H22: 522000 | I22: 11445917 | J22: 1593490 | K22: 877078 | L22: R$ 1.818.18 | M22: R$ 1.000,00 | O22: APROVADO | P22: Env. pgt
A23: AGREGADO | B23: AWD1B98 | C23: 98 | D23: HEINEKEN | E23: ESTADIA DESCARGA | F23: GUARULHOS X PONTA GROSSA | G23: 15/05/2025 | H23: 521648 | I23: 11441022 | J23: 1592119 | K23: 872186 | L23: R$ 1.818.18 | M23: R$ 1.000,00 | O23: APROVADO | P23: Env. pgt
A24: AGREGADO | B24: MEK4B39 | C24: 39 | D24: HEINEKEN | E24: ESTADIA DESCARGA | F24: ITU X PONTA GROSSA | G24: 16/05/2025 | H24: 521898 | I24: 11445909 | J24: 1593073 | K24: 876826 | L24: R$ 800,00 | M24: R$ 500,00 | O24: APROVADO | P24: Env. pgt
A25: AGREGADO | B25: ATX0A70 | C25: 70 | D25: HEINEKEN | E25: DIARIA DE DESCARGA | F25: GUARULHOS X PONTA GROSSA | G25: 14/04/2025 | H25: 516670 | I25: 11370424 | J25: 1569174 | K25: 858980 | L25: R$ 800.00 | O25: APROVADO GL
A26: AGREGADO | B26: MFY4I74 | C26: 74 | D26: HEINEKEN | E26: TAXA DE DESCARGA | F26: PONTA GROSSA X PINHAIS | G26: 16/04/2025 | H26: 2216 | I26: 11367914 | J26: 1568386 | K26: 858141 | L26: R$ 195.25 | O26: APROVADO
A27: AGREGADO | B27: MBP5D79 | C27: 79 | D27: HEINEKEN | E27: TAXA DE DESCARGA | F27: PONTA GROSSA X PALHOÇA | G27: 27/05/2025 | H27: 2252 | I27: 11455383 | J27: 1598295 | K27: 883868 | L27: R$ 144.00 | O27: APROVADO
A28: AGREGADO | B28: JLQ7H51 | C28: 51 | D28: HEINEKEN | E28: TAXA DE DESCARGA | F28: PONTA GROSSA X PALHOÇA | G28: 29/05/2025 | H28: 2247 | I28: 11450898 | J28: 1595703 | K28: 885447 | L28: R$ 156.00 | O28: APROVADO
A29: AGREGADO | B29: IPK4C72 | C29: 72 | D29: HEINEKEN | E29: DIARIA DE DESCARGA | F29: PONTA GROSSA X ITU | G29: 31/05/2025 | I29: 11483185 | J29: 1607107 | K29: 888933 | L29: 909.09 | M29: R$ 500,00 | O29: APROVADO | P29: Env. pgt
A30: AGREGADO | B30: HZE2F70 | C30: 70 | D30: HEINEKEN | E30: TAXA DE DESCARGA | F30: IGREJINHA X PELOTAS | G30: 45876 | H30: 2279 | I30: 11566124 | J30: 1633595 | K30: 907780 | L30: R$ 390.00 | M30: R$ 390.00 | O30: APROVADO | P30: Env. pgt
A31: AGREGADO | B31: MEK4B39 | C31: 39 | D31: HEINEKEN | E31: ESTADIA DESCARGA | F31: ITU X PONTA GROSSA | G31: 24/05/2025 | I31: 11459595 | J31: 1600671 | K31: 882034 | L31: 909.09 | M31: R$ 500,00 | O31: APROVADO | P31: Env. pgt
A32: AGREGADO | B32: ATQ3B32 | C32: 32 | D32: HEINEKEN | E32: ESTADIA DESCARGA | F32: GUARULHOS X PONTA GROSSA | G32: 20/08/2025 | H32: 523747 | I32: 11460143 | J32: 1602869 | K32: 884676 | L32: R$2.727,27 | M32: R$ 1.500.00 | O32: APROVADO | P32: Env. pgt
A33: AGREGADO | B33: AEW3F21 | C33: 21 | D33: HEINEKEN | E33: RETORNO VAZIO | F33: GUARULHOS X PONTA GROSSA | G33: 15/08/2025 | H33: 2288 | I33: 11665805 | J33: 1669523 | K33: 38270 | L33: R$ 4.429.55 | O33: APROVADO | P33: PAGO
A34: AGREGADO | B34: IUQ0B97 | C34: 97 | D34: HEINEKEN | E34: TAXA DE DESCARGA | F34: PONTA GROSSA X SJP | G34: 23/08/2025 | H34: 2294 | I34: 11680324 | J34: 1675410 | K34: 43546 | L34: R$ 325.00 | O34: APROVADO | P34: PAGO
A35: AGREGADO | B35: NJQ6C66 | C35: 66 | D35: HEINEKEN | E35: TAXA DE DESCARGA | F35: PONTA GROSSA X MARINGA | G35: 22/08/2025 | H35: 2290 | I35: 11684093 | J35: 1674761 | K35: 43093 | L35: R$ 52.00 | O35: APROVADO | P35: PAGO
A36: AGREGADO | B36: MFY4I74 | C36: 74 | D36: HEINEKEN | E36: ESTADIA DESCARGA | F36: PONTA GROSSA X CAMBE | G36: 45665 | H36: 2284 | I36: 11631881 | J36: 1657830 | K36: 25634 | L36: R$ 4.800.00 | M36: R$ 2.500.00 | O36: APROVADO | P36: Env. pgt
A37: AGREGADO | B37: ATI8J32 | C37: 32 | D37: HEINEKEN | E37: ESTADIA DESCARGA | F37: PONTA GROSSA X CAMBE | G37: 45665 | H37: 2283 | I37: 11631962 | J37: 1657832 | K37: 25552 | L37: R$ 4.800.00 | M37: R$ 2.500.00 | O37: APROVADO | P37: Env. pgt
A38: AGREGADO | B38: AWD1B98 | C38: 98 | D38: HEINEKEN | E38: TAXA DE DESCARGA | F38: PONTA GROSSA X ITU | G38: 23/08/2025 | H38: 2292 | I38: 11689753 | J38: 1675193 | K38: 46561 | L38: R$ 1.337.73 | O38: APROVADO | P38: PAGO

Sheet MONIT. HNK
B1: AGREGADO | C1: PLACA CAVALO | D1: PLACA DA CARRETA | E1: MOTORISTA | F1: LOCALIZAÇÃO | G1: UF | H1: ORIGEM | I1: UF | J1: CIDADE DESTINO | K1: UF | L1: VEÍCULO ESTÁ? CARREGADO/VAZIO | M1: STATUS | N1: OBSERVAÇÃO
A2: 1 | B2: A63800 | C2: MFY4I74 | D2: ASF9J60 | E2: CLAUDINEI | F2: MARINGA | G2: PR | H2: MARINGA | I2: PR | J2: CURITIBA | K2: PR | L2: PROGRAMADO | M2: PROGRAMADO
A3: 2 | B3: A64030 | C3: MEK4B39 | D3: ATR6534 | E3: JOAO | F3: CURITIBA | G3: PR | L3: INDISPONÍVEL | M3: DESAGREGAÇÃO
A4: 4 | B4: A64570 | C4: AWD1B98 | D4: AUR6B22 | E4: EMERSON | F4: SÃO JOSÉ DOS PINHAIS | G4: PR | L4: VAZIO PR/SC/RS | M4: DISPONÍVEL
A5: 5 | B5: A64410 | C5: MIS0H20 | D5: AWO2238 | F5: BLUMENAU | G5: SC | L5: INDISPONÍVEL | M5: MANUTENÇÃO CAVALO
A6: 6 | B6: A66420 | C6: IUQ0B97 | D6: BAA1452 | E6: LAURO | F6: MARINGA | G6: PR | H6: MARINGA | I6: PR | J6: CURITIBA | K6: PR | L6: PROGRAMADO | M6: PROGRAMADO
A7: 7 | B7: A66530 | C7: ANE6H54 | D7: AUR6B01 | E7: PATRICK | F7: PONTA GROSSA | G7: PR | L7: VAZIO PR/SC/RS | M7: DESAGREGAÇÃO
A8: 8 | B8: A66490 | C8: ATI8J32 | D8: BBK8794 | E8: SERGIO | F8: CURITIBA | G8: PR | H8: CURITIBA | I8: PR | J8: MARINGA | K8: PR | L8: PROGRAMADO | M8: EM TRÂNSITO | N8: TROCA DE OPERAÇÃO
A9: 9 | B9: A66590 | C9: ATD4J25 | D9: SET7F10 | E9: PATRICIA | F9: PONTA GROSSA | G9: PR | L9: INDISPONÍVEL | M9: PROGRAMADO TERCEIRO
A10: 10 | B10: A66620 | C10: TAS0H43 | D10: APF2J30 | E10: MATHEUS | F10: PONTA GROSSA | G10: PR | L10: INDISPONÍVEL | M10: PROBLEMAS PESSOAIS

Sheet AGREGADOS SPOT
A1: FROTA | B1: CAVALO | C1: CODIGO SR | D1: CARRETA | E1: MEDIDA | F1: TAG | G1: MOTORISTA | H1: CPF | I1: TELEFONE | J1: STATUS | K1: TECNOLOGIA
A2: A18000 | B2: BAT2820 | C2: C7315 | D2: AZV7123 | G2: HAMILTON DE LIMA | H2: 614.498.579-49 | I2: 41996428568 | J2: DESAGREGOU
A3: A55160 | B3: ILI8C72 | C3: C7143 | D3: AWO2238 | F3: SEM PARAR | G3: JULIANO DE LIMA SCHRAMM | H3: 780.037.840-34 | I3: 51981351912 | J3: DESAGREGOU
A4: A56540 | B4: AOO8H10 | C4: LC1937 | D4: ENG0375 | F4: TAGGY repom | G4: AUGUSTO CESAR DA ROSA | H4: 301.899.738-70 | I4: 11992946939 | J4: DESAGREGOU
A5: A58340 | B5: IEU5D15 | C5: C7314 | D5: AZV0533 | F5: SEM PARAR | G5: FERNANDO PEDRAO FORTES | H5: 000.417.630-84 | I5: 51981461938 | J5: DESAGREGOU
A6: A60000 | B6: EPB9B81 | C6: LC1907 | D6: EAU9974 | F6: TAGGY repom | G6: DAVID SAVARIS BARROS (ASA DELTA) | H6: 087.190.329-60 | I6: 4196879190 | J6: DESAGREGOU
A7: A60290 | B7: AVV0D80 | C7: C7153 | D7: AWO2852 | F7: TAGGY repom | G7: LUIZ CARLOS DA SILVA | H7: 774.763.609-15 | I7: 44991589147 | J7: DESAGREGOU
A8: A63410 | B8: NUF0C80 | C8: LC1936 | D8: EOA0241 | F8: TAGGY repom | G8: JHONATAN FELIPE DE OLIVEIRA CASSOL | H8: 087.607.979-67 | I8: 4191724120 | J8: DESAGREGOU
A9: A62500 | B9: IZX7E98 | C9: C7316 | D9: BAA1371 | G9: DAVID FELIPE SOARES | H9: 118.858.229-10 | I9: 41998668303 | J9: DESAGREGOU
A10: A63320 | B10: MGF4H86 | C10: RT1741 | D10: BBK8796 | F10: SEM PARAR | G10: MIGUEL DE OLIVEIRA | H10: 000.583.139-31 | I10: 95984064310 | J10: DESAGREGOU | K10: AUTOTRAC
A11: A63650 | B11: MEA5F57 | C11: C1230 | D11: ATR6829 | F11: SEM PARAR | G11: RICARDO DE OLIVEIRA | H11: 263.057.568-30 | I11: 44998001018 | J11: DESAGREGOU
A12: A63800 | B12: MFY4I74 | C12: C7356 | D12: ASF9J60 | F12: SEM PARAR | G12: CLAUDINEI GONÇALVES MATTOS | H12: 986.852.529-20 | I12: 41996333287 | J12: ATIVO
A13: A63820 | B13: ATF7H89 | C13: C921 | D13: APH0J19 | F13: TAGGY repom | G13: GUELBER PIRES COSTA | H13: 690.220.032-72 | I13: 65996318724 | J13: DESAGREGOU
A14: A63850 | B14: BAN2A60 | C14: RT1612 | D14: AUR6B01 | F14: SEM PARAR | G14: CLAUDIO DE SOUZA SANTOS | H14: 687.750.839-49 | I14: 41999408564 | J14: DESAGREGOU
A15: A63860 | B15: GBN9E05 | C15: RT1619 | D15: AUR6B22 | F15: SEM PARAR | G15: ANTONIO LOPES RIBEIRO | H15: 765.717.265-72 | I15: 11933483975 | J15: DESAGREGOU
A16: A63880 | B16: FPU4H61 | C16: LC2014 | D16: QXY6B68 | F16: TAGGY repom | G16: FABIO CORREA GOIVINHO | H16: 072.287.259-30 | I16: 44997130480 | J16: DESAGREGOU
A17: A63910 | B17: AYZ5B53 | C17: C7131 | D17: AWI3960 | F17: SEM PARAR | J17: DESAGREGOU
A18: A63940 | B18: AYP3B37 | C18: C910 | D18: APF2943 | G18: AUDINEI NATALINO VICENTE | H18: 953.675.009-00 | I18: 41997757508 / 41999775084 | J18: DESAGREGOU
A19: A63930 | B19: BCY5G45 | C19: C2306 | D19: SET7F10 | G19: ZULMAR WERLICE | H19: 946.942.069-15 | I19: 48999099089 | J19: DESAGREGOU
A20: A63950 | B20: BAP2G10 | C20: C2306 | D20: SET7F10 | F20: SEM PARAR | G20: DILERMANO DE ASSIS BENTO | H20: 082.554.639-76 | I20: 44997509357 | J20: DESAGREGOU
A21: A64010 | B21: PEJ0C51 | C21: C7326 | D21: BAA1454 | F21: SEM PARAR | G21: NELSON DE OLIVEIRA | H21: 255.091.609-34 | I21: 41998954454 | J21: DESAGREGOU
A22: A64030 | B22: MEK4B39 | C22: C1300 | D22: ATR6534 | F22: SEM PARAR | G22: JOAO PAULO CARVALHO DA SILVA | H22: 030.635.709-74 | I22: 41996632772 | J22: ATIVO
A23: A64140 | B23: IMM1A42 | C23: LC2015 | D23: QXY6B65 | G23: RUBENS ALEXANDRE NOGUEIRA | H23: 873.007.539-49 | I23: 41999214009 | J23: DESAGREGOU
A24: A64170 | B24: ATX0A70 | C24: C1480 | D24: ATU6287 | F24: SEM PARAR | J24: DESAGREGOU
A25: A64190 | B25: FRU4A49 | C25: C923 | D25: APH1C65 | F25: MOVE MAIS | G25: GEYSON MIGUEL KOTACHO SANTOS | H25: 036.464.499-00 | I25: 42988487091 | J25: DESAGREGOU
A26: A64220 | B26: JLQ7H51 | C26: RT1612 | D26: AUR6B01 | F26: MOVE MAIS | G26: ERINALDO COSTA DA FONSECA | H26: 297.805.108-69 | I26: 43998259514 | J26: ATIVO
A27: A64300 | B27: GXS8G38 | C27: C1450 | D27: ATU6298 | F27: MOVE MAIS | G27: SERGIO LICHESKI | H27: 511.925.009-20 | I27: 42 9800-7945 | J27: TROCA DE OP.
A28: A64310 | B28: AXS2A52 | C28: RT1739 | D28: BBK8794 | F28: SEM PARAR | G28: CARLOS ELPIDIO CASTELI BARROS COSTA | H28: 082.080.099-62 | I28: 41989043139 | J28: ATIVO
A29: A64410 | B29: MIS0H20 | C29: C7143 | D29: AWO2238 | F29: SEM PARAR | G29: S/MOTORISTA | J29: MANUTENÇÃO
A30: A64570 | B30: AWD1B98 | C30: RT1619 | D30: AUR6B22 | F30: SEM PARAR | G30: EMERSON GUIMARAES SILVA | H30: 049.405.269-41 | I30: 41987369776 | J30: MANUTENÇÃO
A31: A65530 | B31: MBP5D79 | C31: RT1619 | D31: APF3078 | F31: SEM PARAR | G31: JEAN CARLOS DE BASTOS PINHEIRO | H31: 075.316.209-10 | I31: 46999376658 | J31: ATIVO
A32: A65690 | B32: IPK4C72 | C32: C910 | D32: APF2943 | G32: EDERSON COMINESI | H32: 044.471.759-59 | I32: 42 9982-5250 | J32: DESAGREGOU
A33: A65880 | B33: ATD0G84 | C33: C938 | D33: APH0J24 | G33: LEOCADIO JOSE FERREIRA DE MORAES | H33: 244.827.499-15 | I33: 41 99286-2383 | J33: TROCA DE OP.
A34: A66090 | B34: AMF8J97 | C34: C1480 | D34: ATU6287 | F34: SEM PARAR | G34: LUIS EDUARDO LAYNES | H34: 092.481.469-10 | I34: 42 998709960 | J34: DESAGREGOU
A35: A66130 | B35: MGN6G66 | C35: RT1739 | D35: BBK8794 | F35: REPOM | G35: RODRIGO MISAEL VELOSO | H35: 066.130.969-03 | I35: 41988491623 | J35: TROCA DE OP.
A36: A64420 | B36: IUQ0B97 | C36: C7324 | D36: BAA1452 | F36: REPOM | G36: LAURO HENRIQUE GABRIEL RAPOSO | H36: 022.207.139-70 | I36: 41 99595-8045 | J36: ATIVO
A37: A66530 | B37: ANE6H54 | C37: RT1612 | D37: AUR6B01 | F37: REPOM | G37: PATRICK DALVAN COSTA DA SILVA | H37: 015.842.620-79 | I37: 51 98976-8864 | J37: DESAGREGOU
A38: A66490 | B38: ATI8J32 | C38: RT1739 | D38: BBK8794 | F38: REPOM | G38: SERGIO LUIZ RIBEIRO | H38: 005.815.499-02 | I38: 41 99611-4421 | J38: TROCA DE OP.
A39: A66590 | B39: ATD4J25 | C39: C2306 | D39: SET7F10 | F39: REPOM | G39: PATRICIA MICHELE PIRES QUADRA | H39: 800.791.199-56 | I39: 42 99858-7733 | J39: DESAGREGOU
A40: A66620 | B40: TAS0H43 | C40: C914 | D40: APF2J30 | F40: REPOM | G40: MATHEUS CAMARGO | H40: 006.884.889-78 | I40: 42 99967-3244 | J40: ATIVO

Sheet GUARARAPES
A1: NF | B1: DATA | D1: CLiente | E1: Destino | F1: Frota | G1: TARIFA | H1: FRETE | I1: CF | J1: Romaneio | K1: SM
A2: 262265 | B2: 45444 | D2: HSA | E2: VOTUPORANGA | F2: A59000 | G2: 7522.18 | H2: 6076 | I2: =H2/G2 -> 0.80774456 | J2: 1332275 | K2: 5217400
A3: 262236 | B3: 45444 | D3: HSA | E3: VOTUPORANGA | F3: A59510 | G3: 7522.18 | H3: 6076 | I3: =H3/G3 -> 0.80774456 | J3: 1332214
A4: 262389 | B4: 45447 | D4: HSA | E4: VOTUPORANGA | F4: A58840 | G4: 7522.18 | H4: 6076 | I4: =H4/G4 -> 0.80774456 | J4: 1333430 | K4: 5222636
A5: 262549 | B5: 45447 | D5: MESTRE MARCENEIRO | E5: SÃO JOSÉ DO RIO PRETO | F5: A59500 | G5: 6537.87 | H5: 5295.8 | I5: =H5/G5 -> 0.81001917 | J5: 1333858 | K5: 5225888
A6: 262662 | B6: 45448 | D6: GMAD | E6: PRESIDENTE PRUDENTE | F6: A54920 | G6: 6463.99 | H6: 4371 | I6: =H6/G6 -> 0.67620773 | J6: 1334442 | K6: 5229984
A7: 263089 | B7: 45451 | D7: RAMUTH & RAMUTH LTDA | E7: SÃO JOSÉ DOS CAMPOS | F7: A59500 | G7: 6276.93 | H7: 5040.6 | I7: =H7/G7 -> 0.80303588 | J7: 1336090 | K7: 5240847
A8: 263109 | B8: 45451 | D8: F.M.L MIOTTO INDUSTRIA E COMERCIO DE MOVEIS LTDA | E8: ESTRELA DO OESTE | F8: A59570 | G8: 7522.18 | H8: 6076 | I8: =H8/G8 -> 0.80774456 | J8: 1336153 | K8: 5241079
A9: 263181 | B9: 45453 | D9: STALO-BAURU MOBILIARIO ESCOLAR LTDA | E9: BAURU | F9: A59510 | G9: 5069.65 | H9: 4464 | I9: =H9/G9 -> 0.88053416 | J9: 1336926 | K9: 5244007
A10: 263314 | B10: 45454 | D10: RAMUTH & RAMUTH LTDA | E10: SÃO JOSÉ DOS CAMPOS | F10: A54920 | G10: 6276.93 | H10: 4371 | I10: =H10/G10 -> 0.69635953 | J10: 1337438 | K10: 5248198
A11: 263375 | B11: 45454 | D11: MM COMERCIAL DE MADEIRAS, FERRAGENS E MAQUINAS LTDA | E11: MAUA | F11: A59600 | G11: 6210.37 | H11: 4767.8 | I11: =H11/G11 -> 0.76771593 | J11: 1337635 | K11: 5323394
A12: 263400 | B12: 45454 | D12: RIMAD COMERCIAL LTDA | E12: LEME | F12: A59500 | G12: 5362.02 | H12: 5443.6 | I12: =H12/G12 -> 1.0152144 | J12: 1337926 | K12: 5323503
A13: 263531 | B13: 45455 | D13: MESTRE MARCENEIRO LTDA | E13: CAMPINAS | F13: A58480 | G13: 5905.23 | H13: 4879.4 | I13: =H13/G13 -> 0.8262845 | J13: 1338628 | K13: 5324005
A14: 263666 | B14: 45456 | D14: RAMUTH & RAMUTH LTDA | E14: SÃO JOSE DOS CAMPOS | F14: A58580 | G14: 6276.93 | H14: 5040.6 | I14: =H14/G14 -> 0.80303588 | J14: 1338916 | K14: 5324520
A15: 263671 | B15: 45456 | D15: MADEIREIRA MARJAM LTDA | E15: DIADEMA | F15: A59510 | G15: 5345.63 | H15: 4619 | I15: =H15/G15 -> 0.86407028 | J15: 1338968 | K15: 5324572
... A21: 264494 | B21: 45464 | D21: MM COMERCIAL DE MADEIRAS E FERRAGEN S LTDA | E21: SÃO JOSÉ DOS CAMPOS | F21: A59500 | G21: 6276.93 | H21: 5040.6 | I21: =H21/G21 -> 0.80303588 | J21: 1343737 | K21: 5287290
A22: 264679 80 | B22: 45465 | D22: TABOAO MADEIRAS COMERCIAL LTDA | E22: TABOAO DA SERRA | F22: A59600 | G22: 5216.26 | H22: 4302.8 | I22: =H22/G22 -> 0.8248822 | J22: 1344736 | K22: 5329854
A23: 264857 | B23: 45468 | D23: JR MADEIRAS COMERCIAL LTDA | E23: SÃO JOSE DOS CAMPOS | F23: A59500 | G23: 6276.93 | H23: 5528.4 | I23: =H23/G23 -> 0.88074903 | J23: 1346224 | K23: 5331181
A24: 265290 | B24: 45471 | D24: MESTRE MARCENEIRO LTDA | E24: CAMPINAS | F24: A59600 | G24: 5905.23 | H24: 5351.6 | I24: =H24/G24 -> 0.90624751 | J24: 1348153 | K24: 5312354
A25: 265414 | B25: 45471 | D25: RAMUTH & RAMUTH LTDA | E25: GUARULHOS | F25: A59500 | G25: 6039.19 | H25: 5044.19 | I25: =H25/G25 -> 0.83524281 | J25: 1348816 | K25: 5333176
A26: 265724 | B26: 45475 | D26: MADEIREIRA MARJAM LTDA | E26: DIADEMA | F26: A59600 | G26: 5345.63 | H26: 5066 | I26: =H26/G26 -> 0.94768998 | J26: 1350415 | K26: 5326514
A27: 265789 | B27: 45476 | D27: CASA GIACOMO DE FERRAGENS LTDA | E27: ITAQUAQUECETUBA | F27: A59500 | G27: 6830.51 | H27: 5168 | I27: =H27/G27 -> 0.75660529 | J27: 1350828 | K27: 5329338
A28: 266270 | B28: 45479 | D28: RAMUTH & RAMUTH LTDA | E28: SÃO JOSE DOS CAMPOS | F28: A60050 | G28: 7132.88 | H28: 5378.4 | I28: =H28/G28 -> 0.75402923 | J28: 1353031 | K28: 5336916
A29: 266432 | B29: 45482 | D29: COMERCIO DE MADEIRAS GONZAGA LTDA | E29: ITU | F29: A60060 | G29: 5731.47 | H29: 4672 | I29: =H29/G29 -> 0.81514864 | J29: 1354532 | K29: 5338341
A30: 266476 / 7 | B30: 45482 | D30: LEBENSZTAJN & CIA LTDA | E30: SANTOS | F30: A59600 | G30: 6361.07 | H30: 4608 | I30: =H30/G30 -> 0.72440643 | J30: 1354940 | K30: 5338501
A31: 266640 | B31: 45484 | D31: JKV MADEIRAS E FERRAGENS COMERCIAL LTDA | E31: ATIBAIA | F31: A60050 | G31: 5868.94 | H31: 5049.6 | I31: =H31/G31 -> 0.86039387 | J31: 1355614 | K31: 5339287
A32: 266800 | B32: 45485 | D32: TABOAO MADEIRAS COMERCIAL LTDA | E32: TABOAO DA SERRA | F32: A59500 | G32: 5927.57 | H32: 4456.36 | I32: =H32/G32 -> 0.75180217 | J32: 1356658 | K32: 5340160
A33: 266804 | B33: 45485 | D33: RAMUTH & RAMUTH LTDA | E33: SÃO JOSE DOS CAMPOS | F33: A60060 | G33: 7132.88 | H33: 5378.4 | I33: =H33/G33 -> 0.75402923 | J33: 1356637 | K33: 5364201
A34: 266881 | B34: 45486 | D34: RAMUTH & RAMUTH LTDA | E34: SÃO JOSE DOS CAMPOS | F34: A59600 | G34: 7132.88 | H34: 5378.4 | I34: =H34/G34 -> 0.75402923 | J34: 1357168 | K34: 5340612
A35: 266977 | B35: 45488 | D35: CASA DO MARCENEIRO BAMA COMERCIAL LTDA | E35: CAMPINAS | F35: A60050 | G35: 6710.49 | H35: 5036.8 | I35: =H35/G35 -> 0.75058602 | J35: 1358015 | K35: 5370715
A36: 267272 | B36: 45490 | D36: TABOAO MADEIRAS COMERCIAL LTDA | E36: TABOAO DA SERRA | F36: A60220 | G36: 5927.57 | H36: 4456.36 | I36: =H36/G36 -> 0.75180217 | J36: 1359549 | K36: 5391667
A37: 267403 | B37: 45491 | D37: MADEIRANIT COMERCIO E INDUSTRIA DE MADEIRAS LTDA | E37: JUNDIAI | F37: A55640 | G37: 5847.38 | H37: 4812.8 | I37: =H37/G37 -> 0.82306948 | J37: 1360132 | K37: 5362465
A38: 267436 | B38: 45492 | D38: LEBENSZTAJN & CIA LTDA | E38: SANTOS | F38: A59600 | G38: 6361.07 | H38: 4608 | I38: =H38/G38 -> 0.72440643 | J38: 1360267 | K38: 5396974
A39: 267647 | B39: 45495 | D39: CASA GIACOMO DE FERRAGENS LTDA | E39: ITAQUAQUECETUBA | F39: A60060 | G39: 6830.51 | H39: 4864 | I39: =H39/G39 -> 0.7120991 | J39: 1361413 | K39: 5404873
A40: 267930 | B40: 45497 | D40: S H MACIEL LOPES EIRELI | E40: ITARARE | F40: A60220 | G40: 4055.9424 | H40: 3003.33 | I40: =H40/G40 -> 0.74047649 | J40: 1362669 | K40: 5359983
A41: 268303 | B41: 45499 | D41: RAMUTH & RAMUTH LTDA | E41: SÃO JOSE DOS CAMPOS | F41: A55630 | G41: 7132.88 | H41: 5203.2 | I41: =H41/G41 -> 0.72946692 | J41: 1364273 | K41: 5425365
A42: 268345 | B42: 45499 | D42: LUIS RICARDO ALTOE & CIA LTDA | E42: LEME | F42: A60220 | G42: 6093.209 | H42: 5619.2 | I42: =H42/G42 -> 0.92220699 | J42: 1364514 | K42: 5426849
D46: Avulso/Deslocamento A60050 Gilberto
D47: Avulso/Deslocamento A60060 Luiz
D48: AVULSO/DESLOCAMENTO A60220 EVERALDO
D49: 13/07 Reembolso ASO A60220 R$200,00

Sheet DASH
B26: Carregamento & Faturamento | Dia
B28: Carregamentos: | C28: =Apoio!G21
B29: Faturamento: | C29: =Apoio!P51 -> 367870.94
B30: Car Load: | C30: =Apoio!Q51 -> 4904.9459
B31: Média % CF | C31: =Apoio!I4 -> 0.69364162
O32: =Apoio!Q54
O33: =Apoio!Q55
O34: =Apoio!Q56
O35: =Apoio!Q57
O36: =Apoio!Q58
B47: Status de Carregamento | G47: TOTAL DE OFERTAS | H47: =Apoio!G47

Sheet DASH RETORNO

Sheet Apoio
A2: Faturamento DIA | F2: Carregamento/ Dia | I2: %CF | N2: Aceite de Carga
A3: SUM de R$ 2.336,24 | F3: COUNTA de R$ 2.336,24 | I3: CARREGADO | K3: Total | L3: =100%-L4 -> 0.30635838 | U3: #REF! | Y3: STATUS | AA3: DISPONIBILIDADE
A4: 369253.97 | F4: 69 | I4: 0.69364162 | K4: Média | L4: =I4 -> 0.69364162
Y5: AGUARDANDO DESCARGA | AA5: CARREGADO
Y6: AGUARDANDO DESCARGA TERCEIRO | AA6: RETORNO VAZIO
Y7: DESAGREGAÇÃO | AA7: INDISPONÍVEL
Y8: DISPONÍVEL | AA8: PREVENTIVA
Y9: EM TRÂNSITO | AA9: PROGRAMADO
Y10: MANUTENÇÃO CAVALO | AA10: RETORNO PALLET
J11: DASH RETORNO | Y11: MANUTENÇÃO RASTREADOR RITMO | AA11: RETORNO TERCEIRO
J12: Carregamento/ Retorno | N12: R$/KM POR ORIGEM | Y12: PREVENTIVA CARRETA | AA12: VAZIO GO
J13: #REF! | N13: PR CAP. | O13: COUNTA de TE02 | P13: MEDIAN de R$ 5,83 | S13: Carregamento/ Dia | Y13: PROBLEMAS PESSOAIS | AA13: VAZIO MG
N14: PR CAP. | O14: 12 | P14: 2.0833333 | S14: COUNTA de R$ 2.336,24 | T14: SUM de R$ 2.336,24 | Y14: PROGRAMADO | AA14: VAZIO MT
N15: PR OUT. | O15: 2 | P15: 1.8181818 | S15: 84 | T15: 390963.64 | Y15: AGUARDANDO DOCUMENTAÇÃO | AA15: VAZIO PR/SC/RS
N16: RS | O16: 2 | P16: 5.4546153 | Y16: PROGRAMADO TERCEIRO | AA16: VAZIO SP
N17: SC | O17: 9 | P17: 4.3583535 | Y17: SINISTRO
N18: SP | O18: 11 | P18: 5.8333333 | Y18: TROCA MOTORISTA
N19: SP INT. | O19: 13 | P19: 5.98 | Y19: TROCA DE OPERAÇÃO
N20: Total geral | O20: 49 | P20: 5.1993068
J22: Carregamento/ Retorno | N22: R$/KM MODALIDADE RETORNO
J23: PR CAP. | K23: COUNTA de PR CAP. | L23: MEDIAN de 0 | N23: TE02 | O23: COUNTA de TE02 | P23: MEDIAN de R$ 5,83
J24: RS | K24: 2 | L24: 40.5 | N24: DESLOCAMENTO | O24: 14 | P24: 2.0833333
J25: SC | K25: 1 | L25: 41 | N25: RITMO | O25: 21 | P25: 5.8333333
J26: SP | K26: 8 | L26: 34 | N26: TE02 | O26: 13 | P26: 4.4444444
A27: DISPONIBILIDADE | J27: SP INT. | K27: 10 | L27: 30.5 | N27: VAZIO | O27: 1 | P27: 0
A28: #REF! | J28: Total geral | K28: 21 | L28: 37 | N28: Total geral | O28: 49 | P28: 5.1993068
N34: Destino do Retorno
N35: PONTA GROSSA | O35: COUNTA de PONTA GROSSA | P35: COUNTA de PONTA GROSSA
N36: ANTONIO CARLOS | O36: 2 | P36: 0.029850746
N37: BLUMENAU | O37: 2 | P37: 0.029850746
F38: Status de cargas | N38: CURITIBA | O38: 6 | P38: 0.089552239
A39: DISPONIBILIDADE | F39: CARREGADO | G39: COUNTA de CARREGADO | N39: JOINVILLE | O39: 1 | P39: 0.014925373
A40: #REF! | F40: CANCELADA | G40: 7 | N40: PENDENTE | O40: 4 | P40: 0.059701493
F41: CARREGADO | G41: 82 | N41: PINDAMONHANGABA | O41: 3 | P41: 0.044776119
F42: DECLINADO | G42: 30 | N42: PONTA GROSSA | O42: 49 | P42: 0.73134328
F43: Total geral | G43: 119 | N43: Total geral | O43: 67 | P43: 1
N50: CARREGADO | O50: COUNTA de CARREGADO | P50: SUM de R$ 2.336,24
N51: CARREGADO | O51: 75 | P51: 367870.94 | Q51: =P51/O51 -> 4904.9459
N52: Total geral | O52: 75 | P52: 367870.94 | Q52: =P52/O52 -> 4904.9459
Q53: =P53/O53 -> #DIV/0!
A64: Status
A66: CARREGADO
A67: RETIRADA | F67: Status de cargas
A68: DECLINADO | F68: A54730 | G68: SUM de R$ 1.500,00
A69: CANCELADA | G69: 3000
A70: FALTA DE VEÍCULO | F70: A47130 | G70: 10000
A71: D+ | F71: A53130 | G71: 9500
A72: PROGRAMADO | F72: A54730 | G72: 12800
F73: A54920 | G73: 19000
F74: A54980 | G74: 7000
F75: A55160 | G75: 26050
F76: A55620 | G76: 8500
A77: UF | F77: A55630 | G77: 3000
A78: PR CAP. | F78: A55640 | G78: 7800
A79: PR OUT. | F79: A55650 | G79: 13800
A80: SC | F80: A55660 | G80: 9500
A81: RS | F81: A55890 | G81: 7500
A82: SP | F82: A56060 | G82: 4000
A83: SP INT. | F83: A56360 | G83: 4500
A84: TE02 | F84: A56370 | G84: 3500
A85: - | F85: A56430 | G85: 11300
A86: MS | F86: A56540 | G86: 14500
A87: MT | F87: A56620 | G87: 15500
A88: MG | F88: A56750 | G88: 5500
... A93: TE02 SC | F93: A57700 | G93: 16000
F94: A57780 | G94: 3500
A95: CANAL | F95: A57860 | G95: 3000
A96: ASD | F96: A57980 | G96: 3750
A97: DTB | F97: A58170 | G97: 3000
A98: TRF | F98: MBG6624/MHC3229 | G98: 4000
F99: Total geral | G99: 263300
A101: MODALIDADE RETORNO
A102: RITMO
A103: TE02
A104: DESLOCAMENTO
A105: RETORNO PENDENTE
A106: AGREGADO SP
A107: VAZIO
A108: TE02 PR
A109: TERCEIRO

Sheet DISP MARÇO
D1: Meta 95% | I1: INSTRUÇÕES DE PREENCHIMENTO
I2: Disponível: D | M2: Problemas Pessoais: PP | Q2: S/ Documentação: SD | U2: Viagem Terceiro: VT | Z2: Sinalizou Desagregação: DS
I3: Trânsito: T (carregado) | M3: Manutenção: PC | Q3: S/ Motorista: SM | U3: Encostado: E(somente desengatado) | Z3: Desagregação|Troca de Fluxo: OO
I4: Sinistrado: S | M4: Manutenção Carreta: PV | Q4: Folga/Férias: F | U4: Recusa de Carga: RC
A6: REF | B6: CÓD | C6: PLACA | D6: MOTORISTA | E6: 45352 | F6: 45353 | G6: 45354 | H6: 45355 | I6: 45356 | J6: 45357 | K6: 45358 | L6: 45359 | M6: 45360 | N6: 45361 | O6: 45362 | P6: 45363 | Q6: 45364 | R6: 45365 | S6: 45366 | T6: 45367 | U6: 45368 | V6: 45369 | W6: 45370 | X6: 45371 | Y6: 45372 | Z6: 45373 | AA6: 45374 | AB6: 45375 | AC6: 45376 | AD6: 45377 | AE6: 45378 | AF6: 45379 | AG6: 45380 | AH6: 45381 | AI6: 45382 | AJ6: Dias Disponíveis | AK6: Dias Insdisponíveis | AL6: "OO" | AM6: PRODUTIVIDADE EM DIAS | AN6: Total de dias no mês | AO6: Disponibilidade do Ativo | AP6: Produtividade da Operação | AR6: INDISPONIBILIDADE DE ATIVOS
AR7: PP | AS7: PC | AT7: F | AU7: SD | AV7: SM | AW7: PV | AX7: RC | AY7: S | AZ7: E
A8: 1 | B8: A18000 | C8: BAT2820 | D8: HAMILTON DE LIMA | E8: F | F8: F | G8: F | H8: F | I8: F | J8: F | K8: F | L8: F | M8: F | N8: F | O8: F | P8: F | Q8: F | R8: F | S8: F | T8: F | U8: F | V8: F | W8: F | X8: F | Y8: F | Z8: F | AA8: F | AB8: F | AC8: F | AD8: F | AE8: F | AF8: F | AG8: F | AH8: F | AI8: F | AJ8: =(COUNTIF(E8:AI8,"D")+COUNTIF(E8:AI8,"T")+COUNTIF(E8:AI8,"VT")) -> 0 | AK8: =(COUNTIF(E8:AI8,"pp")+COUNTIF(E8:AI8,"pc")+COUNTIF(E8:AI8,"sd")+COUNTIF(E8:AI8,"sm")+COUNTIF(E8:AI8,"f")+COUNTIF(E8:AI8,"I")+COUNTIF(E8:AI8,"PV")+COUNTIF(E8:AI8,"DS")+COUNTIF(E8:AI8,"RC")) -> 31 | AL8: =COUNTIF(E8:AI8,"OO") -> 0 | AM8: =AN8-AL8 -> 31 | AN8: =COUNTA(E8:AI8) -> 31 | AO8: =AJ8/AN8 -> 0 | AP8: =AJ8/AM8 -> 0 | AR8: =COUNTIF(E8:AK8,"PP") -> 0 | AS8: =COUNTIF(E8:AK8,"PC") -> 0 | AT8: =COUNTIF(E8:AK8,"F") -> 31 | AU8: =COUNTIF(E8:AK8,"SD") -> 0 | AV8: =COUNTIF(E8:AK8,"SM") -> 0 | AW8: =COUNTIF(F8:AL8,"PV") -> 0 | AX8: =COUNTIF(G8:AM8,"RC") -> 0 | AY8: =COUNTIF(H8:AN8,"S") -> 0 | AZ8: =COUNTIF(I8:AO8,"E") -> 0
A9: 2 | B9: A47130 | C9: MFY4I74 | D9: CLAUDINEI GONCALVES MATTOS | E9: VT | F9: VT | G9: VT | H9: VT | I9: T | J9: T | K9: T | L9: T | M9: T | N9: T | O9: T | P9: D | Q9: T | R9: T | S9: T | T9: T | U9: T | V9: D | W9: D | X9: VT | Y9: VT | Z9: T | AA9: T | AB9: T | AC9: T | AD9: T | AE9: T | AF9: T | AG9: T | AH9: T | AI9: T | AJ9: =(COUNTIF(E9:AI9,"D")+COUNTIF(E9:AI9,"T")+COUNTIF(E9:AI9,"VT")) -> 31 | AK9: =(COUNTIF(E9:AI9,"pp")+COUNTIF(E9:AI9,"pc")+COUNTIF(E9:AI9,"sd")+COUNTIF(E9:AI9,"sm")+COUNTIF(E9:AI9,"f")+COUNTIF(E9:AI9,"I")+COUNTIF(E9:AI9,"PV")+COUNTIF(E9:AI9,"DS")+COUNTIF(E9:AI9,"RC")) -> 0 | AL9: =COUNTIF(E9:AI9,"OO") -> 0 | AM9: =AN9-AL9 -> 31 | AN9: =COUNTA(E9:AI9) -> 31 | AO9: =AJ9/AN9 -> 1 | AP9: =AJ9/AM9 -> 1 | AR9: =COUNTIF(E9:AK9,"PP") -> 0 | AS9: =COUNTIF(E9:AK9,"PC") -> 0 | AT9: =COUNTIF(E9:AK9,"F") -> 0 | AU9: =COUNTIF(E9:AK9,"SD") -> 0 | AV9: =COUNTIF(E9:AK9,"SM") -> 0 | AW9: =COUNTIF(F9:AL9,"PV") -> 0 | AX9: =COUNTIF(G9:AM9,"RC") -> 0 | AY9: =COUNTIF(H9:AN9,"S") -> 0 | AZ9: =COUNTIF(I9:AO9,"E") -> 0
A10: 3 | B10: A54920 | C10: GXS8G38 | D10: SERGIO LICHESKI | E10: VT | F10: VT | G10: VT | H10: VT | I10: D | J10: D | K10: D | L10: D | M10: F | N10: D | O10: T | P10: T | Q10: T | R10: T | S10: T | T10: T | U10: T | V10: T | W10: T | X10: T | Y10: T | Z10: T | AA10: PP | AB10: F | AC10: PP | AD10: T | AE10: PP | AF10: PP | AG10: PP | AH10: PP | AI10: PP | AJ10: =(COUNTIF(E10:AI10,"D")+COUNTIF(E10:AI10,"T")+COUNTIF(E10:AI10,"VT")) -> 22 | AK10: =(COUNTIF(E10:AI10,"pp")+COUNTIF(E10:AI10,"pc")+COUNTIF(E10:AI10,"sd")+COUNTIF(E10:AI10,"sm")+COUNTIF(E10:AI10,"f")+COUNTIF(E10:AI10,"I")+COUNTIF(E10:AI10,"PV")+COUNTIF(E10:AI10,"DS")+COUNTIF(E10:AI10,"RC")) -> 9 | AL10: =COUNTIF(E10:AI10,"OO") -> 0 | AM10: =AN10-AL10 -> 31 | AN10: =COUNTA(E10:AI10) -> 31 | AO10: =AJ10/AN10 -> 0.70967742 | AP10: =AJ10/AM10 -> 0.70967742 | AR10: =COUNTIF(E10:AK10,"PP") -> 7 | AS10: =COUNTIF(E10:AK10,"PC") -> 0 | AT10: =COUNTIF(E10:AK10,"F") -> 2 | AU10: =COUNTIF(E10:AK10,"SD") -> 0 | AV10: =COUNTIF(E10:AK10,"SM") -> 0 | AW10: =COUNTIF(F10:AL10,"PV") -> 0 | AX10: =COUNTIF(G10:AM10,"RC") -> 0 | AY10: =COUNTIF(H10:AN10,"S") -> 0 | AZ10: =COUNTIF(I10:AO10,"E") -> 0
A11: 4 | B11: A55160 | C11: ILI8C72 | D11: JULIANO DE LIMA SCHRAMM | E11: VT | F11: VT | G11: VT | H11: T | I11: T | J11: T | K11: T | L11: T | M11: T | N11: T | O11: D | P11: T | Q11: T | R11: VT | S11: VT | T11: VT | U11: VT | V11: VT | W11: F | X11: F | Y11: F | Z11: F | AA11: F | AB11: F | AC11: VT | AD11: VT | AE11: T | AF11: T | AG11: T | AH11: T | AI11: T | AJ11: =(COUNTIF(E11:AI11,"D")+COUNTIF(E11:AI11,"T")+COUNTIF(E11:AI11,"VT")) -> 25 | AK11: =(COUNTIF(E11:AI11,"pp")+COUNTIF(E11:AI11,"pc")+COUNTIF(E11:AI11,"sd")+COUNTIF(E11:AI11,"sm")+COUNTIF(E11:AI11,"f")+COUNTIF(E11:AI11,"I")+COUNTIF(E11:AI11,"PV")+COUNTIF(E11:AI11,"DS")+COUNTIF(E11:AI11,"RC")) -> 6 | AL11: =COUNTIF(E11:AI11,"OO") -> 0 | AM11: =AN11-AL11 -> 31 | AN11: =COUNTA(E11:AI11) -> 31 | AO11: =AJ11/AN11 -> 0.80645161 | AP11: =AJ11/AM11 -> 0.80645161 | AR11: =COUNTIF(E11:AK11,"PP") -> 0 | AS11: =COUNTIF(E11:AK11,"PC") -> 0 | AT11: =COUNTIF(E11:AK11,"F") -> 6 | AU11: =COUNTIF(E11:AK11,"SD") -> 0 | AV11: =COUNTIF(E11:AK11,"SM") -> 0 | AW11: =COUNTIF(F11:AL11,"PV") -> 0 | AX11: =COUNTIF(G11:AM11,"RC") -> 0 | AY11: =COUNTIF(H11:AN11,"S") -> 0 | AZ11: =COUNTIF(I11:AO11,"E") -> 0
A12: 5 | B12: A55620 | C12: QHH0874 | D12: CLEVERTON LUIZ SANTOS | E12: SM | F12: SM | G12: SM | H12: SM | I12: SM | J12: SM | K12: SM | L12: SM | M12: SM | N12: SM | O12: SM | P12: T | Q12: T | R12: T | S12: T | T12: T | U12: T | V12: T | W12: T | X12: T | Y12: T | Z12: T | AA12: PC | AB12: PC | AC12: PC | AD12: PC | AE12: PC | AF12: SM | AG12: SM | AH12: SM | AI12: SM | AJ12: =(COUNTIF(E12:AI12,"D")+COUNTIF(E12:AI12,"T")+COUNTIF(E12:AI12,"VT")) -> 11 | AK12: =(COUNTIF(E12:AI12,"pp")+COUNTIF(E12:AI12,"pc")+COUNTIF(E12:AI12,"sd")+COUNTIF(E12:AI12,"sm")+COUNTIF(E12:AI12,"f")+COUNTIF(E12:AI12,"I")+COUNTIF(E12:AI12,"PV")+COUNTIF(E12:AI12,"DS")+COUNTIF(E12:AI12,"RC")) -> 20 | AL12: =COUNTIF(E12:AI12,"OO") -> 0 | AM12: =AN12-AL12 -> 31 | AN12: =COUNTA(E12:AI12) -> 31 | AO12: =AJ12/AN12 -> 0.35483871 | AP12: =AJ12/AM12 -> 0.35483871 | AR12: =COUNTIF(E12:AK12,"PP") -> 0 | AS12: =COUNTIF(E12:AK12,"PC") -> 5 | AT12: =COUNTIF(E12:AK12,"F") -> 0 | AU12: =COUNTIF(E12:AK12,"SD") -> 0 | AV12: =COUNTIF(E12:AK12,"SM") -> 15 | AW12: =COUNTIF(F12:AL12,"PV") -> 0 | AX12: =COUNTIF(G12:AM12,"RC") -> 0 | AY12: =COUNTIF(H12:AN12,"S") -> 0 | AZ12: =COUNTIF(I12:AO12,"E") -> 0
A13: 6 | B13: A55630 | C13: QJM9J40 | D13: - | E13: PC | F13: PC | G13: F | H13: D | I13: D | J13: T | K13: T | L13: T | M13: T | N13: T | O13: PC | P13: PC | Q13: PC | R13: PC | S13: PC | T13: PC | U13: PC | V13: PC | W13: PC | X13: PC | Y13: PC | Z13: PC | AA13: PC | AB13: PC | AC13: T | AD13: SM | AE13: SM | AF13: SM | AG13: SM | AH13: SM | AI13: SM | AJ13: =(COUNTIF(E13:AI13,"D")+COUNTIF(E13:AI13,"T")+COUNTIF(E13:AI13,"VT")) -> 8 | AK13: =(COUNTIF(E13:AI13,"pp")+COUNTIF(E13:AI13,"pc")+COUNTIF(E13:AI13,"sd")+COUNTIF(E13:AI13,"sm")+COUNTIF(E13:AI13,"f")+COUNTIF(E13:AI13,"I")+COUNTIF(E13:AI13,"PV")+COUNTIF(E13:AI13,"DS")+COUNTIF(E13:AI13,"RC")) -> 23 | AL13: =COUNTIF(E13:AI13,"OO") -> 0 | AM13: =AN13-AL13 -> 31 | AN13: =COUNTA(E13:AI13) -> 31 | AO13: =AJ13/AN13 -> 0.25806452 | AP13: =AJ13/AM13 -> 0.25806452 | AR13: =COUNTIF(E13:AK13,"PP") -> 0 | AS13: =COUNTIF(E13:AK13,"PC") -> 16 | AT13: =COUNTIF(E13:AK13,"F") -> 1 | AU13: =COUNTIF(E13:AK13,"SD") -> 0 | AV13: =COUNTIF(E13:AK13,"SM") -> 6 | AW13: =COUNTIF(F13:AL13,"PV") -> 0 | AX13: =COUNTIF(G13:AM13,"RC") -> 0 | AY13: =COUNTIF(H13:AN13,"S") -> 0 | AZ13: =COUNTIF(I13:AO13,"E") -> 0
A14: 7 | B14: A55640 | C14: RLI4I24 | D14: OTAVIO PAULO DOS SANTOS | E14: SM | F14: SM | G14: SM | H14: SM | I14: D | J14: T | K14: T | L14: T | M14: T | N14: T | O14: T | P14: T | Q14: T | R14: D | S14: T | T14: T | U14: T | V14: T | W14: T | X14: T | Y14: T | Z14: T | AA14: T | AB14: T | AC14: T | AD14: T | AE14: T | AF14: T | AG14: T | AH14: T | AI14: T | AJ14: =(COUNTIF(E14:AI14,"D")+COUNTIF(E14:AI14,"T")+COUNTIF(E14:AI14,"VT")) -> 27 | AK14: =(COUNTIF(E14:AI14,"pp")+COUNTIF(E14:AI14,"pc")+COUNTIF(E14:AI14,"sd")+COUNTIF(E14:AI14,"sm")+COUNTIF(E14:AI14,"f")+COUNTIF(E14:AI14,"I")+COUNTIF(E14:AI14,"PV")+COUNTIF(E14:AI14,"DS")+COUNTIF(E14:AI14,"RC")) -> 4 | AL14: =COUNTIF(E14:AI14,"OO") -> 0 | AM14: =AN14-AL14 -> 31 | AN14: =COUNTA(E14:AI14) -> 31 | AO14: =AJ14/AN14 -> 0.87096774 | AP14: =AJ14/AM14 -> 0.87096774 | AR14: =COUNTIF(E14:AK14,"PP") -> 0 | AS14: =COUNTIF(E14:AK14,"PC") -> 0 | AT14: =COUNTIF(E14:AK14,"F") -> 0 | AU14: =COUNTIF(E14:AK14,"SD") -> 0 | AV14: =COUNTIF(E14:AK14,"SM") -> 4 | AW14: =COUNTIF(F14:AL14,"PV") -> 0 | AX14: =COUNTIF(G14:AM14,"RC") -> 0 | AY14: =COUNTIF(H14:AN14,"S") -> 0 | AZ14: =COUNTIF(I14:AO14,"E") -> 0
A15: 8 | B15: A55650 | C15: RLJ5B74 | D15: - | E15: SM | F15: SM | G15: SM | H15: SM | I15: SM | J15: SM | K15: SM | L15: SM | M15: SM | N15: SM | O15: SM | P15: SM | Q15: SM | R15: SM | S15: SM | T15: SM | U15: SM | V15: SM | W15: SM | X15: SM | Y15: SM | Z15: SM | AA15: SM | AB15: SM | AC15: SM | AD15: SM | AE15: SM | AF15: SM | AG15: SM | AH15: SM | AI15: SM | AJ15: =(COUNTIF(E15:AI15,"D")+COUNTIF(E15:AI15,"T")+COUNTIF(E15:AI15,"VT")) -> 0 | AK15: =(COUNTIF(E15:AI15,"pp")+COUNTIF(E15:AI15,"pc")+COUNTIF(E15:AI15,"sd")+COUNTIF(E15:AI15,"sm")+COUNTIF(E15:AI15,"f")+COUNTIF(E15:AI15,"I")+COUNTIF(E15:AI15,"PV")+COUNTIF(E15:AI15,"DS")+COUNTIF(E15:AI15,"RC")) -> 31 | AL15: =COUNTIF(E15:AI15,"OO") -> 0 | AM15: =AN15-AL15 -> 31 | AN15: =COUNTA(E15:AI15) -> 31 | AO15: =AJ15/AN15 -> 0 | AP15: =AJ15/AM15 -> 0 | AR15: =COUNTIF(E15:AK15,"PP") -> 0 | AS15: =COUNTIF(E15:AK15,"PC") -> 0 | AT15: =COUNTIF(E15:AK15,"F") -> 0 | AU15: =COUNTIF(E15:AK15,"SD") -> 0 | AV15: =COUNTIF(E15:AK15,"SM") -> 31 | AW15: =COUNTIF(F15:AL15,"PV") -> 0 | AX15: =COUNTIF(G15:AM15,"RC") -> 0 | AY15: =COUNTIF(H15:AN15,"S") -> 0 | AZ15: =COUNTIF(I15:AO15,"E") -> 0
A16: 9 | B16: A55660 | C16: RLK2J93 | D16: - | E16: T | F16: PC | G16: PC | H16: PC | I16: SM | J16: SM | K16: SM | L16: SM | M16: SM | N16: SM | O16: SM | P16: SM | Q16: SM | R16: SM | S16: SM | T16: SM | U16: SM | V16: SM | W16: SM | X16: SM | Y16: SM | Z16: SM | AA16: SM | AB16: SM | AC16: SM | AD16: SM | AE16: T | AF16: T | AG16: T | AH16: T | AI16: T | AJ16: =(COUNTIF(E16:AI16,"D")+COUNTIF(E16:AI16,"T")+COUNTIF(E16:AI16,"VT")) -> 6 | AK16: =(COUNTIF(E16:AI16,"pp")+COUNTIF(E16:AI16,"pc")+COUNTIF(E16:AI16,"sd")+COUNTIF(E16:AI16,"sm")+COUNTIF(E16:AI16,"f")+COUNTIF(E16:AI16,"I")+COUNTIF(E16:AI16,"PV")+COUNTIF(E16:AI16,"DS")+COUNTIF(E16:AI16,"RC")) -> 25 | AL16: =COUNTIF(E16:AI16,"OO") -> 0 | AM16: =AN16-AL16 -> 31 | AN16: =COUNTA(E16:AI16) -> 31 | AO16: =AJ16/AN16 -> 0.19354839 | AP16: =AJ16/AM16 -> 0.19354839 | AR16: =COUNTIF(E16:AK16,"PP") -> 0 | AS16: =COUNTIF(E16:AK16,"PC") -> 3 | AT16: =COUNTIF(E16:AK16,"F") -> 0 | AU16: =COUNTIF(E16:AK16,"SD") -> 0 | AV16: =COUNTIF(E16:AK16,"SM") -> 22 | AW16: =COUNTIF(F16:AL16,"PV") -> 0 | AX16: =COUNTIF(G16:AM16,"RC") -> 0 | AY16: =COUNTIF(H16:AN16,"S") -> 0 | AZ16: =COUNTIF(I16:AO16,"E") -> 0
A17: 10 | B17: A55890 | C17: QHB7A24 | D17: - | E17: PC | F17: PC | G17: PC | H17: PC | I17: PC | J17: PC | K17: PC | L17: PC | M17: PC | N17: PC | O17: PC | P17: PC | Q17: PC | R17: PC | S17: PC | T17: PC | U17: PC | V17: PC | W17: PC | X17: PC | Y17: T | Z17: T | AA17: T | AB17: T | AC17: T | AD17: T | AE17: T | AF17: T | AG17: T | AH17: T | AI17: T | AJ17: =(COUNTIF(E17:AI17,"D")+COUNTIF(E17:AI17,"T")+COUNTIF(E17:AI17,"VT")) -> 11 | AK17: =(COUNTIF(E17:AI17,"pp")+COUNTIF(E17:AI17,"pc")+COUNTIF(E17:AI17,"sd")+COUNTIF(E17:AI17,"sm")+COUNTIF(E17:AI17,"f")+COUNTIF(E17:AI17,"I")+COUNTIF(E17:AI17,"PV")+COUNTIF(E17:AI17,"DS")+COUNTIF(E17:AI17,"RC")) -> 20 | AL17: =COUNTIF(E17:AI17,"OO") -> 0 | AM17: =AN17-AL17 -> 31 | AN17: =COUNTA(E17:AI17) -> 31 | AO17: =AJ17/AN17 -> 0.35483871 | AP17: =AJ17/AM17 -> 0.35483871 | AR17: =COUNTIF(E17:AK17,"PP") -> 0 | AS17: =COUNTIF(E17:AK17,"PC") -> 20 | AT17: =COUNTIF(E17:AK17,"F") -> 0 | AU17: =COUNTIF(E17:AK17,"SD") -> 0 | AV17: =COUNTIF(E17:AK17,"SM") -> 0 | AW17: =COUNTIF(F17:AL17,"PV") -> 0 | AX17: =COUNTIF(G17:AM17,"RC") -> 0 | AY17: =COUNTIF(H17:AN17,"S") -> 0 | AZ17: =COUNTIF(I17:AO17,"E") -> 0
A18: 11 | B18: A56060 | C18: MDJ8F78 | D18: FABRICIO CAETANO GARCIA | E18: T | F18: T | G18: T | H18: VT | I18: VT | J18: SM | K18: SM | L18: SM | M18: SM | N18: SM | O18: PP | P18: PP | Q18: T | R18: D | S18: T | T18: T | U18: T | V18: T | W18: T | X18: PC | Y18: PC | Z18: PC | AA18: PC | AB18: PC | AC18: PC | AD18: PC | AE18: PC | AF18: PV | AG18: PV | AH18: PV | AI18: PV | AJ18: =(COUNTIF(E18:AI18,"D")+COUNTIF(E18:AI18,"T")+COUNTIF(E18:AI18,"VT")) -> 12 | AK18: =(COUNTIF(E18:AI18,"pp")+COUNTIF(E18:AI18,"pc")+COUNTIF(E18:AI18,"sd")+COUNTIF(E18:AI18,"sm")+COUNTIF(E18:AI18,"f")+COUNTIF(E18:AI18,"I")+COUNTIF(E18:AI18,"PV")+COUNTIF(E18:AI18,"DS")+COUNTIF(E18:AI18,"RC")) -> 19 | AL18: =COUNTIF(E18:AI18,"OO") -> 0 | AM18: =AN18-AL18 -> 31 | AN18: =COUNTA(E18:AI18) -> 31 | AO18: =AJ18/AN18 -> 0.38709677 | AP18: =AJ18/AM18 -> 0.38709677 | AR18: =COUNTIF(E18:AK18,"PP") -> 2 | AS18: =COUNTIF(E18:AK18,"PC") -> 8 | AT18: =COUNTIF(E18:AK18,"F") -> 0 | AU18: =COUNTIF(E18:AK18,"SD") -> 0 | AV18: =COUNTIF(E18:AK18,"SM") -> 5 | AW18: =COUNTIF(F18:AL18,"PV") -> 4 | AX18: =COUNTIF(G18:AM18,"RC") -> 0 | AY18: =COUNTIF(H18:AN18,"S") -> 0 | AZ18: =COUNTIF(I18:AO18,"E") -> 0
A19: 12 | B19: A56090 | C19: KVN1C55 | D19: LUIZ CARLOS DA SILVA | E19: PC | F19: PC | G19: PC | H19: PC | I19: PC | J19: PC | K19: PC | L19: PC | M19: PC | N19: PC | O19: PC | P19: PC | Q19: PC | R19: PC | S19: PC | T19: PC | U19: PC | V19: PC | W19: PC | X19: PC | Y19: PC | Z19: PC | AA19: PC | AB19: PC | AC19: PC | AD19: PC | AE19: PC | AF19: PC | AG19: PC | AH19: PC | AI19: PC | AJ19: =(COUNTIF(E19:AI19,"D")+COUNTIF(E19:AI19,"T")+COUNTIF(E19:AI19,"VT")) -> 0 | AK19: =(COUNTIF(E19:AI19,"pp")+COUNTIF(E19:AI19,"pc")+COUNTIF(E19:AI19,"sd")+COUNTIF(E19:AI19,"sm")+COUNTIF(E19:AI19,"f")+COUNTIF(E19:AI19,"I")+COUNTIF(E19:AI19,"PV")+COUNTIF(E19:AI19,"DS")+COUNTIF(E19:AI19,"RC")) -> 31 | AL19: =COUNTIF(E19:AI19,"OO") -> 0 | AM19: =AN19-AL19 -> 31 | AN19: =COUNTA(E19:AI19) -> 31 | AO19: =AJ19/AN19 -> 0 | AP19: =AJ19/AM19 -> 0 | AR19: =COUNTIF(E19:AK19,"PP") -> 0 | AS19: =COUNTIF(E19:AK19,"PC") -> 31 | AT19: =COUNTIF(E19:AK19,"F") -> 0 | AU19: =COUNTIF(E19:AK19,"SD") -> 0 | AV19: =COUNTIF(E19:AK19,"SM") -> 0 | AW19: =COUNTIF(F19:AL19,"PV") -> 0 | AX19: =COUNTIF(G19:AM19,"RC") -> 0 | AY19: =COUNTIF(H19:AN19,"S") -> 0 | AZ19: =COUNTIF(I19:AO19,"E") -> 0
... A30: 23 | B30: A58510 | C30: EVO3A49 | D30: EDNO | E30: OO | F30: OO | G30: OO | H30: OO | I30: OO | J30: OO | K30: OO | L30: OO | M30: OO | N30: OO | O30: OO | P30: OO | Q30: OO | R30: OO | S30: OO | T30: T | U30: PC | V30: OO | W30: OO | X30: OO | Y30: OO | Z30: OO | AA30: OO | AB30: OO | AC30: OO | AD30: OO | AE30: OO | AF30: OO | AG30: OO | AH30: OO | AI30: OO | AJ30: =(COUNTIF(E30:AI30,"D")+COUNTIF(E30:AI30,"T")+COUNTIF(E30:AI30,"VT")) -> 1 | AK30: =(COUNTIF(E30:AI30,"pp")+COUNTIF(E30:AI30,"pc")+COUNTIF(E30:AI30,"sd")+COUNTIF(E30:AI30,"sm")+COUNTIF(E30:AI30,"f")+COUNTIF(E30:AI30,"I")+COUNTIF(E30:AI30,"PV")+COUNTIF(E30:AI30,"DS")+COUNTIF(E30:AI30,"RC")) -> 1 | AL30: =COUNTIF(E30:AI30,"OO") -> 29 | AM30: =AN30-AL30 -> 2 | AN30: =COUNTA(E30:AI30) -> 31 | AO30: =AJ30/AN30 -> 0.032258065 | AP30: =AJ30/AM30 -> 0.5 | AR30: =COUNTIF(E30:AK30,"PP") -> 0 | AS30: =COUNTIF(E30:AK30,"PC") -> 1 | AT30: =COUNTIF(E30:AK30,"F") -> 0 | AU30: =COUNTIF(E30:AK30,"SD") -> 0 | AV30: =COUNTIF(E30:AK30,"SM") -> 0 | AW30: =COUNTIF(F30:AL30,"PV") -> 0 | AX30: =COUNTIF(G30:AM30,"RC") -> 0 | AY30: =COUNTIF(H30:AN30,"S") -> 0 | AZ30: =COUNTIF(I30:AO30,"E") -> 0
AJ31: =COUNTIF(E31:AI31,"d")+COUNTIF(E31:AI31,"t")+COUNTIF(E31:AI31,"vt")+COUNTIF(E31:AI31,"pv")+COUNTIF(E31:AI31,"RC") -> 0 | AK31: =(COUNTIF(E31:AI31,"pp")+COUNTIF(E31:AI31,"pc")+COUNTIF(E31:AI31,"sd")+COUNTIF(E31:AI31,"sm")+COUNTIF(E31:AI31,"f")) -> 0 | AL31: =COUNTIF(E31:AI31,"OO") -> 0 | AM31: =AN31-AL31 -> 0 | AN31: =COUNTA(E31:AI31) -> 0 | AR31: =COUNTIF(E31:AK31,"PP") -> 0 | AS31: =COUNTIF(E31:AK31,"PC") -> 0 | AT31: =COUNTIF(E31:AK31,"F") -> 0 | AU31: =COUNTIF(E31:AK31,"SD") -> 0 | AV31: =COUNTIF(E31:AK31,"SM") -> 0 | AW31: =COUNTIF(F31:AL31,"PV") -> 0 | AX31: =COUNTIF(G31:AM31,"RC") -> 0 | AY31: =COUNTIF(H31:AN31,"S") -> 0 | AZ31: =COUNTIF(I31:AO31,"E") -> 0
AJ32: =COUNTIF(E32:AI32,"d")+COUNTIF(E32:AI32,"t")+COUNTIF(E32:AI32,"vt")+COUNTIF(E32:AI32,"pv")+COUNTIF(E32:AI32,"RC") -> 0 | AK32: =(COUNTIF(E32:AI32,"pp")+COUNTIF(E32:AI32,"pc")+COUNTIF(E32:AI32,"sd")+COUNTIF(E32:AI32,"sm")+COUNTIF(E32:AI32,"f")) -> 0 | AL32: =COUNTIF(E32:AI32,"OO") -> 0 | AM32: =AN32-AL32 -> 0 | AN32: =COUNTA(E32:AI32) -> 0 | AR32: =COUNTIF(E32:AK32,"PP") -> 0 | AS32: =COUNTIF(E32:AK32,"PC") -> 0 | AT32: =COUNTIF(E32:AK32,"F") -> 0 | AU32: =COUNTIF(E32:AK32,"SD") -> 0 | AV32: =COUNTIF(E32:AK32,"SM") -> 0 | AW32: =COUNTIF(F32:AL32,"PV") -> 0 | AX32: =COUNTIF(G32:AM32,"RC") -> 0 | AY32: =COUNTIF(H32:AN32,"S") -> 0 | AZ32: =COUNTIF(I32:AO32,"E") -> 0
D33: Disponibilidade por dia | E33: =COUNTIF(E8:E32,"d")+COUNTIF(E8:E32,"t")+COUNTIF(E8:E32,"vt") -> 13 | F33: =COUNTIF(F8:F32,"d")+COUNTIF(F8:F32,"t")+COUNTIF(F8:F32,"vt") -> 12 | G33: =COUNTIF(G8:G32,"d")+COUNTIF(G8:G32,"t")+COUNTIF(G8:G32,"vt") -> 12 | H33: =COUNTIF(H8:H32,"d")+COUNTIF(H8:H32,"t")+COUNTIF(H8:H32,"vt") -> 12 | I33: =COUNTIF(I8:I32,"d")+COUNTIF(I8:I32,"t")+COUNTIF(I8:I32,"vt") -> 13 | J33: =COUNTIF(J8:J32,"d")+COUNTIF(J8:J32,"t")+COUNTIF(J8:J32,"vt") -> 11 | K33: =COUNTIF(K8:K32,"d")+COUNTIF(K8:K32,"t")+COUNTIF(K8:K32,"vt") -> 11 | L33: =COUNTIF(L8:L32,"d")+COUNTIF(L8:L32,"t")+COUNTIF(L8:L32,"vt") -> 11 | ... AI33: =COUNTIF(AI8:AI32,"d")+COUNTIF(AI8:AI32,"t")+COUNTIF(AI8:AI32,"vt") -> 11 | AO33: =(AJ36/AN36) -> 0.51893408 | AP33: =AJ36/AM36 -> 0.55223881 | AR33: =SUM(AR8:AR32) -> 30 | AS33: =SUM(AS8:AS32) -> 113 | AT33: =SUM(AT8:AT32) -> 41 | AU33: =SUM(AU8:AU32) -> 0 | AV33: =SUM(AV8:AV32) -> 92 | AW33: =SUM(AW8:AW32) -> 5 | AX33: =SUM(AX8:AX32) -> 0 | AY33: =SUM(AY8:AY32) -> 0 | AZ33: =SUM(AZ8:AZ32) -> 0
D34: Indisponibilidade por dia | E34: =E35-E33 -> 9 | F34: =F35-F33 -> 10 | G34: =G35-G33 -> 10 | H34: =H35-H33 -> 10 | I34: =I35-I33 -> 8 | J34: =J35-J33 -> 10 | K34: =K35-K33 -> 10 | L34: =L35-L33 -> 10 | ... AI34: =AI35-AI33 -> 9
D35: Total de Ativos no dia | E35: =COUNTIF(E8:E30,"D")+COUNTIF(E8:E30,"T")+COUNTIF(E8:E30,"S")+COUNTIF(E8:E30,"PP")+COUNTIF(E8:E30,"PC")+COUNTIF(E8:E30,"PV")+COUNTIF(E8:E30,"SD")+COUNTIF(E8:E30,"SM")+COUNTIF(E8:E30,"F")+COUNTIF(E8:E30,"VT")+COUNTIF(E8:E30,"E")+COUNTIF(E8:E30,"RC") -> 22 | F35: =COUNTIF(F8:F30,"D")+COUNTIF(F8:F30,"T")+COUNTIF(F8:F30,"S")+COUNTIF(F8:F30,"PP")+COUNTIF(F8:F30,"PC")+COUNTIF(F8:F30,"PV")+COUNTIF(F8:F30,"SD")+COUNTIF(F8:F30,"SM")+COUNTIF(F8:F30,"F")+COUNTIF(F8:F30,"VT")+COUNTIF(F8:F30,"E")+COUNTIF(F8:F30,"RC") -> 22 | G35: =COUNTIF(G8:G30,"D")+COUNTIF(G8:G30,"T")+COUNTIF(G8:G30,"S")+COUNTIF(G8:G30,"PP")+COUNTIF(G8:G30,"PC")+COUNTIF(G8:G30,"PV")+COUNTIF(G8:G30,"SD")+COUNTIF(G8:G30,"SM")+COUNTIF(G8:G30,"F")+COUNTIF(G8:G30,"VT")+COUNTIF(G8:G30,"E")+COUNTIF(G8:G30,"RC") -> 22 | H35: =COUNTIF(H8:H30,"D")+COUNTIF(H8:H30,"T")+COUNTIF(H8:H30,"S")+COUNTIF(H8:H30,"PP")+COUNTIF(H8:H30,"PC")+COUNTIF(H8:H30,"PV")+COUNTIF(H8:H30,"SD")+COUNTIF(H8:H30,"SM")+COUNTIF(H8:H30,"F")+COUNTIF(H8:H30,"VT")+COUNTIF(H8:H30,"E")+COUNTIF(H8:H30,"RC") -> 22 | I35: =COUNTIF(I8:I30,"D")+COUNTIF(I8:I30,"T")+COUNTIF(I8:I30,"S")+COUNTIF(I8:I30,"PP")+COUNTIF(I8:I30,"PC")+COUNTIF(I8:I30,"PV")+COUNTIF(I8:I30,"SD")+COUNTIF(I8:I30,"SM")+COUNTIF(I8:I30,"F")+COUNTIF(I8:I30,"VT")+COUNTIF(I8:I30,"E")+COUNTIF(I8:I30,"RC") -> 21 | J35: =COUNTIF(J8:J30,"D")+COUNTIF(J8:J30,"T")+COUNTIF(J8:J30,"S")+COUNTIF(J8:J30,"PP")+COUNTIF(J8:J30,"PC")+COUNTIF(J8:J30,"PV")+COUNTIF(J8:J30,"SD")+COUNTIF(J8:J30,"SM")+COUNTIF(J8:J30,"F")+COUNTIF(J8:J30,"VT")+COUNTIF(J8:J30,"E")+COUNTIF(J8:J30,"RC") -> 21 | K35: =COUNTIF(K8:K30,"D")+COUNTIF(K8:K30,"T")+COUNTIF(K8:K30,"S")+COUNTIF(K8:K30,"PP")+COUNTIF(K8:K30,"PC")+COUNTIF(K8:K30,"PV")+COUNTIF(K8:K30,"SD")+COUNTIF(K8:K30,"SM")+COUNTIF(K8:K30,"F")+COUNTIF(K8:K30,"VT")+COUNTIF(K8:K30,"E")+COUNTIF(K8:K30,"RC") -> 21 | L35: =COUNTIF(L8:L30,"D")+COUNTIF(L8:L30,"T")+COUNTIF(L8:L30,"S")+COUNTIF(L8:L30,"PP")+COUNTIF(L8:L30,"PC")+COUNTIF(L8:L30,"PV")+COUNTIF(L8:L30,"SD")+COUNTIF(L8:L30,"SM")+COUNTIF(L8:L30,"F")+COUNTIF(L8:L30,"VT")+COUNTIF(L8:L30,"E")+COUNTIF(L8:L30,"RC") -> 21 | ... AI35: =COUNTIF(AI8:AI30,"D")+COUNTIF(AI8:AI30,"T")+COUNTIF(AI8:AI30,"S")+COUNTIF(AI8:AI30,"PP")+COUNTIF(AI8:AI30,"PC")+COUNTIF(AI8:AI30,"PV")+COUNTIF(AI8:AI30,"SD")+COUNTIF(AI8:AI30,"SM")+COUNTIF(AI8:AI30,"F")+COUNTIF(AI8:AI30,"VT")+COUNTIF(AI8:AI30,"E")+COUNTIF(AI8:AI30,"RC") -> 20
D36: Disponibilidade por dia em % | E36: =E33/E35 -> 0.59090909 | F36: =F33/F35 -> 0.54545455 | G36: =G33/G35 -> 0.54545455 | H36: =H33/H35 -> 0.54545455 | I36: =I33/I35 -> 0.61904762 | J36: =J33/J35 -> 0.52380952 | K36: =K33/K35 -> 0.52380952 | L36: =L33/L35 -> 0.52380952 | ... AI36: =AI33/AI35 -> 0.55 | AJ36: =SUM(AJ8:AJ32) -> 370 | AK36: =SUM(AK8:AK32) -> 300 | AL36: =SUM(AL8:AL32) -> 43 | AM36: =SUM(AM8:AM32) -> 670 | AN36: =SUM(AN8:AN32) -> 713
E37: =COUNTIF(E8:E32,"E")+COUNTIF(E8:E32,"S") -> 0 | F37: =COUNTIF(F8:F32,"E")+COUNTIF(F8:F32,"S") -> 0 | G37: =COUNTIF(G8:G32,"E")+COUNTIF(G8:G32,"S") -> 0 | H37: =COUNTIF(H8:H32,"E")+COUNTIF(H8:H32,"S") -> 0 | I37: =COUNTIF(I8:I32,"E")+COUNTIF(I8:I32,"S") -> 0 | J37: =COUNTIF(J8:J32,"E")+COUNTIF(J8:J32,"S") -> 0 | K37: =COUNTIF(K8:K32,"E")+COUNTIF(K8:K32,"S") -> 0 | L37: =COUNTIF(L8:L32,"E")+COUNTIF(L8:L32,"S") -> 0 | ... AI37: =COUNTIF(AI8:AI32,"E")+COUNTIF(AI8:AI32,"S") -> 0

Sheet DISP
D1: Meta 95% | I1: INSTRUÇÕES DE PREENCHIMENTO
I2: Disponível: D | M2: Problemas Pessoais: PP | Q2: S/ Documentação: SD | U2: Viagem Terceiro: VT | Z2: Sinalizou Desagregação: DS
I3: Trânsito: T (carregado) | M3: Manutenção: PC | Q3: S/ Motorista: SM | U3: Encostado: E(somente desengatado) | Z3: Desagregação|Troca de Fluxo: OO
I4: Sinistrado: S | M4: Manutenção Carreta: PV | Q4: Folga/Férias: F | U4: Recusa de Carga: RC
A6: REF | B6: CÓD | C6: PLACA | D6: MOTORISTA | E6: 45383 | F6: 45384 | G6: 45385 | H6: 45386 | I6: 45387 | J6: 45388 | K6: 45389 | L6: 45390 | M6: 45391 | N6: 45392 | O6: 45393 | P6: 45394 | Q6: 45395 | R6: 45396 | S6: 45397 | T6: 45398 | U6: 45399 | V6: 45400 | W6: 45401 | X6: 45402 | Y6: 45403 | Z6: 45404 | AA6: 45405 | AB6: 45406 | AC6: 45407 | AD6: 45408 | AE6: 45409 | AF6: 45410 | AG6: 45411 | AH6: 45412 | AJ6: Dias Disponíveis | AK6: Dias Insdisponíveis | AL6: "OO" | AM6: PRODUTIVIDADE EM DIAS | AN6: Total de dias no mês | AO6: Disponibilidade do Ativo | AP6: Produtividade da Operação | AR6: INDISPONIBILIDADE DE ATIVOS
AR7: PP | AS7: PC | AT7: F | AU7: SD | AV7: SM | AW7: PV | AX7: RC | AY7: S | AZ7: E
A8: 1 | B8: A18000 | C8: BAT2820 | D8: HAMILTON DE LIMA | E8: E | F8: D | G8: T | H8: PC | I8: T | J8: T | K8: T | L8: VT | M8: VT | N8: VT | O8: VT | P8: D | Q8: D | R8: F | S8: D | T8: D | U8: D | V8: D | W8: D | X8: D | Y8: F | Z8: PC | AA8: T | AJ8: =(COUNTIF(E8:AI8,"D")+COUNTIF(E8:AI8,"T")+COUNTIF(E8:AI8,"VT")) -> 18 | AK8: =(COUNTIF(E8:AI8,"pp")+COUNTIF(E8:AI8,"pc")+COUNTIF(E8:AI8,"sd")+COUNTIF(E8:AI8,"sm")+COUNTIF(E8:AI8,"f")+COUNTIF(E8:AI8,"I")+COUNTIF(E8:AI8,"PV")+COUNTIF(E8:AI8,"DS")+COUNTIF(E8:AI8,"RC")) -> 4 | AL8: =COUNTIF(E8:AI8,"OO") -> 0 | AM8: =AN8-AL8 -> 23 | AN8: =COUNTA(E8:AI8) -> 23 | AO8: =AJ8/AN8 -> 0.7826087 | AP8: =AJ8/AM8 -> 0.7826087 | AR8: =COUNTIF(E8:AK8,"PP") -> 0 | AS8: =COUNTIF(E8:AK8,"PC") -> 2 | AT8: =COUNTIF(E8:AK8,"F") -> 2 | AU8: =COUNTIF(E8:AK8,"SD") -> 0 | AV8: =COUNTIF(E8:AK8,"SM") -> 0 | AW8: =COUNTIF(F8:AL8,"PV") -> 0 | AX8: =COUNTIF(G8:AM8,"RC") -> 0 | AY8: =COUNTIF(H8:AN8,"S") -> 0 | AZ8: =COUNTIF(I8:AO8,"E") -> 0
A9: 2 | B9: A47130 | C9: MFY4I74 | D9: CLAUDINEI GONCALVES MATTOS | E9: T | F9: T | G9: T | H9: T | I9: VT | J9: VT | K9: VT | L9: VT | M9: VT | N9: VT | O9: D | P9: D | Q9: D | R9: F | S9: T | T9: T | U9: T | V9: T | W9: VT | X9: VT | Y9: VT | Z9: PC | AA9: PC | AJ9: =(COUNTIF(E9:AI9,"D")+COUNTIF(E9:AI9,"T")+COUNTIF(E9:AI9,"VT")) -> 20 | AK9: =(COUNTIF(E9:AI9,"pp")+COUNTIF(E9:AI9,"pc")+COUNTIF(E9:AI9,"sd")+COUNTIF(E9:AI9,"sm")+COUNTIF(E9:AI9,"f")+COUNTIF(E9:AI9,"I")+COUNTIF(E9:AI9,"PV")+COUNTIF(E9:AI9,"DS")+COUNTIF(E9:AI9,"RC")) -> 3 | AL9: =COUNTIF(E9:AI9,"OO") -> 0 | AM9: =AN9-AL9 -> 23 | AN9: =COUNTA(E9:AI9) -> 23 | AO9: =AJ9/AN9 -> 0.86956522 | AP9: =AJ9/AM9 -> 0.86956522 | AR9: =COUNTIF(E9:AK9,"PP") -> 0 | AS9: =COUNTIF(E9:AK9,"PC") -> 2 | AT9: =COUNTIF(E9:AK9,"F") -> 1 | AU9: =COUNTIF(E9:AK9,"SD") -> 0 | AV9: =COUNTIF(E9:AK9,"SM") -> 0 | AW9: =COUNTIF(F9:AL9,"PV") -> 0 | AX9: =COUNTIF(G9:AM9,"RC") -> 0 | AY9: =COUNTIF(H9:AN9,"S") -> 0 | AZ9: =COUNTIF(I9:AO9,"E") -> 0
A10: 3 | B10: A54920 | C10: GXS8G38 | D10: SERGIO LICHESKI | E10: PP | F10: T | G10: T | H10: T | I10: VT | J10: VT | K10: VT | L10: T | M10: T | N10: T | O10: D | P10: D | Q10: D | R10: F | S10: T | T10: T | U10: T | V10: T | W10: T | X10: T | Y10: T | Z10: T | AA10: VT | AJ10: =(COUNTIF(E10:AI10,"D")+COUNTIF(E10:AI10,"T")+COUNTIF(E10:AI10,"VT")) -> 21 | AK10: =(COUNTIF(E10:AI10,"pp")+COUNTIF(E10:AI10,"pc")+COUNTIF(E10:AI10,"sd")+COUNTIF(E10:AI10,"sm")+COUNTIF(E10:AI10,"f")+COUNTIF(E10:AI10,"I")+COUNTIF(E10:AI10,"PV")+COUNTIF(E10:AI10,"DS")+COUNTIF(E10:AI10,"RC")) -> 2 | AL10: =COUNTIF(E10:AI10,"OO") -> 0 | AM10: =AN10-AL10 -> 23 | AN10: =COUNTA(E10:AI10) -> 23 | AO10: =AJ10/AN10 -> 0.91304348 | AP10: =AJ10/AM10 -> 0.91304348 | AR10: =COUNTIF(E10:AK10,"PP") -> 1 | AS10: =COUNTIF(E10:AK10,"PC") -> 0 | AT10: =COUNTIF(E10:AK10,"F") -> 1 | AU10: =COUNTIF(E10:AK10,"SD") -> 0 | AV10: =COUNTIF(E10:AK10,"SM") -> 0 | AW10: =COUNTIF(F10:AL10,"PV") -> 0 | AX10: =COUNTIF(G10:AM10,"RC") -> 0 | AY10: =COUNTIF(H10:AN10,"S") -> 0 | AZ10: =COUNTIF(I10:AO10,"E") -> 0
A11: 4 | B11: A55160 | C11: ILI8C72 | D11: JULIANO DE LIMA SCHRAMM | E11: T | F11: T | G11: T | H11: T | I11: T | J11: T | K11: T | L11: T | M11: T | N11: T | O11: D | P11: D | Q11: D | R11: F | S11: T | T11: T | U11: T | V11: T | W11: T | X11: T | Y11: F | Z11: PC | AA11: D | AJ11: =(COUNTIF(E11:AI11,"D")+COUNTIF(E11:AI11,"T")+COUNTIF(E11:AI11,"VT")) -> 20 | AK11: =(COUNTIF(E11:AI11,"pp")+COUNTIF(E11:AI11,"pc")+COUNTIF(E11:AI11,"sd")+COUNTIF(E11:AI11,"sm")+COUNTIF(E11:AI11,"f")+COUNTIF(E11:AI11,"I")+COUNTIF(E11:AI11,"PV")+COUNTIF(E11:AI11,"DS")+COUNTIF(E11:AI11,"RC")) -> 3 | AL11: =COUNTIF(E11:AI11,"OO") -> 0 | AM11: =AN11-AL11 -> 23 | AN11: =COUNTA(E11:AI11) -> 23 | AO11: =AJ11/AN11 -> 0.86956522 | AP11: =AJ11/AM11 -> 0.86956522 | AR11: =COUNTIF(E11:AK11,"PP") -> 0 | AS11: =COUNTIF(E11:AK11,"PC") -> 1 | AT11: =COUNTIF(E11:AK11,"F") -> 2 | AU11: =COUNTIF(E11:AK11,"SD") -> 0 | AV11: =COUNTIF(E11:AK11,"SM") -> 0 | AW11: =COUNTIF(F11:AL11,"PV") -> 0 | AX11: =COUNTIF(G11:AM11,"RC") -> 0 | AY11: =COUNTIF(H11:AN11,"S") -> 0 | AZ11: =COUNTIF(I11:AO11,"E") -> 0
A12: 5 | B12: A55620 | C12: QHH0874 | D12: EMERSON | E12: E | F12: E | G12: E | H12: E | I12: E | J12: E | K12: E | L12: E | M12: E | N12: E | O12: E | P12: E | Q12: E | R12: E | S12: D | T12: D | U12: D | V12: T | W12: T | X12: T | Y12: T | Z12: T | AA12: T | AJ12: =(COUNTIF(E12:AI12,"D")+COUNTIF(E12:AI12,"T")+COUNTIF(E12:AI12,"VT")) -> 9 | AK12: =(COUNTIF(E12:AI12,"pp")+COUNTIF(E12:AI12,"pc")+COUNTIF(E12:AI12,"sd")+COUNTIF(E12:AI12,"sm")+COUNTIF(E12:AI12,"f")+COUNTIF(E12:AI12,"I")+COUNTIF(E12:AI12,"PV")+COUNTIF(E12:AI12,"DS")+COUNTIF(E12:AI12,"RC")) -> 0 | AL12: =COUNTIF(E12:AI12,"OO") -> 0 | AM12: =AN12-AL12 -> 23 | AN12: =COUNTA(E12:AI12) -> 23 | AO12: =AJ12/AN12 -> 0.39130435 | AP12: =AJ12/AM12 -> 0.39130435 | AR12: =COUNTIF(E12:AK12,"PP") -> 0 | AS12: =COUNTIF(E12:AK12,"PC") -> 0 | AT12: =COUNTIF(E12:AK12,"F") -> 0 | AU12: =COUNTIF(E12:AK12,"SD") -> 0 | AV12: =COUNTIF(E12:AK12,"SM") -> 0 | AW12: =COUNTIF(F12:AL12,"PV") -> 0 | AX12: =COUNTIF(G12:AM12,"RC") -> 0 | AY12: =COUNTIF(H12:AN12,"S") -> 0 | AZ12: =COUNTIF(I12:AO12,"E") -> 10
A13: 6 | B13: A55630 | C13: QJM9J40 | D13: - | E13: SM | F13: SM | G13: SM | H13: SM | I13: SM | J13: SM | K13: SM | L13: SM | M13: SM | N13: SM | O13: SM | P13: SM | Q13: SM | R13: SM | S13: SM | T13: SM | U13: SM | V13: SM | W13: SM | X13: SM | Y13: SM | Z13: T | AA13: T | AJ13: =(COUNTIF(E13:AI13,"D")+COUNTIF(E13:AI13,"T")+COUNTIF(E13:AI13,"VT")) -> 2 | AK13: =(COUNTIF(E13:AI13,"pp")+COUNTIF(E13:AI13,"pc")+COUNTIF(E13:AI13,"sd")+COUNTIF(E13:AI13,"sm")+COUNTIF(E13:AI13,"f")+COUNTIF(E13:AI13,"I")+COUNTIF(E13:AI13,"PV")+COUNTIF(E13:AI13,"DS")+COUNTIF(E13:AI13,"RC")) -> 21 | AL13: =COUNTIF(E13:AI13,"OO") -> 0 | AM13: =AN13-AL13 -> 23 | AN13: =COUNTA(E13:AI13) -> 23 | AO13: =AJ13/AN13 -> 0.086956522 | AP13: =AJ13/AM13 -> 0.086956522 | AR13: =COUNTIF(E13:AK13,"PP") -> 0 | AS13: =COUNTIF(E13:AK13,"PC") -> 0 | AT13: =COUNTIF(E13:AK13,"F") -> 0 | AU13: =COUNTIF(E13:AK13,"SD") -> 0 | AV13: =COUNTIF(E13:AK13,"SM") -> 21 | AW13: =COUNTIF(F13:AL13,"PV") -> 0 | AX13: =COUNTIF(G13:AM13,"RC") -> 0 | AY13: =COUNTIF(H13:AN13,"S") -> 0 | AZ13: =COUNTIF(I13:AO13,"E") -> 0
A14: 7 | B14: A55640 | C14: RLI4I24 | D14: OTAVIO PAULO DOS SANTOS | E14: T | F14: D | G14: T | H14: T | I14: T | J14: T | K14: T | L14: T | M14: T | N14: D | O14: D | P14: D | Q14: VT | R14: VT | S14: VT | T14: D | U14: D | V14: T | W14: D | X14: D | Y14: D | Z14: D | AA14: T | AJ14: =(COUNTIF(E14:AI14,"D")+COUNTIF(E14:AI14,"T")+COUNTIF(E14:AI14,"VT")) -> 23 | AK14: =(COUNTIF(E14:AI14,"pp")+COUNTIF(E14:AI14,"pc")+COUNTIF(E14:AI14,"sd")+COUNTIF(E14:AI14,"sm")+COUNTIF(E14:AI14,"f")+COUNTIF(E14:AI14,"I")+COUNTIF(E14:AI14,"PV")+COUNTIF(E14:AI14,"DS")+COUNTIF(E14:AI14,"RC")) -> 0 | AL14: =COUNTIF(E14:AI14,"OO") -> 0 | AM14: =AN14-AL14 -> 23 | AN14: =COUNTA(E14:AI14) -> 23 | AO14: =AJ14/AN14 -> 1 | AP14: =AJ14/AM14 -> 1 | AR14: =COUNTIF(E14:AK14,"PP") -> 0 | AS14: =COUNTIF(E14:AK14,"PC") -> 0 | AT14: =COUNTIF(E14:AK14,"F") -> 0 | AU14: =COUNTIF(E14:AK14,"SD") -> 0 | AV14: =COUNTIF(E14:AK14,"SM") -> 0 | AW14: =COUNTIF(F14:AL14,"PV") -> 0 | AX14: =COUNTIF(G14:AM14,"RC") -> 0 | AY14: =COUNTIF(H14:AN14,"S") -> 0 | AZ14: =COUNTIF(I14:AO14,"E") -> 0
A15: 8 | B15: A55660 | C15: RLK2J93 | D15: CLEVERTON LUIZ SANTOS | E15: D | F15: D | G15: T | H15: T | I15: T | J15: T | K15: T | L15: T | M15: T | N15: T | O15: T | P15: D | Q15: D | R15: F | S15: D | T15: T | U15: T | V15: PC | W15: PC | X15: PC | Y15: PC | Z15: PC | AA15: PC | AJ15: =(COUNTIF(E15:AI15,"D")+COUNTIF(E15:AI15,"T")+COUNTIF(E15:AI15,"VT")) -> 16 | AK15: =(COUNTIF(E15:AI15,"pp")+COUNTIF(E15:AI15,"pc")+COUNTIF(E15:AI15,"sd")+COUNTIF(E15:AI15,"sm")+COUNTIF(E15:AI15,"f")+COUNTIF(E15:AI15,"I")+COUNTIF(E15:AI15,"PV")+COUNTIF(E15:AI15,"DS")+COUNTIF(E15:AI15,"RC")) -> 7 | AL15: =COUNTIF(E15:AI15,"OO") -> 0 | AM15: =AN15-AL15 -> 23 | AN15: =COUNTA(E15:AI15) -> 23 | AO15: =AJ15/AN15 -> 0.69565217 | AP15: =AJ15/AM15 -> 0.69565217 | AR15: =COUNTIF(E15:AK15,"PP") -> 0 | AS15: =COUNTIF(E15:AK15,"PC") -> 6 | AT15: =COUNTIF(E15:AK15,"F") -> 1 | AU15: =COUNTIF(E15:AK15,"SD") -> 0 | AV15: =COUNTIF(E15:AK15,"SM") -> 0 | AW15: =COUNTIF(F15:AL15,"PV") -> 0 | AX15: =COUNTIF(G15:AM15,"RC") -> 0 | AY15: =COUNTIF(H15:AN15,"S") -> 0 | AZ15: =COUNTIF(I15:AO15,"E") -> 0
A16: 9 | B16: A55890 | C16: QHB7A24 | D16: WELLINGTON | E16: T | F16: T | G16: T | H16: T | I16: VT | J16: VT | K16: VT | L16: VT | M16: PC | N16: PC | O16: PC | P16: PC | Q16: PC | R16: PC | S16: PC | T16: PC | U16: PC | V16: PC | W16: D | X16: D | Y16: F | Z16: D | AA16: D | AJ16: =(COUNTIF(E16:AI16,"D")+COUNTIF(E16:AI16,"T")+COUNTIF(E16:AI16,"VT")) -> 12 | AK16: =(COUNTIF(E16:AI16,"pp")+COUNTIF(E16:AI16,"pc")+COUNTIF(E16:AI16,"sd")+COUNTIF(E16:AI16,"sm")+COUNTIF(E16:AI16,"f")+COUNTIF(E16:AI16,"I")+COUNTIF(E16:AI16,"PV")+COUNTIF(E16:AI16,"DS")+COUNTIF(E16:AI16,"RC")) -> 11 | AL16: =COUNTIF(E16:AI16,"OO") -> 0 | AM16: =AN16-AL16 -> 23 | AN16: =COUNTA(E16:AI16) -> 23 | AO16: =AJ16/AN16 -> 0.52173913 | AP16: =AJ16/AM16 -> 0.52173913 | AR16: =COUNTIF(E16:AK16,"PP") -> 0 | AS16: =COUNTIF(E16:AK16,"PC") -> 10 | AT16: =COUNTIF(E16:AK16,"F") -> 1 | AU16: =COUNTIF(E16:AK16,"SD") -> 0 | AV16: =COUNTIF(E16:AK16,"SM") -> 0 | AW16: =COUNTIF(F16:AL16,"PV") -> 0 | AX16: =COUNTIF(G16:AM16,"RC") -> 0 | AY16: =COUNTIF(H16:AN16,"S") -> 0 | AZ16: =COUNTIF(I16:AO16,"E") -> 0
A17: 10 | B17: A56060 | C17: MDJ8F78 | D17: - | E17: E | F17: E | G17: E | H17: E | I17: E | J17: E | K17: E | L17: E | M17: E | N17: E | O17: E | P17: E | Q17: E | R17: E | S17: T | T17: T | U17: VT | V17: VT | W17: PC | X17: PC | Y17: PC | Z17: PC | AA17: PC | AJ17: =(COUNTIF(E17:AI17,"D")+COUNTIF(E17:AI17,"T")+COUNTIF(E17:AI17,"VT")) -> 4 | AK17: =(COUNTIF(E17:AI17,"pp")+COUNTIF(E17:AI17,"pc")+COUNTIF(E17:AI17,"sd")+COUNTIF(E17:AI17,"sm")+COUNTIF(E17:AI17,"f")+COUNTIF(E17:AI17,"I")+COUNTIF(E17:AI17,"PV")+COUNTIF(E17:AI17,"DS")+COUNTIF(E17:AI17,"RC")) -> 5 | AL17: =COUNTIF(E17:AI17,"OO") -> 0 | AM17: =AN17-AL17 -> 23 | AN17: =COUNTA(E17:AI17) -> 23 | AO17: =AJ17/AN17 -> 0.17391304 | AP17: =AJ17/AM17 -> 0.17391304 | AR17: =COUNTIF(E17:AK17,"PP") -> 0 | AS17: =COUNTIF(E17:AK17,"PC") -> 5 | AT17: =COUNTIF(E17:AK17,"F") -> 0 | AU17: =COUNTIF(E17:AK17,"SD") -> 0 | AV17: =COUNTIF(E17:AK17,"SM") -> 0 | AW17: =COUNTIF(F17:AL17,"PV") -> 0 | AX17: =COUNTIF(G17:AM17,"RC") -> 0 | AY17: =COUNTIF(H17:AN17,"S") -> 0 | AZ17: =COUNTIF(I17:AO17,"E") -> 10
A18: 11 | B18: A56090 | C18: KVN1C55 | D18: LUIZ CARLOS DA SILVA | E18: E | F18: E | G18: T | H18: T | I18: T | J18: T | K18: F | L18: D | M18: T | N18: T | O18: T | P18: T | Q18: D | R18: F | S18: VT | T18: VT | U18: VT | V18: D | W18: PC | X18: PC | Y18: PC | Z18: PC | AA18: PC | AJ18: =(COUNTIF(E18:AI18,"D")+COUNTIF(E18:AI18,"T")+COUNTIF(E18:AI18,"VT")) -> 14 | AK18: =(COUNTIF(E18:AI18,"pp")+COUNTIF(E18:AI18,"pc")+COUNTIF(E18:AI18,"sd")+COUNTIF(E18:AI18,"sm")+COUNTIF(E18:AI18,"f")+COUNTIF(E18:AI18,"I")+COUNTIF(E18:AI18,"PV")+COUNTIF(E18:AI18,"DS")+COUNTIF(E18:AI18,"RC")) -> 7 | AL18: =COUNTIF(E18:AI18,"OO") -> 0 | AM18: =AN18-AL18 -> 23 | AN18: =COUNTA(E18:AI18) -> 23 | AO18: =AJ18/AN18 -> 0.60869565 | AP18: =AJ18/AM18 -> 0.60869565 | AR18: =COUNTIF(E18:AK18,"PP") -> 0 | AS18: =COUNTIF(E18:AK18,"PC") -> 5 | AT18: =COUNTIF(E18:AK18,"F") -> 2 | AU18: =COUNTIF(E18:AK18,"SD") -> 0 | AV18: =COUNTIF(E18:AK18,"SM") -> 0 | AW18: =COUNTIF(F18:AL18,"PV") -> 0 | AX18: =COUNTIF(G18:AM18,"RC") -> 0 | AY18: =COUNTIF(H18:AN18,"S") -> 0 | AZ18: =COUNTIF(I18:AO18,"E") -> 0
A19: 12 | B19: A56360 | C19: MDJ3986 | D19: EDEMIR RICARDO EIDAM | E19: T | F19: T | G19: T | H19: T | I19: T | J19: PP | K19: PP | L19: PP | M19: DS | N19: DS | O19: DS | P19: DS | Q19: DS | R19: DS | S19: DS | T19: DS | U19: DS | V19: DS | W19: DS | X19: DS | Y19: DS | Z19: DS | AA19: DS | AJ19: =(COUNTIF(E19:AI19,"D")+COUNTIF(E19:AI19,"T")+COUNTIF(E19:AI19,"VT")) -> 5 | AK19: =(COUNTIF(E19:AI19,"pp")+COUNTIF(E19:AI19,"pc")+COUNTIF(E19:AI19,"sd")+COUNTIF(E19:AI19,"sm")+COUNTIF(E19:AI19,"f")+COUNTIF(E19:AI19,"I")+COUNTIF(E19:AI19,"PV")+COUNTIF(E19:AI19,"DS")+COUNTIF(E19:AI19,"RC")) -> 18 | AL19: =COUNTIF(E19:AI19,"OO") -> 0 | AM19: =AN19-AL19 -> 23 | AN19: =COUNTA(E19:AI19) -> 23 | AO19: =AJ19/AN19 -> 0.2173913 | AP19: =AJ19/AM19 -> 0.2173913 | AR19: =COUNTIF(E19:AK19,"PP") -> 3 | AS19: =COUNTIF(E19:AK19,"PC") -> 0 | AT19: =COUNTIF(E19:AK19,"F") -> 0 | AU19: =COUNTIF(E19:AK19,"SD") -> 0 | AV19: =COUNTIF(E19:AK19,"SM") -> 0 | AW19: =COUNTIF(F19:AL19,"PV") -> 0 | AX19: =COUNTIF(G19:AM19,"RC") -> 0 | AY19: =COUNTIF(H19:AN19,"S") -> 0 | AZ19: =COUNTIF(I19:AO19,"E") -> 0
... A25: 18 | B25: A57620 | C25: MEI2020 | D25: NILO LUIZ MANARIN | E25: PP | F25: VT | G25: VT | H25: VT | I25: T | J25: T | K25: T | L25: T | M25: T | N25: T | O25: T | P25: D | Q25: D | R25: F | S25: D | T25: T | U25: T | V25: T | W25: D | X25: PC | Y25: F | Z25: T | AA25: T | AJ25: =(COUNTIF(E25:AI25,"D")+COUNTIF(E25:AI25,"T")+COUNTIF(E25:AI25,"VT")) -> 19 | AK25: =(COUNTIF(E25:AI25,"pp")+COUNTIF(E25:AI25,"pc")+COUNTIF(E25:AI25,"sd")+COUNTIF(E25:AI25,"sm")+COUNTIF(E25:AI25,"f")+COUNTIF(E25:AI25,"I")+COUNTIF(E25:AI25,"PV")+COUNTIF(E25:AI25,"DS")+COUNTIF(E25:AI25,"RC")) -> 4 | AL25: =COUNTIF(E25:AI25,"OO") -> 0 | AM25: =AN25-AL25 -> 23 | AN25: =COUNTA(E25:AI25) -> 23 | AO25: =AJ25/AN25 -> 0.82608696 | AP25: =AJ25/AM25 -> 0.82608696 | AR25: =COUNTIF(E25:AK25,"PP") -> 1 | AS25: =COUNTIF(E25:AK25,"PC") -> 1 | AT25: =COUNTIF(E25:AK25,"F") -> 2 | AU25: =COUNTIF(E25:AK25,"SD") -> 0 | AV25: =COUNTIF(E25:AK25,"SM") -> 0 | AW25: =COUNTIF(F25:AL25,"PV") -> 0 | AX25: =COUNTIF(G25:AM25,"RC") -> 0 | AY25: =COUNTIF(H25:AN25,"S") -> 0 | AZ25: =COUNTIF(I25:AO25,"E") -> 0
A26: 19 | B26: A57860 | C26: DPF3B18 | D26: CLEBER MARONI | E26: DS | F26: DS | G26: DS | H26: DS | I26: DS | J26: DS | K26: DS | L26: DS | M26: DS | N26: DS | O26: DS | P26: DS | Q26: DS | R26: DS | S26: DS | T26: DS | U26: DS | V26: DS | W26: DS | X26: DS | Y26: DS | Z26: DS | AA26: DS | AJ26: =(COUNTIF(E26:AI26,"D")+COUNTIF(E26:AI26,"T")+COUNTIF(E26:AI26,"VT")) -> 0 | AK26: =(COUNTIF(E26:AI26,"pp")+COUNTIF(E26:AI26,"pc")+COUNTIF(E26:AI26,"sd")+COUNTIF(E26:AI26,"sm")+COUNTIF(E26:AI26,"f")+COUNTIF(E26:AI26,"I")+COUNTIF(E26:AI26,"PV")+COUNTIF(E26:AI26,"DS")+COUNTIF(E26:AI26,"RC")) -> 23 | AL26: =COUNTIF(E26:AI26,"OO") -> 0 | AM26: =AN26-AL26 -> 23 | AN26: =COUNTA(E26:AI26) -> 23 | AO26: =AJ26/AN26 -> 0 | AP26: =AJ26/AM26 -> 0
A27: 20 | B27: A58340 | C27: IEU5D15 | D27: SILVIO | E27: E | F27: E | G27: E | H27: E | I27: E | J27: E | K27: E | L27: E | M27: D | N27: T | O27: T | P27: VT | Q27: VT | R27: VT | S27: VT | T27: VT | U27: F | V27: F | W27: PP | X27: PP | Y27: PP | Z27: PP | AA27: PP | AJ27: =(COUNTIF(E27:AI27,"D")+COUNTIF(E27:AI27,"T")+COUNTIF(E27:AI27,"VT")) -> 8 | AK27: =(COUNTIF(E27:AI27,"pp")+COUNTIF(E27:AI27,"pc")+COUNTIF(E27:AI27,"sd")+COUNTIF(E27:AI27,"sm")+COUNTIF(E27:AI27,"f")+COUNTIF(E27:AI27,"I")+COUNTIF(E27:AI27,"PV")+COUNTIF(E27:AI27,"DS")+COUNTIF(E27:AI27,"RC")) -> 7 | AL27: =COUNTIF(E27:AI27,"OO") -> 0 | AM27: =AN27-AL27 -> 23 | AN27: =COUNTA(E27:AI27) -> 23 | AO27: =AJ27/AN27 -> 0.34782609 | AP27: =AJ27/AM27 -> 0.34782609 | AR27: =COUNTIF(E27:AK27,"PP") -> 5 | AS27: =COUNTIF(E27:AK27,"PC") -> 0 | AT27: =COUNTIF(E27:AK27,"F") -> 2 | AU27: =COUNTIF(E27:AK27,"SD") -> 0 | AV27: =COUNTIF(E27:AK27,"SM") -> 0 | AW27: =COUNTIF(F27:AL27,"PV") -> 0 | AX27: =COUNTIF(G27:AM27,"RC") -> 0 | AY27: =COUNTIF(H27:AN27,"S") -> 0 | AZ27: =COUNTIF(I27:AO27,"E") -> 4
A28: 21 | B28: A58810 | C28: EVU7C10 | D28: MARCIO | E28: OO | F28: OO | G28: OO | H28: OO | I28: OO | J28: OO | K28: OO | L28: OO | M28: OO | N28: T | O28: T | P28: T | Q28: D | R28: F | S28: T | T28: T | U28: T | V28: T | W28: D | X28: D | Y28: F | Z28: D | AA28: D | AJ28: =(COUNTIF(E28:AI28,"D")+COUNTIF(E28:AI28,"T")+COUNTIF(E28:AI28,"VT")) -> 12 | AK28: =(COUNTIF(E28:AI28,"pp")+COUNTIF(E28:AI28,"pc")+COUNTIF(E28:AI28,"sd")+COUNTIF(E28:AI28,"sm")+COUNTIF(E28:AI28,"f")+COUNTIF(E28:AI28,"I")+COUNTIF(E28:AI28,"PV")+COUNTIF(E28:AI28,"DS")+COUNTIF(E28:AI28,"RC")) -> 2 | AL28: =COUNTIF(E28:AI28,"OO") -> 9 | AM28: =AN28-AL28 -> -9 | AN28: =AH28/AK28 -> 0 | AO28: 0.11 | AP28: =COUNTIF(C28:AI28,"PP") -> 0 | AQ28: =COUNTIF(C28:AI28,"PC") -> 0 | AR28: =COUNTIF(C28:AI28,"F") -> 2 | AS28: =COUNTIF(C28:AI28,"SD") -> 0 | AT28: =COUNTIF(C28:AI28,"SM") -> 0 | AU28: =COUNTIF(D28:AJ28,"PV") -> 0 | AV28: =COUNTIF(E28:AK28,"RC") -> 0 | AW28: =COUNTIF(F28:AL28,"S") -> 0 | AX28: =COUNTIF(G28:AM28,"E") -> 0 | AY28: 0 | AZ28: 4
A29: 22 | B29: A58840 | C29: AKE1I66 | D29: EMERSON | E29: OO | F29: OO | G29: OO | H29: OO | I29: OO | J29: OO | K29: OO | L29: OO | M29: OO | N29: OO | O29: OO | P29: D | Q29: D | R29: D | S29: D | T29: T | U29: T | V29: T | W29: VT | X29: VT | Y29: VT | Z29: VT | AA29: PC | AJ29: =(COUNTIF(E29:AI29,"D")+COUNTIF(E29:AI29,"T")+COUNTIF(E29:AI29,"VT")) -> 11 | AK29: =(COUNTIF(E29:AI29,"pp")+COUNTIF(E29:AI29,"pc")+COUNTIF(E29:AI29,"sd")+COUNTIF(E29:AI29,"sm")+COUNTIF(E29:AI29,"f")+COUNTIF(E29:AI29,"I")+COUNTIF(E29:AI29,"PV")+COUNTIF(E29:AI29,"DS")+COUNTIF(E29:AI29,"RC")) -> 1 | AL29: =COUNTIF(E29:AI29,"OO") -> 11 | AM29: =AN29-AL29 -> 12 | AN29: =COUNTA(E29:AI29) -> 23 | AO29: =AJ29/AN29 -> 0.47826087 | AP29: =AJ29/AM29 -> 0.91666667 | AR29: =COUNTIF(E29:AK29,"PP") -> 0 | AS29: =COUNTIF(E29:AK29,"PC") -> 1 | AT29: =COUNTIF(E29:AK29,"F") -> 0 | AU29: =COUNTIF(E29:AK29,"SD") -> 0 | AV29: =COUNTIF(E29:AK29,"SM") -> 0 | AW29: =COUNTIF(F29:AL29,"PV") -> 0 | AX29: =COUNTIF(G29:AM29,"RC") -> 0 | AY29: =COUNTIF(H29:AN29,"S") -> 0 | AZ29: =COUNTIF(I29:AO29,"E") -> 0
A30: 23 | B30: A58890 | C30: AOZ6A05 | D30: JACIR | E30: OO | F30: OO | G30: OO | H30: OO | I30: OO | J30: OO | K30: OO | L30: OO | M30: OO | N30: OO | O30: OO | P30: OO | Q30: OO | R30: OO | S30: D | T30: D | U30: D | V30: VT | W30: VT | X30: VT | Y30: VT | Z30: VT | AA30: VT | AJ30: =(COUNTIF(E30:AI30,"D")+COUNTIF(E30:AI30,"T")+COUNTIF(E30:AI30,"VT")) -> 9 | AK30: =(COUNTIF(E30:AI30,"pp")+COUNTIF(E30:AI30,"pc")+COUNTIF(E30:AI30,"sd")+COUNTIF(E30:AI30,"sm")+COUNTIF(E30:AI30,"f")+COUNTIF(E30:AI30,"I")+COUNTIF(E30:AI30,"PV")+COUNTIF(E30:AI30,"DS")+COUNTIF(E30:AI30,"RC")) -> 0 | AL30: =COUNTIF(E30:AI30,"OO") -> 14 | AM30: =AN30-AL30 -> 9 | AN30: =COUNTA(E30:AI30) -> 23 | AO30: =AJ30/AN30 -> 0.39130435 | AP30: =AJ30/AM30 -> 1 | AR30: =COUNTIF(E30:AK30,"PP") -> 0 | AS30: =COUNTIF(E30:AK30,"PC") -> 0 | AT30: =COUNTIF(E30:AK30,"F") -> 0 | AU30: =COUNTIF(E30:AK30,"SD") -> 0 | AV30: =COUNTIF(E30:AK30,"SM") -> 0 | AW30: =COUNTIF(F30:AL30,"PV") -> 0 | AX30: =COUNTIF(G30:AM30,"RC") -> 0 | AY30: =COUNTIF(H30:AN30,"S") -> 0 | AZ30: =COUNTIF(I30:AO30,"E") -> 0
A31: 24 | B31: A58960 | C31: OGU3G26 | D31: ANDRÉ | E31: OO | F31: OO | G31: OO | H31: OO | I31: OO | J31: OO | K31: OO | L31: OO | M31: OO | N31: OO | O31: OO | P31: OO | Q31: OO | R31: OO | S31: OO | T31: D | U31: D | V31: D | W31: T | X31: T | Y31: T | Z31: T | AA31: T | AJ31: =(COUNTIF(E31:AI31,"D")+COUNTIF(E31:AI31,"T")+COUNTIF(E31:AI31,"VT")) -> 8 | AK31: =(COUNTIF(E31:AI31,"pp")+COUNTIF(E31:AI31,"pc")+COUNTIF(E31:AI31,"sd")+COUNTIF(E31:AI31,"sm")+COUNTIF(E31:AI31,"f")+COUNTIF(E31:AI31,"I")+COUNTIF(E31:AI31,"PV")+COUNTIF(E31:AI31,"DS")+COUNTIF(E31:AI31,"RC")) -> 0 | AL31: =COUNTIF(E31:AI31,"OO") -> 15 | AM31: =AN31-AL31 -> 8 | AN31: =COUNTA(E31:AI31) -> 23 | AO31: =AJ31/AN31 -> 0.34782609 | AP31: =AJ31/AM31 -> 1 | AR31: =COUNTIF(E31:AK31,"PP") -> 0 | AS31: =COUNTIF(E31:AK31,"PC") -> 0 | AT31: =COUNTIF(E31:AK31,"F") -> 0 | AU31: =COUNTIF(E31:AK31,"SD") -> 0 | AV31: =COUNTIF(E31:AK31,"SM") -> 0 | AW31: =COUNTIF(F31:AL31,"PV") -> 0 | AX31: =COUNTIF(G31:AM31,"RC") -> 0 | AY31: =COUNTIF(H31:AN31,"S") -> 0 | AZ31: =COUNTIF(I31:AO31,"E") -> 0
A32: 25 | B32: A58890 | C32: AOZ6A05 | D32: DONIZETE | E32: OO | F32: OO | G32: OO | H32: OO | I32: OO | J32: OO | K32: OO | L32: OO | M32: OO | N32: OO | O32: OO | P32: OO | Q32: OO | R32: OO | S32: OO | T32: OO | U32: OO | V32: OO | W32: D | X32: T | Y32: T | Z32: T | AA32: T
A33: 26 | B33: A59000 | C33: MHR9H37 | D33: FABIANO | E33: OO | F33: OO | G33: OO | H33: OO | I33: OO | J33: OO | K33: OO | L33: OO | M33: OO | N33: OO | O33: OO | P33: OO | Q33: OO | R33: OO | S33: OO | T33: OO | U33: OO | V33: OO | W33: OO | X33: OO | Y33: OO | Z33: OO | AA33: D | AJ33: =(COUNTIF(E33:AI33,"D")+COUNTIF(E33:AI33,"T")+COUNTIF(E33:AI33,"VT")) -> 1 | AK33: =(COUNTIF(E33:AI33,"pp")+COUNTIF(E33:AI33,"pc")+COUNTIF(E33:AI33,"sd")+COUNTIF(E33:AI33,"sm")+COUNTIF(E33:AI33,"f")+COUNTIF(E33:AI33,"I")+COUNTIF(E33:AI33,"PV")+COUNTIF(E33:AI33,"DS")+COUNTIF(E33:AI33,"RC")) -> 0 | AL33: =COUNTIF(E33:AI33,"OO") -> 22 | AM33: =AN33-AL33 -> 1 | AN33: =COUNTA(E33:AI33) -> 23 | AO33: =AJ33/AN33 -> 0.043478261 | AP33: =AJ33/AM33 -> 1 | AR33: =COUNTIF(E33:AK33,"PP") -> 0 | AS33: =COUNTIF(E33:AK33,"PC") -> 0 | AT33: =COUNTIF(E33:AK33,"F") -> 0 | AU33: =COUNTIF(E33:AK33,"SD") -> 0 | AV33: =COUNTIF(E33:AK33,"SM") -> 0 | AW33: =COUNTIF(F33:AL33,"PV") -> 0 | AX33: =COUNTIF(G33:AM33,"RC") -> 0 | AY33: =COUNTIF(H33:AN33,"S") -> 0 | AZ33: =COUNTIF(I33:AO33,"E") -> 0
AJ34: =COUNTIF(E34:AI34,"d")+COUNTIF(E34:AI34,"t")+COUNTIF(E34:AI34,"vt")+COUNTIF(E34:AI34,"pv")+COUNTIF(E34:AI34,"RC") -> 0 | AK34: =(COUNTIF(E34:AI34,"pp")+COUNTIF(E34:AI34,"pc")+COUNTIF(E34:AI34,"sd")+COUNTIF(E34:AI34,"sm")+COUNTIF(E34:AI34,"f")) -> 0 | AL34: =COUNTIF(E34:AI34,"OO") -> 0 | AM34: =AN34-AL34 -> 0 | AN34: =COUNTA(E34:AI34) -> 0 | AR34: =COUNTIF(E34:AK34,"PP") -> 0 | AS34: =COUNTIF(E34:AK34,"PC") -> 0 | AT34: =COUNTIF(E34:AK34,"F") -> 0 | AU34: =COUNTIF(E34:AK34,"SD") -> 0 | AV34: =COUNTIF(E34:AK34,"SM") -> 0 | AW34: =COUNTIF(F34:AL34,"PV") -> 0 | AX34: =COUNTIF(G34:AM34,"RC") -> 0 | AY34: =COUNTIF(H34:AN34,"S") -> 0 | AZ34: =COUNTIF(I34:AO34,"E") -> 0
AJ35: =COUNTIF(E35:AI35,"d")+COUNTIF(E35:AI35,"t")+COUNTIF(E35:AI35,"vt")+COUNTIF(E35:AI35,"pv")+COUNTIF(E35:AI35,"RC") -> 0 | AK35: =(COUNTIF(E35:AI35,"pp")+COUNTIF(E35:AI35,"pc")+COUNTIF(E35:AI35,"sd")+COUNTIF(E35:AI35,"sm")+COUNTIF(E35:AI35,"f")) -> 0 | AL35: =COUNTIF(E35:AI35,"OO") -> 0 | AM35: =AN35-AL35 -> 0 | AN35: =COUNTA(E35:AI35) -> 0 | AR35: =COUNTIF(E35:AK35,"PP") -> 0 | AS35: =COUNTIF(E35:AK35,"PC") -> 0 | AT35: =COUNTIF(E35:AK35,"F") -> 0 | AU35: =COUNTIF(E35:AK35,"SD") -> 0 | AV35: =COUNTIF(E35:AK35,"SM") -> 0 | AW35: =COUNTIF(F35:AL35,"PV") -> 0 | AX35: =COUNTIF(G35:AM35,"RC") -> 0 | AY35: =COUNTIF(H35:AN35,"S") -> 0 | AZ35: =COUNTIF(I35:AO35,"E") -> 0
D36: Disponibilidade por dia | E36: =COUNTIF(E8:E35,"d")+COUNTIF(E8:E35,"t")+COUNTIF(E8:E35,"vt") -> 10 | F36: =COUNTIF(F8:F35,"d")+COUNTIF(F8:F35,"t")+COUNTIF(F8:F35,"vt") -> 13 | G36: =COUNTIF(G8:G35,"d")+COUNTIF(G8:G35,"t")+COUNTIF(G8:G35,"vt") -> 14 | H36: =COUNTIF(H8:H35,"d")+COUNTIF(H8:H35,"t")+COUNTIF(H8:H35,"vt") -> 13 | I36: =COUNTIF(I8:I35,"d")+COUNTIF(I8:I35,"t")+COUNTIF(I8:I35,"vt") -> 12 | J36: =COUNTIF(J8:J35,"d")+COUNTIF(J8:J35,"t")+COUNTIF(J8:J35,"vt") -> 11 | K36: =COUNTIF(K8:K35,"d")+COUNTIF(K8:K35,"t")+COUNTIF(K8:K35,"vt") -> 10 | L36: =COUNTIF(L8:L35,"d")+COUNTIF(L8:L35,"t")+COUNTIF(L8:L35,"vt") -> 12 | ... AI36: =COUNTIF(AI8:AI35,"d")+COUNTIF(AI8:AI35,"t")+COUNTIF(AI8:AI35,"vt") -> 0 | AO36: =(AJ39/AN39) -> 0.53442029 | AP36: =AJ39/AM39 -> 0.61330561 | AR36: =SUM(AR8:AR35) -> 32 | AS36: =SUM(AS8:AS35) -> 38 | AT36: =SUM(AT8:AT35) -> 18 | AU36: =SUM(AU8:AU35) -> 0 | AV36: =SUM(AV8:AV35) -> 21 | AW36: =SUM(AW8:AW35) -> 0 | AX36: =SUM(AX8:AX35) -> 0 | AY36: =SUM(AY8:AY35) -> 0 | AZ36: =SUM(AZ8:AZ35) -> 32
D37: Indisponibilidade por dia | E37: =E38-E36 -> 9 | F37: =F38-F36 -> 6 | G37: =G38-G36 -> 5 | H37: =H38-H36 -> 6 | I37: =I38-I36 -> 7 | J37: =J38-J36 -> 8 | K37: =K38-K36 -> 9 | L37: =L38-L36 -> 7 | ... AI37: =AI38-AI36 -> 0
D38: Total de Ativos no dia | E38: =COUNTIF(E8:E33,"D")+COUNTIF(E8:E33,"T")+COUNTIF(E8:E33,"S")+COUNTIF(E8:E33,"PP")+COUNTIF(E8:E33,"PC")+COUNTIF(E8:E33,"PV")+COUNTIF(E8:E33,"SD")+COUNTIF(E8:E33,"SM")+COUNTIF(E8:E33,"F")+COUNTIF(E8:E33,"VT")+COUNTIF(E8:E33,"E")+COUNTIF(E8:E33,"RC") -> 19 | F38: =COUNTIF(F8:F33,"D")+COUNTIF(F8:F33,"T")+COUNTIF(F8:F33,"S")+COUNTIF(F8:F33,"PP")+COUNTIF(F8:F33,"PC")+COUNTIF(F8:F33,"PV")+COUNTIF(F8:F33,"SD")+COUNTIF(F8:F33,"SM")+COUNTIF(F8:F33,"F")+COUNTIF(F8:F33,"VT")+COUNTIF(F8:F33,"E")+COUNTIF(F8:F33,"RC") -> 19 | G38: =COUNTIF(G8:G33,"D")+COUNTIF(G8:G33,"T")+COUNTIF(G8:G33,"S")+COUNTIF(G8:G33,"PP")+COUNTIF(G8:G33,"PC")+COUNTIF(G8:G33,"PV")+COUNTIF(G8:G33,"SD")+COUNTIF(G8:G33,"SM")+COUNTIF(G8:G33,"F")+COUNTIF(G8:G33,"VT")+COUNTIF(G8:G33,"E")+COUNTIF(G8:G33,"RC") -> 19 | H38: =COUNTIF(H8:H33,"D")+COUNTIF(H8:H33,"T")+COUNTIF(H8:H33,"S")+COUNTIF(H8:H33,"PP")+COUNTIF(H8:H33,"PC")+COUNTIF(H8:H33,"PV")+COUNTIF(H8:H33,"SD")+COUNTIF(H8:H33,"SM")+COUNTIF(H8:H33,"F")+COUNTIF(H8:H33,"VT")+COUNTIF(H8:H33,"E")+COUNTIF(H8:H33,"RC") -> 19 | I38: =COUNTIF(I8:I33,"D")+COUNTIF(I8:I33,"T")+COUNTIF(I8:I33,"S")+COUNTIF(I8:I33,"PP")+COUNTIF(I8:I33,"PC")+COUNTIF(I8:I33,"PV")+COUNTIF(I8:I33,"SD")+COUNTIF(I8:I33,"SM")+COUNTIF(I8:I33,"F")+COUNTIF(I8:I33,"VT")+COUNTIF(I8:I33,"E")+COUNTIF(I8:I33,"RC") -> 19 | J38: =COUNTIF(J8:J33,"D")+COUNTIF(J8:J33,"T")+COUNTIF(J8:J33,"S")+COUNTIF(J8:J33,"PP")+COUNTIF(J8:J33,"PC")+COUNTIF(J8:J33,"PV")+COUNTIF(J8:J33,"SD")+COUNTIF(J8:J33,"SM")+COUNTIF(J8:J33,"F")+COUNTIF(J8:J33,"VT")+COUNTIF(J8:J33,"E")+COUNTIF(J8:J33,"RC") -> 19 | K38: =COUNTIF(K8:K33,"D")+COUNTIF(K8:K33,"T")+COUNTIF(K8:K33,"S")+COUNTIF(K8:K33,"PP")+COUNTIF(K8:K33,"PC")+COUNTIF(K8:K33,"PV")+COUNTIF(K8:K33,"SD")+COUNTIF(K8:K33,"SM")+COUNTIF(K8:K33,"F")+COUNTIF(K8:K33,"VT")+COUNTIF(K8:K33,"E")+COUNTIF(K8:K33,"RC") -> 19 | L38: =COUNTIF(L8:L33,"D")+COUNTIF(L8:L33,"T")+COUNTIF(L8:L33,"S")+COUNTIF(L8:L33,"PP")+COUNTIF(L8:L33,"PC")+COUNTIF(L8:L33,"PV")+COUNTIF(L8:L33,"SD")+COUNTIF(L8:L33,"SM")+COUNTIF(L8:L33,"F")+COUNTIF(L8:L33,"VT")+COUNTIF(L8:L33,"E")+COUNTIF(L8:L33,"RC") -> 19 | ... AI38: =COUNTIF(AI8:AI33,"D")+COUNTIF(AI8:AI33,"T")+COUNTIF(AI8:AI33,"S")+COUNTIF(AI8:AI33,"PP")+COUNTIF(AI8:AI33,"PC")+COUNTIF(AI8:AI33,"PV")+COUNTIF(AI8:AI33,"SD")+COUNTIF(AI8:AI33,"SM")+COUNTIF(AI8:AI33,"F")+COUNTIF(AI8:AI33,"VT")+COUNTIF(AI8:AI33,"E")+COUNTIF(AI8:AI33,"RC") -> 0
D39: Disponibilidade por dia em % | E39: =E36/E38 -> 0.52631579 | F39: =F36/F38 -> 0.68421053 | G39: =G36/G38 -> 0.73684211 | H39: =H36/H38 -> 0.68421053 | I39: =I36/I38 -> 0.63157895 | J39: =J36/J38 -> 0.57894737 | K39: =K36/K38 -> 0.52631579 | L39: =L36/L38 -> 0.63157895 | ... AI39: =AI36/AI38 -> #DIV/0! | AJ39: =SUM(AJ8:AJ35) -> 295 | AK39: =SUM(AK8:AK35) -> 162 | AL39: =SUM(AL8:AL35) -> 71 | AM39: =SUM(AM8:AM35) -> 481 | AN39: =SUM(AN8:AN35) -> 552
E40: =COUNTIF(E8:E35,"E")+COUNTIF(E8:E35,"S") -> 6 | F40: =COUNTIF(F8:F35,"E")+COUNTIF(F8:F35,"S") -> 5 | G40: =COUNTIF(G8:G35,"E")+COUNTIF(G8:G35,"S") -> 4 | H40: =COUNTIF(H8:H35,"E")+COUNTIF(H8:H35,"S") -> 4 | I40: =COUNTIF(I8:I35,"E")+COUNTIF(I8:I35,"S") -> 4 | J40: =COUNTIF(J8:J35,"E")+COUNTIF(J8:J35,"S") -> 4 | K40: =COUNTIF(K8:K35,"E")+COUNTIF(K8:K35,"S") -> 4 | L40: =COUNTIF(L8:L35,"E")+COUNTIF(L8:L35,"S") -> 4 | ... AI40: =COUNTIF(AI8:AI35,"E")+COUNTIF(AI8:AI35,"S") -> 0

Sheet RETORNO TERCEIRO
A1: DATA | B1: AGREGADO | C1: ORIGEM | D1: DESTINO | E1: KM | F1: ROMANEIO | G1: E-MAIL | H1: EMPRESA | I1: PRODUTO | J1: FRETE EMPRESA | K1: FRETE AGREGADO
Q2: =IFERROR(R2/P2,0) -> 0
A3: FEVEREIRO | Q3: =IFERROR(R3/P3,0) -> 0
A4: 45351 | B4: A47130 | C4: POUSO ALEGRE/MG | D4: LAGES/SC | E4: 978 | F4: 1283976 | G4: OK | H4: CARSTEN | I4: GARRAFA | J4: R$ 8.316,00 | K4: 8000 | Q4: =IFERROR(R4/P4,0) -> 0
A5: 45351 | B5: A57130 | C5: PASSO FUNDO/RS | D5: CAMBÉ/PR | E5: 793 | F5: 1283980 | G5: OK | K5: 5000 | Q5: =IFERROR(R5/P5,0) -> 0
A6: 45351 | B6: A55160 | C6: CANOAS/RS | D6: IMBITUVA/PR | E6: 687 | F6: 1283970 | G6: OK | K6: R$ 4.500,00 | Q6: =IFERROR(R6/P6,0) -> 0
A7: 45352 | B7: A57700 | C7: MONTENEGRO/RS | D7: PONTA GROSSA/PR | E7: 766 | F7: 1283981 | G7: OK | H7: RTC LOGÍSTICA | I7: MDF | J7: R$ 4.562,53 | K7: 3800 | Q7: =IFERROR(R7/P7,0) -> 0
A8: 45351 | B8: A54920 | C8: BENTO GONÇALVES/RS | D8: CURITIBA/PR | E8: 613 | F8: 1284006 | G8: OK | K8: 4300 | Q8: =IFERROR(R8/P8,0) -> 0
A9: 45352 | B9: A56620 | C9: AGUDOS/SP | D9: CURITIBA/PR | E9: 500 | F9: 1283985 | G9: OK | H9: TRANSNIL | I9: CERVEJA | J9: 7158.12 | K9: 5000 | Q9: =IFERROR(R9/P9,0) -> 0
A10: 45355 | B10: A56060 | C10: GUARULHOS/SP | D10: PONTA GROSSA/PR | E10: 547 | F10: 1284097 | G10: OK | H10: JMF TRANSPORTES | I10: GARRAFA | J10: R$ 4.655,79 | K10: R$ 3.500,00 | Q10: =IFERROR(R10/P10,0) -> 0
A11: 45356 | B11: A57620 | C11: CAMPO MOURÃO/PR | D11: PINHAIS/PR | E11: 463 | H11: ANDERLE | I11: ÓLEO VEGETAL | J11: 5550 | K11: R$ 3.500,00
A12: 45364 | B12: A55160 | C12: JUNDIAÍ/SP | D12: CURITIBA/PR | F12: 1289750 | H12: MASTER CARGO | I12: PEÇAS | K12: 2100 | Q12: =IFERROR(R12/P12,0) -> 0
A13: 45364 | B13: A56540 | C13: JACUTINGA/MG | D13: PONTA GROSSA/PR | E13: 617 | H13: JMF TRANSPORTES | I13: GARRAFA | J13: 7676.67 | K13: 5100 | Q13: =IFERROR(R13/P13,0) -> 0
A14: 45365 | B14: A55160 | C14: CURITIBA/PR | D14: SANTA MARIA/RS | F14: 5254899 | I14: PAPEL | J14: 6100 | K14: 5000 | Q14: =IFERROR(R14/P14,0) -> 0
A15: 45369 | B15: A56540 | C15: ROLÂNDIA/PR | D15: CURITIBA/PR | E15: 395 | H15: POPOV TRANSP. | I15: FARINHA | K15: 3000
A16: 45371 | B16: A56370 | C16: JACUTINGA/MG | D16: PONTA GROSSA/PR | E16: 617 | F16: 1293824 | G16: OK | H16: JALOTO | I16: GARRAFA | J16: 7827.27 | K16: 5100 | Q16: =IFERROR(R16/P16,0) -> 0
A17: 45371 | B17: A47130 | C17: JACUTINGA/MG | D17: PONTA GROSSA/PR | E17: 617 | H17: JALOTO | I17: GARRAFA | J17: 7827.27 | K17: 5100 | Q17: =IFERROR(R17/P17,0) -> 0
A18: 45378 | B18: A57860 | C18: JACUTINGA/MG | D18: PONTA GROSSA/PR | E18: 617 | H18: JALOTO | I18: GARRAFA | J18: 7827.27 | K18: 5100
A19: 45383 | B19: A56620 | C19: AGUDOS/SP | D19: CURITIBA/PR | E19: 500 | H19: TRANSNIL | I19: CERVEJA | J19: 7158.12 | K19: 5000
A20: 45385 | B20: A57620 | C20: CAMPO MOURÃO/PR | D20: PINHAIS/PR | E20: 463 | H20: ANDERLE | I20: ÓLEO VEGETAL | J20: 5550 | K20: R$ 3.500,00
A21: 45386 | B21: A55890 | C21: TAPEJARA/RS | D21: CURITIBA/PR | E21: 526 | H21: HOFFMANN | I21: FORRO POLIPROPILENO | J21: 5700
A22: 45386 | B22: A56540 | C22: CANOAS/RS | D22: ITUPORANGA/SC | E22: 438 | H22: LOG TECH | I22: FERTILIZANTE | J22: 5950
A23: 45387 | B23: A54920 | C23: JACUTINGA/MG | D23: PONTA GROSSA/PR | E23: 617 | H23: TEREJOROGE | I23: GARRAFA | J23: 7827.27 | K23: 5100
A24: 45387 | B24: A47130 | C24: IGREJUNHA/RS | D24: ITAJAÍ/SC | E24: 521 | H24: COOPERCARGA | I24: CERVEJA
A25: 45390 | B25: A18000 | C25: ITAJAÍ/SC | D25: PONTA GROSSA/PR | E25: 330 | H25: RTM TRASNPORTE | I25: POLITÍLENO | K25: 3000
A26: 45390 | B26: A47130 | C26: BLUMENAU/SC | D26: PONTA GROSSA/PR | E26: 325 | H26: TDM | I26: GARRAFA | J26: 4900 | K26: 3500
A27: 45398 | B27: A58340 | C27: JAGUARIUNA/SP | D27: SAPUCAIA DO SUL/RS | H27: CONRADO TRANSPORTES | I27: REFRIGERANTE | J27: 7435.82
A28: 45399 | B28: A56060 | C28: SUMARÉ/SP | D28: MARINGÁ/PR | E28: 588 | H28: 3M DO BRASIL LTDA
A29: 45400 | B29: A56540 | C29: POUSO ALEGRE/MG | D29: IÇARA/SC | H29: LEALES LOG TRANSPORTES | I29: UNILEVER | K29: 5000
A30: 45399 | B30: A56750 | C30: SÃO PAULO/SP | D30: PARANAGUÁ
A31: 45400 | B31: A58890 | C31: PONTA GROSSA/PR | D31: LONDRINA/PR | H31: Traspotadora Eduardo Justus Olegario LTDA | I31: DRYWALL | J31: 3950 | K31: 3000
A32: 45400 | B32: A56090 | C32: PONTA GROSSA/PR | D32: JOINVILLE/SC | J32: 2600
A33: 45401 | B33: A58840 | C33: SÃO JOSE/SC | D33: CURITIBA/PR | H33: ROTTA RECICLAVEIS | I33: GARRAFA PET | K33: 1800
A34: 45402 | B34: A58890 | C34: LONDRINA/PR | D34: CURITIBA/PR
A35: 45405 | B35: A56540 | C35: TUBARÃO/SC | D35: CURITIBA/PR | E35: 425
A36: 45407 | B36: A18000 | C36: ITAJAÍ/SC | D36: SÃO JOSÉ DOS PINHAIS/PR | I36: PALLET
A37: 45418 | B37: A59080 | C37: TIJUCAS/SC | D37: IRATI/PR | H37: Industria de papel são João Batista | I37: PAPEL VELHO | K37: 3200
A38: 45420 | B38: A59090 | C38: BRAGANÇA PAULISTA/SP | D38: MORRETES | E38: PR | H38: Papelão | I38: Sucapel | K38: 3360

Sheet Disponibilidade Guararapes
A1: AGREGADO | B1: 1 | C1: 2 | D1: 3 | E1: 4 | F1: 5 | G1: 6 | H1: 7 | I1: 8 | J1: 9 | K1: 10 | L1: 11 | M1: 12 | N1: 13 | O1: 14 | P1: 15 | Q1: 16 | R1: 17 | S1: 18 | T1: 19 | U1: 20 | V1: 21 | W1: 22 | X1: 23 | Y1: 24 | Z1: 25 | AA1: 26 | AB1: 27 | AC1: 28 | AD1: 29 | AE1: 30 | AF1: 31 | AG1: DISPONÍVEIS | AH1: INDISPONÍVEIS | AI1: DISPONIBILIDADE
A2: A59500 | B2: D | C2: D | D2: D | E2: D | F2: D | G2: D | H2: D | I2: I | J2: I | K2: I | L2: D | M2: D | N2: D | O2: D | P2: D | Q2: I | R2: I | S2: I | T2: I | U2: I | V2: I | W2: I | X2: I | Y2: I | Z2: I | AA2: I | AB2: I | AC2: I | AD2: I | AE2: I | AF2: I | AG2: =COUNTIF(B2:AF2,"D") -> 12 | AH2: =COUNTIF(B2:AF2,"I") -> 19 | AI2: =AG2/31 -> 0.38709677
A3: A59570 | B3: I | C3: I | D3: I | E3: I | F3: I | G3: I | H3: I | I3: I | J3: I | K3: I | L3: I | M3: I | N3: I | O3: I | P3: I | Q3: D | R3: D | S3: I | T3: I | U3: I | V3: I | W3: I | X3: D | Y3: D | Z3: I | AA3: I | AB3: D | AC3: D | AD3: D | AE3: D | AF3: I | AG3: =COUNTIF(B3:AF3,"D") -> 8 | AH3: =COUNTIF(B3:AF3,"I") -> 23 | AI3: =AG3/31 -> 0.25806452
A4: A59600 | B4: D | C4: D | D4: D | E4: D | F4: D | G4: D | H4: D | I4: D | J4: D | K4: D | L4: D | M4: D | N4: D | O4: D | P4: D | Q4: D | R4: D | S4: D | T4: D | U4: D | V4: D | W4: D | X4: D | Y4: I | Z4: I | AA4: D | AB4: D | AC4: D | AD4: D | AE4: D | AF4: I | AG4: =COUNTIF(B4:AF4,"D") -> 28 | AH4: =COUNTIF(B4:AF4,"I") -> 3 | AI4: =AG4/31 -> 0.90322581
A5: A58580 | B5: I | C5: I | D5: I | E5: I | F5: I | G5: I | H5: I | I5: I | J5: I | K5: I | L5: I | M5: I | N5: I | O5: I | P5: I | Q5: I | R5: I | S5: I | T5: I | U5: I | V5: I | W5: I | X5: I | Y5: I | Z5: I | AA5: I | AB5: I | AC5: I | AD5: I | AE5: I | AF5: I | AG5: =COUNTIF(B5:AF5,"D") -> 0 | AH5: =COUNTIF(B5:AF5,"I") -> 31 | AI5: =AG5/31 -> 0
A6: A59590 | B6: I | C6: I | D6: I | E6: I | F6: I | G6: I | H6: I | I6: I | J6: I | K6: I | L6: I | M6: I | N6: I | O6: I | P6: I | Q6: I | R6: I | S6: I | T6: I | U6: I | V6: I | W6: I | X6: I | Y6: I | Z6: I | AA6: I | AB6: I | AC6: I | AD6: I | AE6: I | AF6: I | AG6: =COUNTIF(B6:AF6,"D") -> 0 | AH6: =COUNTIF(B6:AF6,"I") -> 31 | AI6: =AG6/31 -> 0
A7: A55630 | B7: I | C7: I | D7: I | E7: I | F7: I | G7: I | H7: I | I7: I | J7: I | K7: I | L7: I | M7: I | N7: I | O7: I | P7: I | Q7: D | R7: D | S7: I | T7: I | U7: I | V7: D | W7: D | X7: D | Y7: D | Z7: D | AA7: D | AB7: D | AC7: D | AD7: D | AE7: D | AF7: I | AG7: =COUNTIF(B7:AF7,"D") -> 12 | AH7: =COUNTIF(B7:AF7,"I") -> 19 | AI7: =AG7/31 -> 0.38709677
A8: A55640 | B8: I | C8: I | D8: I | E8: I | F8: I | G8: I | H8: I | I8: I | J8: I | K8: I | L8: I | M8: I | N8: I | O8: I | P8: I | Q8: I | R8: I | S8: D | T8: D | U8: D | V8: D | W8: D | X8: I | Y8: I | Z8: D | AA8: D | AB8: D | AC8: D | AD8: D | AE8: D | AF8: I | AG8: =COUNTIF(B8:AF8,"D") -> 11 | AH8: =COUNTIF(B8:AF8,"I") -> 20 | AI8: =AG8/31 -> 0.35483871
A9: A60050 | B9: I | C9: I | D9: I | E9: I | F9: D | G9: D | H9: D | I9: D | J9: D | K9: D | L9: D | M9: D | N9: D | O9: D | P9: D | Q9: D | R9: D | S9: I | T9: I | U9: I | V9: I | W9: I | X9: I | Y9: I | Z9: I | AA9: I | AB9: I | AC9: I | AD9: I | AE9: I | AF9: I | AG9: =COUNTIF(B9:AF9,"D") -> 13 | AH9: =COUNTIF(B9:AF9,"I") -> 18 | AI9: =AG9/31 -> 0.41935484
A10: A59860 | B10: I | C10: I | D10: I | E10: I | F10: I | G10: I | H10: I | I10: I | J10: I | K10: I | L10: I | M10: I | N10: I | O10: I | P10: I | Q10: I | R10: I | S10: I | T10: I | U10: I | V10: I | W10: I | X10: I | Y10: I | Z10: I | AA10: I | AB10: I | AC10: I | AD10: I | AE10: I | AF10: I | AG10: =COUNTIF(B10:AF10,"D") -> 0 | AH10: =COUNTIF(B10:AF10,"I") -> 31 | AI10: =AG10/31 -> 0
A11: A60060 | B11: I | C11: I | D11: I | E11: I | F11: I | G11: I | H11: I | I11: I | J11: D | K11: D | L11: D | M11: D | N11: D | O11: D | P11: D | Q11: D | R11: D | S11: I | T11: I | U11: D | V11: D | W11: D | X11: D | Y11: D | Z11: I | AA11: I | AB11: I | AC11: I | AD11: I | AE11: I | AF11: I | AG11: =COUNTIF(B11:AF11,"D") -> 14 | AH11: =COUNTIF(B11:AF11,"I") -> 17 | AI11: =AG11/31 -> 0.4516129
A12: A60220 | B12: I | C12: I | D12: I | E12: I | F12: I | G12: I | H12: I | I12: I | J12: I | K12: I | L12: I | M12: I | N12: I | O12: I | P12: I | Q12: I | R12: D | S12: D | T12: D | U12: D | V12: D | W12: D | X12: D | Y12: D | Z12: D | AA12: D | AB12: D | AC12: D | AD12: D | AE12: D | AF12: I | AG12: =COUNTIF(B12:AF12,"D") -> 14 | AH12: =COUNTIF(B12:AF12,"I") -> 17 | AI12: =AG12/31 -> 0.4516129
M14: =COUNTIF(B2:P12,"D") -> 45 | P14: =COUNTIF(Q2:AF12,"D") -> 67
A21: AGREGADO | B21: 1 | C21: 2 | D21: 3 | E21: 4 | F21: 5 | G21: 6 | H21: 7 | I21: 8 | J21: 9 | K21: 10 | L21: 11 | M21: 12 | N21: 13 | O21: 14 | P21: 15 | Q21: 16 | R21: 17 | S21: 18 | T21: 19 | U21: 20 | V21: 21 | W21: 22 | X21: 23 | Y21: 24 | Z21: 25 | AA21: 26 | AB21: 27 | AC21: 28 | AD21: 29 | AE21: 30 | AF21: 31 | AG21: DISPONÍVEIS | AH21: INDISPONÍVEIS | AI21: DISPONIBILIDADE
